Workbook

Sheet Dashboard
A1: MAISON 41 — COCKPIT QUOTIDIEN
A2: Conserverie artisanale · Bocaux Weck · 0 Additif · 0 Nitrite · Depuis 2023
A4: VISION DU JOUR
A5: Production du jour | E5: Marches / evenements du jour
A6: Lots prevus, autoclaves, temps estime (feuille Planning) | E6: Marches, livraisons, evenements (feuille Marches)
A8: INDICATEURS CLES
A9: CA mois en cours | B9: =IFERROR(SUMPRODUCT((MONTH(Ventes!A5:A504)=MONTH(TODAY()))*(YEAR(Ventes!A5:A504)=YEAR(TODAY()))*Ventes!G5:G504),0) -> #ERROR! | C9: EUR | E9: Lots planifies 7j | F9: =IFERROR(COUNTIFS(Planning!A4:A303,">="&TODAY(),Planning!A4:A303,"<="&TODAY()+7),0) -> #ERROR! | G9: lots
A10: Bocaux en stock | B10: =IFERROR(SUMIF(Stock!D208:D262,"<>",Stock!D208:D262),0) -> #ERROR! | C10: boc. | E10: Recettes actives | F10: =IFERROR(COUNTIF(Recettes!H4:H32,"Actif"),0) -> #ERROR! | G10: rec.
A11: MP en rupture | B11: =IFERROR(COUNTIF(Stock!G6:G205,"Rupture"),0) -> #ERROR! | C11: MP | E11: Charges fixes mensuelles | F11: =IFERROR(SUMIF(Charges!B4:B16,"Fixe",Charges!C4:C16),0) -> #ERROR! | G11: EUR
A13: ACTIONS RAPIDES
A14: Assistant Production | B14: Priorites de production, lots a lancer
A15: Achats a lancer | B15: MP a commander, quantites, fournisseurs
A16: Marches a preparer | B16: Stock recommande, prevision CA
A17: HACCP du jour | B17: Enregistrements, controles, non-conformites
A18: DDM a surveiller | B18: Lots proches DDM, actions
A19: Pilotage financier | B19: Seuil de rentabilite, marge, tresorerie
A21: NAVIGATION
A22: Referentiels | B22: MP Referentiel · Recettes · Detail Recettes · Prix Vente
A23: Operations | B23: Planning · Stock · Fiche Lot · Ventes · Marches
A24: Gestion | B24: Charges · Previsionnel · Compta
A25: Qualite | B25: HACCP · Plan Nettoyage · DDM · Autoclaves
A26: Pilotage | B26: Assistant Production · Assistant Decisions · CRM

Sheet AuditLog
A1: Horodatage | B1: Utilisateur | C1: Rôle | D1: Action | E1: Détail
A2: 46114.591 | B2: Alex | C2: ? | D2: saveLotProduction | E2: {"numLot":"LOT-20260402-003","recette":"Rillettes du Chef"}

Sheet MP Référentiel
A4: Code MP | B4: Designation | C4: Categorie | D4: Unite | E4: Fournisseur | F4: Prix EUR/U | G4: Date MAJ | H4: Stock min | I4: Allergenes | J4: Notes

Sheet Traçabilité Lots
A1: N° Lot | B1: Date Production | C1: Recette | D1: Opérateur | E1: Code MP | F1: Désignation MP | G1: Qté consommée (kg) | H1: N° Lot Fournisseur | I1: Fournisseur | J1: DLC Fournisseur | K1: Date Réception | L1: URL Photo Étiquette | M1: URL Dossier Drive

Sheet Avoirs
A4: Date | B4: N° Avoir | C4: Type | D4: Client | E4: Recette | F4: Gamme | G4: Format | H4: Qte | I4: PU HT | J4: Remise % | K4: Net HT | L4: TVA EUR | M4: TTC EUR | N4: Motif

Sheet Clients
A2: ID | B2: Prénom | C2: Nom | D2: Email | E2: Téléphone | F2: Adresse | G2: Département | H2: Canal | I2: Statut Ulule | J2: Vote recette | K2: Nb achats | L2: CA total | M2: Type | N2: Notes

Sheet Parc Machine
A1: ID | B1: Nom | C1: Type | D1: Cap_RR290 | E1: Cap_RR580 | F1: Cap_RR850 | G1: Cap_W050 | H1: Cap_W080 | I1: Debit_kg_h | J1: Conso_kW | K1: Statut | L1: Notes

Sheet Utilisateurs
A1: PIN | B1: Nom | C1: Role | D1: Planning | E1: Calculateur | F1: Logistique | G1: Machines | H1: Vente | I1: Reporting | J1: Doc | K1: Admin
A2: 2929 | B2: Alex | C2: Gérant | D2: TRUE | E2: TRUE | F2: TRUE | G2: TRUE | H2: TRUE | I2: TRUE | J2: TRUE | K2: TRUE
A3: 1111 | B3: Jean | C3: Ouvrier | D3: TRUE | E3: TRUE | F3: FALSE | G3: TRUE | H3: FALSE | I3: FALSE | J3: TRUE | K3: FALSE
A4: 2222 | B4: Julie | C4: Vendeuse | D4: FALSE | E4: FALSE | F4: FALSE | G4: FALSE | H4: TRUE | I4: FALSE | J4: TRUE | K4: FALSE
A5: 0 | B5: Expert | C5: Compta | D5: FALSE | E5: FALSE | F5: FALSE | G5: FALSE | H5: FALSE | I5: TRUE | J5: FALSE | K5: FALSE

Sheet 👤 Clients
A1: ID Client | B1: Prénom | C1: Nom | D1: Email | E1: Téléphone | F1: Adresse | G1: Département | H1: Canal origine | I1: Niveau Ulule | J1: Vote recette | K1: Nb commandes | L1: CA total TTC | M1: Dernière commande | N1: Date création | O1: Source | P1: Notes | Q1: Sync

Sheet Guide Utilisation
A1: MAISON 41 — GUIDE D'UTILISATION DE L'ERP — Mode d'emploi de toutes les feuilles
A3: REFERENTIELS (ne pas supprimer)
A4: Feuille | B4: Quand | C4: Comment / Ce qu'il faut saisir | D4: Point d'attention
A5: MP Referentiel | B5: Saisie annuelle | C5: Mettre a jour le prix col F (jaune) quand le fournisseur change · Tout se recalcule | D5: Saisir prix en EUR/kg
A6: Recettes | B6: Creation + validation | C6: Renseigner allergenes (cols M-R) et valeurs nutritionnelles (cols S-W) · Statut = Actif pour apparaitre dans Planning | D6: Ne modifier que si recette change
A7: Referentiel Gamme | B7: Lecture seule | C7: Nomenclature complete des references · Codes departements · Formats | D7: Reference officielle
A9: PRODUCTION (flux quotidien)
A10: Feuille | B10: Quand | C10: Comment / Ce qu'il faut saisir | D10: Point d'attention
A11: Planning | B11: Chaque jour de production | C11: Renseigner Date + Recette + Autoclave + Fraction → Nb bocaux se calcule · Passer en "En production" → Fiche Lot creee auto | D11: Statut = Termine declenche DDM
A12: Fiche Lot | B12: Pendant la production | C12: Completer T° coeur (CCP1 obligatoire) + Nb bocaux reels + Observations · Statut = Valide → Stock mis a jour auto | D12: ARCHIVER 5 ANS apres DDM
A13: DDM | B13: Automatique | C13: Saisir N° lot col A → Recette, Format, DDM se remplissent depuis Fiche Lot · Surveiller les dates proches | D13: Priorite vente si < 30j
A14: Historique Lots | B14: Bilan | C14: Saisir N° lot → tout se remplit depuis Fiche Lot · Completer CA reel + cout reel apres vente | D14: Bilan mensuel
A16: COMMERCIAL (flux ventes)
A17: Feuille | B17: Quand | C17: Comment / Ce qu'il faut saisir | D17: Point d'attention
A18: Ventes | B18: Apres chaque vente | C18: Saisir date + canal + recette + format + qte + prix · La TVA et le HT se calculent depuis Config | D18: Source KPI Dashboard
A19: Bons de Commande | B19: Avant livraison B2B | C19: Saisir client + produits · Statut "Confirme" → lot Planning cree · Statut "Livre" → Vente enregistree auto | D19: N° facture = N° BC
A20: CRM | B20: Apres chaque contact | C20: Enrichir fiche client apres chaque vente · Alerte orange si B2B > 90j sans commande | D20: Source picking Ulule
A21: CE & Associations | B21: Oct-Dec | C21: Saisir commandes collectives · Remise calculee auto selon quantite | D21: Peak Oct-Dec
A22: Marches | B22: Avant chaque marche | C22: Renseigner date + lieu + CA previsionnel · Completer CA reel apres le marche | D22: Analyse canal B2C
A24: FINANCE
A25: Feuille | B25: Quand | C25: Comment / Ce qu'il faut saisir | D25: Point d'attention
A26: Prix Vente | B26: A chaque changement | C26: Saisir uniquement col C (jaune) = TTC B2C x1 · Tout le reste se calcule | D26: PVC conseille en note survol
A27: Cout de Revient | B27: Automatique | C27: Se recalcule quand MP Referentiel ou Detail Recettes change · Verifier marge cible Config | D27: Marge < 30% = danger
A28: Previsionnel | B28: Mensuel | C28: Mettre a jour Tresorerie 13 semaines · Comparer reel vs previsionnel | D28: Presenter a la banque
A29: Compta | B29: Mensuel | C29: Saisir toutes les operations · Categories pour export expert-comptable | D29: Export CSV mensuel
A31: DDPP & QUALITE (obligations legales)
A32: Feuille | B32: Quand | C32: Comment / Ce qu'il faut saisir | D32: Point d'attention
A33: HACCP | B33: Chaque controle | C33: Enregistrer chaque point de controle · Statut NC → Action corrective obligatoire | D33: 5 ans archive minimum
A34: Plan Nettoyage | B34: Chaque nettoyage | C34: Cocher les zones nettoyees · Produit utilise · Signature operateur | D34: Controle DDPP
A35: Reclamations | B35: A chaque reclamation | C35: Enregistrer dans les 24h · Action corrective obligatoire · Critique → contacter DDPP | D35: Delai reponse J+1 si Critique
A36: Fiches Techniques | B36: A valider | C36: Completer allergenes + nutritionnels + bareme par recette · Document officiel INCO | D36: Presenter a tout controle
A37: DUERP | B37: Annuel | C37: Evaluer les risques (PxG) · Actions correctives si >=9 · Signer et dater | D37: Mise a jour annuelle obligatoire
A38: PMS | B38: Presenter a DDPP | C38: Document de reference sanitaire · Mettre a jour si procedure change | D38: Avant toute ouverture officielle

Sheet MP Referentiel
A1: MAISON 41 — REFERENTIEL MATIERES PREMIERES — Source de verite
A2: Colonne F (JAUNE) = PRIX A RENSEIGNER — Toutes les recettes se recalculent
A3: Code MP · Designation · Categorie · Unite · Fournisseur · Prix (JAUNE) · Date MaJ · Note · Recettes · Sync
A4: Code MP | B4: Designation | C4: Categorie | D4: Unite | E4: Fournisseur | F4: PRIX SAISIR ICI | G4: Date MaJ | H4: Note qualite | I4: Nb recettes | J4: Sync App | K4: Prix precedent | L4: Variation %
A5: MP01 | B5: Porc epaule desossee | C5: Viande porc | D5: kg | F5: 8.5 | G5: Mar 2026 | L5: =IFERROR(IF(OR(F5="",K5=""),"",((F5-K5)/K5)*100),"") -> #ERROR!
A6: MP02 | B6: Porc gorge (gras dur) | C6: Viande porc | D6: kg | F6: 5.5 | G6: Mar 2026 | L6: =IFERROR(IF(OR(F6="",K6=""),"",((F6-K6)/K6)*100),"") -> #ERROR!
A7: MP03 | B7: Porc foie | C7: Viande porc | D7: kg | F7: 4.5 | G7: Mar 2026 | L7: =IFERROR(IF(OR(F7="",K7=""),"",((F7-K7)/K7)*100),"") -> #ERROR!
A8: MP04 | B8: Porc couenne | C8: Viande porc | D8: kg | F8: 2.8 | G8: Mar 2026 | L8: =IFERROR(IF(OR(F8="",K8=""),"",((F8-K8)/K8)*100),"") -> #ERROR!
A9: MP05 | B9: Lardons nature sans nitrite | C9: Viande porc | D9: kg | F9: 14 | G9: Mar 2026 | L9: =IFERROR(IF(OR(F9="",K9=""),"",((F9-K9)/K9)*100),"") -> #ERROR!
A10: MP06 | B10: Saucisses Toulouse artisanales | C10: Charcuterie | D10: kg | F10: 13.5 | G10: Mar 2026 | L10: =IFERROR(IF(OR(F10="",K10=""),"",((F10-K10)/K10)*100),"") -> #ERROR!
A11: MP07 | B11: Boeuf paleron | C11: Viande boeuf | D11: kg | F11: 14.5 | G11: Mar 2026 | L11: =IFERROR(IF(OR(F11="",K11=""),"",((F11-K11)/K11)*100),"") -> #ERROR!
A12: MP08 | B12: Os a moelle boeuf | C12: Viande boeuf | D12: kg | F12: 5.5 | G12: Mar 2026 | L12: =IFERROR(IF(OR(F12="",K12=""),"",((F12-K12)/K12)*100),"") -> #ERROR!
A13: MP09 | B13: Ail frais | C13: Legumes | D13: kg | F13: 6.5 | G13: Mar 2026 | L13: =IFERROR(IF(OR(F13="",K13=""),"",((F13-K13)/K13)*100),"") -> #ERROR!
A14: MP10 | B14: Carotte | C14: Legumes | D14: kg | F14: 1.2 | G14: Mar 2026 | L14: =IFERROR(IF(OR(F14="",K14=""),"",((F14-K14)/K14)*100),"") -> #ERROR!
A15: MP11 | B15: Celeri branche | C15: Legumes | D15: kg | F15: 1.8 | G15: Mar 2026 | L15: =IFERROR(IF(OR(F15="",K15=""),"",((F15-K15)/K15)*100),"") -> #ERROR!
A16: MP12 | B16: Celeri-rave | C16: Legumes | D16: kg | F16: 2 | G16: Mar 2026 | L16: =IFERROR(IF(OR(F16="",K16=""),"",((F16-K16)/K16)*100),"") -> #ERROR!
... A77: MP73 | B77: Bocal Weck W60-160 + joint | C77: Consommable | D77: u | F77: 1.1 | G77: Mar 2026 | L77: =IFERROR(IF(OR(F77="",K77=""),"",((F77-K77)/K77)*100),"") -> #ERROR!
A78: Gorge | B78: gorge de porc | C78: Viande | D78: g | E78: cooperl | F78: 2 | G78: Mar 2026
A79: AJOUTER ICI — Prochain code : MP74
A80: MP58 | B80: Ricard | C80: Alcools | D80: kg | E80: gms | F80: 15.45 | G80: Apr 2026
A81: MP74 | B81: Ricard | C81: Alcools | D81: kg | E81: gms | F81: 15.51 | G81: Apr 2026

Sheet Recettes
A1: MAISON 41 — REFERENTIEL RECETTES
A2: 4 gammes · Recettes actives · Voir "Detail Recettes" pour les ingredients
A3: Ref. | B3: Nom commercial | C3: Gamme | D3: Format principal | E3: Rendement % | F3: Batch kg MP | G3: Temps (h) | H3: Statut | I3: Nb ing. | J3: Cout MP/kg (EUR) | K3: Date creation | L3: Gluten | M3: Oeufs | N3: Lait | O3: Sulfites | P3: Moutarde | Q3: Autres allerg. | R3: kcal/100g | S3: Prot. g/100g | T3: Lip. g/100g | U3: Gluc. g/100g | V3: Sel g/100g | W3: Sync App
A4: RC | B4: Rillettes du Chef | C4: Rillettes | D4: RR100-580 | E4: 85 | F4: 5 | G4: 3.5 | H4: Actif | I4: =IFERROR(COUNTIF('Detail Recettes'!A:A,"RC"),"") -> #ERROR! | J4: =IFERROR(SUMPRODUCT(('Detail Recettes'!A:A="RC")*'Detail Recettes'!D:D*IFERROR(INDEX('MP Referentiel'!F:F,MATCH('Detail Recettes'!B:B,'MP Referentiel'!A:A,0)),0))/5,"") -> #ERROR! | K4: Mar 2026 | L4: OK
A5: PC | B5: Pate du Chef | C5: Pates & Terrines | D5: RR100-580 | E5: 88 | F5: 5 | G5: 4 | H5: Actif | I5: =IFERROR(COUNTIF('Detail Recettes'!A:A,"PC"),"") -> #ERROR! | J5: =IFERROR(SUMPRODUCT(('Detail Recettes'!A:A="PC")*'Detail Recettes'!D:D*IFERROR(INDEX('MP Referentiel'!F:F,MATCH('Detail Recettes'!B:B,'MP Referentiel'!A:A,0)),0))/5,"") -> #ERROR! | K5: Mar 2026 | L5: OK
A6: MC | B6: Mousse du Chef | C6: Mousses | D6: RR100-370 | E6: 82 | F6: 4 | G6: 2.5 | H6: Actif | I6: =IFERROR(COUNTIF('Detail Recettes'!A:A,"MC"),"") -> #ERROR! | J6: =IFERROR(SUMPRODUCT(('Detail Recettes'!A:A="MC")*'Detail Recettes'!D:D*IFERROR(INDEX('MP Referentiel'!F:F,MATCH('Detail Recettes'!B:B,'MP Referentiel'!A:A,0)),0))/4,"") -> #ERROR! | K6: Mar 2026 | L6: OK
A7: TC | B7: Plat Traiteur du Chef | C7: Plats cuisines | D7: RR100-850 | E7: 80 | F7: 6 | G7: 3.5 | H7: Actif | I7: =IFERROR(COUNTIF('Detail Recettes'!A:A,"TC"),"") -> #ERROR! | J7: =IFERROR(SUMPRODUCT(('Detail Recettes'!A:A="TC")*'Detail Recettes'!D:D*IFERROR(INDEX('MP Referentiel'!F:F,MATCH('Detail Recettes'!B:B,'MP Referentiel'!A:A,0)),0))/6,"") -> #ERROR! | K7: Mar 2026 | L7: OK
A8: DC | B8: Dessert du Chef - Creme Vanill | C8: Desserts appertises | D8: RR100-290 | E8: 95 | F8: 4 | G8: 2 | H8: Actif | I8: =IFERROR(COUNTIF('Detail Recettes'!A:A,"DC"),"") -> #ERROR! | J8: =IFERROR(SUMPRODUCT(('Detail Recettes'!A:A="DC")*'Detail Recettes'!D:D*IFERROR(INDEX('MP Referentiel'!F:F,MATCH('Detail Recettes'!B:B,'MP Referentiel'!A:A,0)),0))/4,"") -> #ERROR! | K8: Mar 2026 | L8: OK
A9: P01 | B9: Pate de Campagne Maison 41 | C9: Pates & Terrines | D9: RR100-580 | E9: 88 | F9: 5 | G9: 4 | H9: Actif | I9: =IFERROR(COUNTIF('Detail Recettes'!A:A,"P01"),"") -> #ERROR! | J9: =IFERROR(SUMPRODUCT(('Detail Recettes'!A:A="P01")*'Detail Recettes'!D:D*IFERROR(INDEX('MP Referentiel'!F:F,MATCH('Detail Recettes'!B:B,'MP Referentiel'!A:A,0)),0))/5,"") -> #ERROR! | K9: Mar 2026 | L9: OK
A10: P02 | B10: Pate Echalote & Thym Citron | C10: Pates & Terrines | D10: RR100-580 | E10: 88 | F10: 5 | G10: 4 | H10: Actif | I10: =IFERROR(COUNTIF('Detail Recettes'!A:A,"P02"),"") -> #ERROR! | J10: =IFERROR(SUMPRODUCT(('Detail Recettes'!A:A="P02")*'Detail Recettes'!D:D*IFERROR(INDEX('MP Referentiel'!F:F,MATCH('Detail Recettes'!B:B,'MP Referentiel'!A:A,0)),0))/5,"") -> #ERROR! | K10: Mar 2026 | L10: OK
A11: P03 | B11: Pate Basque Piment d'Espelette | C11: Pates & Terrines | D11: RR100-580 | E11: 87 | F11: 5 | G11: 4.5 | H11: Actif | I11: =IFERROR(COUNTIF('Detail Recettes'!A:A,"P03"),"") -> #ERROR! | J11: =IFERROR(SUMPRODUCT(('Detail Recettes'!A:A="P03")*'Detail Recettes'!D:D*IFERROR(INDEX('MP Referentiel'!F:F,MATCH('Detail Recettes'!B:B,'MP Referentiel'!A:A,0)),0))/5,"") -> #ERROR! | K11: Mar 2026 | L11: OK
A12: P04 | B12: Pate Pleurotes & Persil Plat | C12: Pates & Terrines | D12: RR100-580 | E12: 86 | F12: 5 | G12: 4.5 | H12: Actif | I12: =IFERROR(COUNTIF('Detail Recettes'!A:A,"P04"),"") -> #ERROR! | J12: =IFERROR(SUMPRODUCT(('Detail Recettes'!A:A="P04")*'Detail Recettes'!D:D*IFERROR(INDEX('MP Referentiel'!F:F,MATCH('Detail Recettes'!B:B,'MP Referentiel'!A:A,0)),0))/5,"") -> #ERROR! | K12: Mar 2026 | L12: OK
A13: P07 | B13: Pate Chataigne Ardeche | C13: Pates & Terrines | D13: RR100-580 | E13: 87 | F13: 5 | G13: 4.5 | H13: Actif | I13: =IFERROR(COUNTIF('Detail Recettes'!A:A,"P07"),"") -> #ERROR! | J13: =IFERROR(SUMPRODUCT(('Detail Recettes'!A:A="P07")*'Detail Recettes'!D:D*IFERROR(INDEX('MP Referentiel'!F:F,MATCH('Detail Recettes'!B:B,'MP Referentiel'!A:A,0)),0))/5,"") -> #ERROR! | K13: Mar 2026 | L13: OK
A14: P49 | B14: Pate Echalotes Grises d'Anjou | C14: Pates & Terrines | D14: RR100-580 | E14: 88 | F14: 5 | G14: 4 | H14: Actif | I14: =IFERROR(COUNTIF('Detail Recettes'!A:A,"P49"),"") -> #ERROR! | J14: =IFERROR(SUMPRODUCT(('Detail Recettes'!A:A="P49")*'Detail Recettes'!D:D*IFERROR(INDEX('MP Referentiel'!F:F,MATCH('Detail Recettes'!B:B,'MP Referentiel'!A:A,0)),0))/5,"") -> #ERROR! | K14: Mar 2026 | L14: OK
A15: R41 | B15: Rillettes Classiques au Thym | C15: Rillettes | D15: RR100-580 | E15: 85 | F15: 5 | G15: 3.5 | H15: Actif | I15: =IFERROR(COUNTIF('Detail Recettes'!A:A,"R41"),"") -> #ERROR! | J15: =IFERROR(SUMPRODUCT(('Detail Recettes'!A:A="R41")*'Detail Recettes'!D:D*IFERROR(INDEX('MP Referentiel'!F:F,MATCH('Detail Recettes'!B:B,'MP Referentiel'!A:A,0)),0))/5,"") -> #ERROR! | K15: Mar 2026 | L15: OK
A16: R42 | B16: Rillettes Poireaux Confits | C16: Rillettes | D16: RR100-580 | E16: 84 | F16: 5 | G16: 4 | H16: Actif | I16: =IFERROR(COUNTIF('Detail Recettes'!A:A,"R42"),"") -> #ERROR! | J16: =IFERROR(SUMPRODUCT(('Detail Recettes'!A:A="R42")*'Detail Recettes'!D:D*IFERROR(INDEX('MP Referentiel'!F:F,MATCH('Detail Recettes'!B:B,'MP Referentiel'!A:A,0)),0))/5,"") -> #ERROR! | K16: Mar 2026 | L16: OK
A17: R43 | B17: Rillettes Gingembre & Citron | C17: Rillettes | D17: RR100-370 | E17: 85 | F17: 5 | G17: 3.5 | H17: Actif | I17: =IFERROR(COUNTIF('Detail Recettes'!A:A,"R43"),"") -> #ERROR! | J17: =IFERROR(SUMPRODUCT(('Detail Recettes'!A:A="R43")*'Detail Recettes'!D:D*IFERROR(INDEX('MP Referentiel'!F:F,MATCH('Detail Recettes'!B:B,'MP Referentiel'!A:A,0)),0))/5,"") -> #ERROR! | K17: Mar 2026 | L17: OK
A18: R44 | B18: Rillettes Poivre de Madagascar | C18: Rillettes | D18: RR100-370 | E18: 85 | F18: 5 | G18: 3.5 | H18: Actif | I18: =IFERROR(COUNTIF('Detail Recettes'!A:A,"R44"),"") -> #ERROR! | J18: =IFERROR(SUMPRODUCT(('Detail Recettes'!A:A="R44")*'Detail Recettes'!D:D*IFERROR(INDEX('MP Referentiel'!F:F,MATCH('Detail Recettes'!B:B,'MP Referentiel'!A:A,0)),0))/5,"") -> #ERROR! | K18: Mar 2026 | L18: OK
A19: R59 | B19: Rillettes Poireaux Confits Nord | C19: Rillettes | D19: RR100-370 | E19: 84 | F19: 5 | G19: 4 | H19: Actif | I19: =IFERROR(COUNTIF('Detail Recettes'!A:A,"R59"),"") -> #ERROR! | J19: =IFERROR(SUMPRODUCT(('Detail Recettes'!A:A="R59")*'Detail Recettes'!D:D*IFERROR(INDEX('MP Referentiel'!F:F,MATCH('Detail Recettes'!B:B,'MP Referentiel'!A:A,0)),0))/5,"") -> #ERROR! | K19: Mar 2026 | L19: OK
A20: R974 | B20: Rillettes Curry Vert Reunion | C20: Rillettes | D20: RR100-370 | E20: 85 | F20: 5 | G20: 3.5 | H20: Actif | I20: =IFERROR(COUNTIF('Detail Recettes'!A:A,"R974"),"") -> #ERROR! | J20: =IFERROR(SUMPRODUCT(('Detail Recettes'!A:A="R974")*'Detail Recettes'!D:D*IFERROR(INDEX('MP Referentiel'!F:F,MATCH('Detail Recettes'!B:B,'MP Referentiel'!A:A,0)),0))/5,"") -> #ERROR! | K20: Mar 2026 | L20: OK
A21: M13 | B21: Mousse Brandade de Morue | C21: Mousses | D21: RR100-370 | E21: 82 | F21: 4 | G21: 2.5 | H21: Actif | I21: =IFERROR(COUNTIF('Detail Recettes'!A:A,"M13"),"") -> #ERROR! | J21: =IFERROR(SUMPRODUCT(('Detail Recettes'!A:A="M13")*'Detail Recettes'!D:D*IFERROR(INDEX('MP Referentiel'!F:F,MATCH('Detail Recettes'!B:B,'MP Referentiel'!A:A,0)),0))/4,"") -> #ERROR! | K21: Mar 2026 | L21: OK
A22: PC01 | B22: Saucisses Lentilles Puy | C22: Plats cuisines | D22: RR100-850 | E22: 82 | F22: 6 | G22: 3 | H22: Actif | I22: =IFERROR(COUNTIF('Detail Recettes'!A:A,"PC01"),"") -> #ERROR! | J22: =IFERROR(SUMPRODUCT(('Detail Recettes'!A:A="PC01")*'Detail Recettes'!D:D*IFERROR(INDEX('MP Referentiel'!F:F,MATCH('Detail Recettes'!B:B,'MP Referentiel'!A:A,0)),0))/6,"") -> #ERROR! | K22: Mar 2026 | L22: OK
A23: PC02 | B23: Bourguignon de Boeuf | C23: Plats cuisines | D23: RR100-850 | E23: 78 | F23: 6 | G23: 4.5 | H23: Actif | I23: =IFERROR(COUNTIF('Detail Recettes'!A:A,"PC02"),"") -> #ERROR! | J23: =IFERROR(SUMPRODUCT(('Detail Recettes'!A:A="PC02")*'Detail Recettes'!D:D*IFERROR(INDEX('MP Referentiel'!F:F,MATCH('Detail Recettes'!B:B,'MP Referentiel'!A:A,0)),0))/6,"") -> #ERROR! | K23: Mar 2026 | L23: OK
A24: PC03 | B24: Pot-au-Feu de Boeuf | C24: Plats cuisines | D24: RR100-1050 | E24: 80 | F24: 6 | G24: 5 | H24: Actif | I24: =IFERROR(COUNTIF('Detail Recettes'!A:A,"PC03"),"") -> #ERROR! | J24: =IFERROR(SUMPRODUCT(('Detail Recettes'!A:A="PC03")*'Detail Recettes'!D:D*IFERROR(INDEX('MP Referentiel'!F:F,MATCH('Detail Recettes'!B:B,'MP Referentiel'!A:A,0)),0))/6,"") -> #ERROR! | K24: Mar 2026 | L24: OK
A25: PC04 | B25: Saute Porc & Puree | C25: Plats cuisines | D25: RR100-850 | E25: 83 | F25: 6 | G25: 3 | H25: Actif | I25: =IFERROR(COUNTIF('Detail Recettes'!A:A,"PC04"),"") -> #ERROR! | J25: =IFERROR(SUMPRODUCT(('Detail Recettes'!A:A="PC04")*'Detail Recettes'!D:D*IFERROR(INDEX('MP Referentiel'!F:F,MATCH('Detail Recettes'!B:B,'MP Referentiel'!A:A,0)),0))/6,"") -> #ERROR! | K25: Mar 2026 | L25: OK
A26: T31 | B26: Cassoulet Maison 41 | C26: Plats cuisines | D26: RR100-850 | E26: 80 | F26: 6 | G26: 4 | H26: Actif | I26: =IFERROR(COUNTIF('Detail Recettes'!A:A,"T31"),"") -> #ERROR! | J26: =IFERROR(SUMPRODUCT(('Detail Recettes'!A:A="T31")*'Detail Recettes'!D:D*IFERROR(INDEX('MP Referentiel'!F:F,MATCH('Detail Recettes'!B:B,'MP Referentiel'!A:A,0)),0))/6,"") -> #ERROR! | K26: Mar 2026 | L26: OK
A27: S64 | B27: Garbure Bearnaise | C27: Soupes | D27: RR100-850 | E27: 85 | F27: 5 | G27: 3 | H27: Actif | I27: =IFERROR(COUNTIF('Detail Recettes'!A:A,"S64"),"") -> #ERROR! | J27: =IFERROR(SUMPRODUCT(('Detail Recettes'!A:A="S64")*'Detail Recettes'!D:D*IFERROR(INDEX('MP Referentiel'!F:F,MATCH('Detail Recettes'!B:B,'MP Referentiel'!A:A,0)),0))/5,"") -> #ERROR! | K27: Mar 2026 | L27: OK
A28: D01 | B28: Creme Oeufs Vanille Bourbon | C28: Desserts appertises | D28: RR100-290 | E28: 95 | F28: 4 | G28: 2 | H28: Actif | I28: =IFERROR(COUNTIF('Detail Recettes'!A:A,"D01"),"") -> #ERROR! | J28: =IFERROR(SUMPRODUCT(('Detail Recettes'!A:A="D01")*'Detail Recettes'!D:D*IFERROR(INDEX('MP Referentiel'!F:F,MATCH('Detail Recettes'!B:B,'MP Referentiel'!A:A,0)),0))/4,"") -> #ERROR! | K28: Mar 2026 | L28: OK
A29: D02 | B29: Creme Chocolat Noir 70% | C29: Desserts appertises | D29: RR100-290 | E29: 95 | F29: 4 | G29: 2 | H29: Actif | I29: =IFERROR(COUNTIF('Detail Recettes'!A:A,"D02"),"") -> #ERROR! | J29: =IFERROR(SUMPRODUCT(('Detail Recettes'!A:A="D02")*'Detail Recettes'!D:D*IFERROR(INDEX('MP Referentiel'!F:F,MATCH('Detail Recettes'!B:B,'MP Referentiel'!A:A,0)),0))/4,"") -> #ERROR! | K29: Mar 2026 | L29: OK
A30: D03 | B30: Creme Caramel Renversee | C30: Desserts appertises | D30: RR100-290 | E30: 94 | F30: 4 | G30: 2.5 | H30: Actif | I30: =IFERROR(COUNTIF('Detail Recettes'!A:A,"D03"),"") -> #ERROR! | J30: =IFERROR(SUMPRODUCT(('Detail Recettes'!A:A="D03")*'Detail Recettes'!D:D*IFERROR(INDEX('MP Referentiel'!F:F,MATCH('Detail Recettes'!B:B,'MP Referentiel'!A:A,0)),0))/4,"") -> #ERROR! | K30: Mar 2026 | L30: OK
A31: D04 | B31: Riz au Lait Cannelle & Orange | C31: Desserts appertises | D31: RR100-370 | E31: 92 | F31: 4 | G31: 1.5 | H31: Actif | I31: =IFERROR(COUNTIF('Detail Recettes'!A:A,"D04"),"") -> #ERROR! | J31: =IFERROR(SUMPRODUCT(('Detail Recettes'!A:A="D04")*'Detail Recettes'!D:D*IFERROR(INDEX('MP Referentiel'!F:F,MATCH('Detail Recettes'!B:B,'MP Referentiel'!A:A,0)),0))/4,"") -> #ERROR! | K31: Mar 2026 | L31: OK
A32: D29 | B32: Far Breton aux Pruneaux | C32: Desserts appertises | D32: RR100-370 | E32: 88 | F32: 4 | G32: 2 | H32: Actif | I32: =IFERROR(COUNTIF('Detail Recettes'!A:A,"D29"),"") -> #ERROR! | J32: =IFERROR(SUMPRODUCT(('Detail Recettes'!A:A="D29")*'Detail Recettes'!D:D*IFERROR(INDEX('MP Referentiel'!F:F,MATCH('Detail Recettes'!B:B,'MP Referentiel'!A:A,0)),0))/4,"") -> #ERROR! | K32: Mar 2026 | L32: OK
A33: RC | B33: Rillettes du Chef | C33: Rillettes | D33: En développement | G33: 115 | H33: 24 | Q33: 46110 | R33: 46110
A34: NOUVELLES RECETTES — ajouter ici + renseigner les ingredients dans "Detail Recettes"
A35: R51 | B35: Rillettes aux Ricard | C35: Rillettes | E35: 95 | H35: Actif | K35: 46113

Sheet Detail Recettes
A1: MAISON 41 — DETAIL RECETTES — Ingredients par recette
A2: Source du cout MP et du calcul des besoins d'achat depuis le planning
A3: Ref recette · Code MP · Designation · Quantite · Unite · Prix MP · Cout ligne · % du cout total
A4: Ref. recette | B4: Code MP | C4: Designation MP | D4: Qte par batch | E4: Unite | F4: Prix MP (EUR) | G4: Cout ligne (EUR) | H4: % cout total | I4: Gamme recette | J4: Batch (kg)
A5: PC | B5: MP01 | C5: Epaule porc desossee | D5: 0.54 | E5: kg | F5: =IFERROR(INDEX('MP Referentiel'!F:F,MATCH(B14,'MP Referentiel'!A:A,0)),"") -> #ERROR! | G5: =IFERROR(D14*F14,"") -> #ERROR! | H5: =IFERROR(G14/SUMPRODUCT(('Detail Recettes'!A$5:A$183=A14)*'Detail Recettes'!G$5:G$183),"") -> #ERROR! | I5: =IFERROR(INDEX(Recettes!C:C,MATCH(A14,Recettes!A:A,0)),"") -> #ERROR! | J5: =IFERROR(INDEX(Recettes!F:F,MATCH(A14,Recettes!A:A,0)),"") -> #ERROR!
A6: PC | B6: MP02 | C6: Gorge porc | D6: 0.16 | E6: kg | F6: =IFERROR(INDEX('MP Referentiel'!F:F,MATCH(B15,'MP Referentiel'!A:A,0)),"") -> #ERROR! | G6: =IFERROR(D15*F15,"") -> #ERROR! | H6: =IFERROR(G15/SUMPRODUCT(('Detail Recettes'!A$5:A$183=A15)*'Detail Recettes'!G$5:G$183),"") -> #ERROR! | I6: =IFERROR(INDEX(Recettes!C:C,MATCH(A15,Recettes!A:A,0)),"") -> #ERROR! | J6: =IFERROR(INDEX(Recettes!F:F,MATCH(A15,Recettes!A:A,0)),"") -> #ERROR!
A7: PC | B7: MP03 | C7: Foie porc | D7: 0.08 | E7: kg | F7: =IFERROR(INDEX('MP Referentiel'!F:F,MATCH(B16,'MP Referentiel'!A:A,0)),"") -> #ERROR! | G7: =IFERROR(D16*F16,"") -> #ERROR! | H7: =IFERROR(G16/SUMPRODUCT(('Detail Recettes'!A$5:A$183=A16)*'Detail Recettes'!G$5:G$183),"") -> #ERROR! | I7: =IFERROR(INDEX(Recettes!C:C,MATCH(A16,Recettes!A:A,0)),"") -> #ERROR! | J7: =IFERROR(INDEX(Recettes!F:F,MATCH(A16,Recettes!A:A,0)),"") -> #ERROR!
A8: PC | B8: MP34 | C8: Oeufs frais entiers | D8: 0.06 | E8: kg | F8: =IFERROR(INDEX('MP Referentiel'!F:F,MATCH(B17,'MP Referentiel'!A:A,0)),"") -> #ERROR! | G8: =IFERROR(D17*F17,"") -> #ERROR! | H8: =IFERROR(G17/SUMPRODUCT(('Detail Recettes'!A$5:A$183=A17)*'Detail Recettes'!G$5:G$183),"") -> #ERROR! | I8: =IFERROR(INDEX(Recettes!C:C,MATCH(A17,Recettes!A:A,0)),"") -> #ERROR! | J8: =IFERROR(INDEX(Recettes!F:F,MATCH(A17,Recettes!A:A,0)),"") -> #ERROR!
A9: PC | B9: MP16 | C9: Oignon jaune | D9: 0.04 | E9: kg | F9: =IFERROR(INDEX('MP Referentiel'!F:F,MATCH(B18,'MP Referentiel'!A:A,0)),"") -> #ERROR! | G9: =IFERROR(D18*F18,"") -> #ERROR! | H9: =IFERROR(G18/SUMPRODUCT(('Detail Recettes'!A$5:A$183=A18)*'Detail Recettes'!G$5:G$183),"") -> #ERROR! | I9: =IFERROR(INDEX(Recettes!C:C,MATCH(A18,Recettes!A:A,0)),"") -> #ERROR! | J9: =IFERROR(INDEX(Recettes!F:F,MATCH(A18,Recettes!A:A,0)),"") -> #ERROR!
A10: PC | B10: MP60 | C10: Cognac / Armagnac | D10: 0.02 | E10: L | F10: =IFERROR(INDEX('MP Referentiel'!F:F,MATCH(B19,'MP Referentiel'!A:A,0)),"") -> #ERROR! | G10: =IFERROR(D19*F19,"") -> #ERROR! | H10: =IFERROR(G19/SUMPRODUCT(('Detail Recettes'!A$5:A$183=A19)*'Detail Recettes'!G$5:G$183),"") -> #ERROR! | I10: =IFERROR(INDEX(Recettes!C:C,MATCH(A19,Recettes!A:A,0)),"") -> #ERROR! | J10: =IFERROR(INDEX(Recettes!F:F,MATCH(A19,Recettes!A:A,0)),"") -> #ERROR!
A11: PC | B11: MP51 | C11: Sel fin | D11: 0.015 | E11: kg | F11: =IFERROR(INDEX('MP Referentiel'!F:F,MATCH(B20,'MP Referentiel'!A:A,0)),"") -> #ERROR! | G11: =IFERROR(D20*F20,"") -> #ERROR! | H11: =IFERROR(G20/SUMPRODUCT(('Detail Recettes'!A$5:A$183=A20)*'Detail Recettes'!G$5:G$183),"") -> #ERROR! | I11: =IFERROR(INDEX(Recettes!C:C,MATCH(A20,Recettes!A:A,0)),"") -> #ERROR! | J11: =IFERROR(INDEX(Recettes!F:F,MATCH(A20,Recettes!A:A,0)),"") -> #ERROR!
A12: PC | B12: MP50 | C12: Poivre noir moulu | D12: 0.003 | E12: kg | F12: =IFERROR(INDEX('MP Referentiel'!F:F,MATCH(B21,'MP Referentiel'!A:A,0)),"") -> #ERROR! | G12: =IFERROR(D21*F21,"") -> #ERROR! | H12: =IFERROR(G21/SUMPRODUCT(('Detail Recettes'!A$5:A$183=A21)*'Detail Recettes'!G$5:G$183),"") -> #ERROR! | I12: =IFERROR(INDEX(Recettes!C:C,MATCH(A21,Recettes!A:A,0)),"") -> #ERROR! | J12: =IFERROR(INDEX(Recettes!F:F,MATCH(A21,Recettes!A:A,0)),"") -> #ERROR!
A13: PC | B13: MP25 | C13: Quatre-epices | D13: 0.001 | E13: kg | F13: =IFERROR(INDEX('MP Referentiel'!F:F,MATCH(B22,'MP Referentiel'!A:A,0)),"") -> #ERROR! | G13: =IFERROR(D22*F22,"") -> #ERROR! | H13: =IFERROR(G22/SUMPRODUCT(('Detail Recettes'!A$5:A$183=A22)*'Detail Recettes'!G$5:G$183),"") -> #ERROR! | I13: =IFERROR(INDEX(Recettes!C:C,MATCH(A22,Recettes!A:A,0)),"") -> #ERROR! | J13: =IFERROR(INDEX(Recettes!F:F,MATCH(A22,Recettes!A:A,0)),"") -> #ERROR!
A14: PC | B14: MP42 | C14: Thym seche | D14: 0.003 | E14: kg | F14: =IFERROR(INDEX('MP Referentiel'!F:F,MATCH(B23,'MP Referentiel'!A:A,0)),"") -> #ERROR! | G14: =IFERROR(D23*F23,"") -> #ERROR! | H14: =IFERROR(G23/SUMPRODUCT(('Detail Recettes'!A$5:A$183=A23)*'Detail Recettes'!G$5:G$183),"") -> #ERROR! | I14: =IFERROR(INDEX(Recettes!C:C,MATCH(A23,Recettes!A:A,0)),"") -> #ERROR! | J14: =IFERROR(INDEX(Recettes!F:F,MATCH(A23,Recettes!A:A,0)),"") -> #ERROR!
A15: PC | B15: MP39 | C15: Laurier | D15: 0.002 | E15: kg | F15: =IFERROR(INDEX('MP Referentiel'!F:F,MATCH(B24,'MP Referentiel'!A:A,0)),"") -> #ERROR! | G15: =IFERROR(D24*F24,"") -> #ERROR! | H15: =IFERROR(G24/SUMPRODUCT(('Detail Recettes'!A$5:A$183=A24)*'Detail Recettes'!G$5:G$183),"") -> #ERROR! | I15: =IFERROR(INDEX(Recettes!C:C,MATCH(A24,Recettes!A:A,0)),"") -> #ERROR! | J15: =IFERROR(INDEX(Recettes!F:F,MATCH(A24,Recettes!A:A,0)),"") -> #ERROR!
A16: MC | B16: MP03 | C16: Foie porc | D16: 0.52 | E16: kg | F16: =IFERROR(INDEX('MP Referentiel'!F:F,MATCH(B25,'MP Referentiel'!A:A,0)),"") -> #ERROR! | G16: =IFERROR(D25*F25,"") -> #ERROR! | H16: =IFERROR(G25/SUMPRODUCT(('Detail Recettes'!A$5:A$183=A25)*'Detail Recettes'!G$5:G$183),"") -> #ERROR! | I16: =IFERROR(INDEX(Recettes!C:C,MATCH(A25,Recettes!A:A,0)),"") -> #ERROR! | J16: =IFERROR(INDEX(Recettes!F:F,MATCH(A25,Recettes!A:A,0)),"") -> #ERROR!
... A174: D29 | B174: MP28 | C174: Beurre doux | D174: 0.08 | E174: kg | F174: =IFERROR(INDEX('MP Referentiel'!F:F,MATCH(B183,'MP Referentiel'!A:A,0)),"") -> #ERROR! | G174: =IFERROR(D183*F183,"") -> #ERROR! | H174: =IFERROR(G183/SUMPRODUCT(('Detail Recettes'!A$5:A$183=A183)*'Detail Recettes'!G$5:G$183),"") -> #ERROR! | I174: =IFERROR(INDEX(Recettes!C:C,MATCH(A183,Recettes!A:A,0)),"") -> #ERROR! | J174: =IFERROR(INDEX(Recettes!F:F,MATCH(A183,Recettes!A:A,0)),"") -> #ERROR!
A175: R51 | B175: MP01 | D175: 1 | E175: kg
A176: R51
F177: =IFERROR(INDEX('MP Referentiel'!F:F,MATCH(B186,'MP Referentiel'!A:A,0)),"") -> #ERROR! | G177: =IFERROR(D186*F186,"") -> #ERROR!
F178: =IFERROR(INDEX('MP Referentiel'!F:F,MATCH(B187,'MP Referentiel'!A:A,0)),"") -> #ERROR! | G178: =IFERROR(D187*F187,"") -> #ERROR!
F179: =IFERROR(INDEX('MP Referentiel'!F:F,MATCH(B188,'MP Referentiel'!A:A,0)),"") -> #ERROR! | G179: =IFERROR(D188*F188,"") -> #ERROR!
F180: =IFERROR(INDEX('MP Referentiel'!F:F,MATCH(B189,'MP Referentiel'!A:A,0)),"") -> #ERROR! | G180: =IFERROR(D189*F189,"") -> #ERROR!
F181: =IFERROR(INDEX('MP Referentiel'!F:F,MATCH(B190,'MP Referentiel'!A:A,0)),"") -> #ERROR! | G181: =IFERROR(D190*F190,"") -> #ERROR!
F182: =IFERROR(INDEX('MP Referentiel'!F:F,MATCH(B191,'MP Referentiel'!A:A,0)),"") -> #ERROR! | G182: =IFERROR(D191*F191,"") -> #ERROR!
F183: =IFERROR(INDEX('MP Referentiel'!F:F,MATCH(B192,'MP Referentiel'!A:A,0)),"") -> #ERROR! | G183: =IFERROR(D192*F192,"") -> #ERROR!
F184: =IFERROR(INDEX('MP Referentiel'!F:F,MATCH(B193,'MP Referentiel'!A:A,0)),"") -> #ERROR! | G184: =IFERROR(D193*F193,"") -> #ERROR!
F185: =IFERROR(INDEX('MP Referentiel'!F:F,MATCH(B194,'MP Referentiel'!A:A,0)),"") -> #ERROR! | G185: =IFERROR(D194*F194,"") -> #ERROR!
F186: =IFERROR(INDEX('MP Referentiel'!F:F,MATCH(B195,'MP Referentiel'!A:A,0)),"") -> #ERROR! | G186: =IFERROR(D195*F195,"") -> #ERROR!
F187: =IFERROR(INDEX('MP Referentiel'!F:F,MATCH(B196,'MP Referentiel'!A:A,0)),"") -> #ERROR! | G187: =IFERROR(D196*F196,"") -> #ERROR!
F188: =IFERROR(INDEX('MP Referentiel'!F:F,MATCH(B197,'MP Referentiel'!A:A,0)),"") -> #ERROR! | G188: =IFERROR(D197*F197,"") -> #ERROR!
... F276: =IFERROR(INDEX('MP Referentiel'!F:F,MATCH(B285,'MP Referentiel'!A:A,0)),"") -> #ERROR! | G276: =IFERROR(D285*F285,"") -> #ERROR!

Sheet Recette Vierge
A1: MAISON 41 — RECETTE VIERGE — Dupliquer cet onglet · Renommer avec le code produit
A2: Mode d'emploi : Fichier > Copier · Ou clic droit onglet > Dupliquer · Renommer ex: R45
A4: IDENTITE PRODUIT
A5: Code produit | B5: Ex: R45, P05, MC2, D05 | C5: Code unique — format Gamme+Dept ou Gamme+Num
A6: Nom commercial | B6: Ex: Rillettes de Canard au Cepes | C6: Nom sur etiquette et en vente
A7: Gamme | C7: Choisir : Pates/Rillettes/Mousses/Plats/Desserts/Soupes
A8: Format Weck principal | C8: Format le plus vendu pour cette recette
A9: Rendement (%) | C9: Ex: 85 = 850g de produit fini pour 1kg de MP
A10: Batch production (kg MP) | C10: Quantite MP pour 1 lot complet
A11: Temps total (h) | C11: Preparation + cuisson + sterilisation
A12: Statut | B12: En developpement | C12: En developpement / Actif / Archive
A13: Validee par | C13: Nom + date de validation recette
A14: Date creation
A15: Version | B15: V1.0 | C15: Incrementer a chaque modification recette
A18: INGREDIENTS (batch complet)
A19: Code MP | B19: Designation | C19: Quantite | D19: Unite | E19: Prix/unite EUR | F19: Cout ligne EUR
B20: =IFERROR(INDEX('MP Referentiel'!B:B,MATCH(A20,'MP Referentiel'!A:A,0)),"") -> #ERROR! | D20: kg | E20: =IFERROR(INDEX('MP Referentiel'!F:F,MATCH(A20,'MP Referentiel'!A:A,0)),"") -> #ERROR! | F20: =IFERROR(C20*E20,"") -> #ERROR!
B21: =IFERROR(INDEX('MP Referentiel'!B:B,MATCH(A21,'MP Referentiel'!A:A,0)),"") -> #ERROR! | D21: kg | E21: =IFERROR(INDEX('MP Referentiel'!F:F,MATCH(A21,'MP Referentiel'!A:A,0)),"") -> #ERROR! | F21: =IFERROR(C21*E21,"") -> #ERROR!
B22: =IFERROR(INDEX('MP Referentiel'!B:B,MATCH(A22,'MP Referentiel'!A:A,0)),"") -> #ERROR! | D22: kg | E22: =IFERROR(INDEX('MP Referentiel'!F:F,MATCH(A22,'MP Referentiel'!A:A,0)),"") -> #ERROR! | F22: =IFERROR(C22*E22,"") -> #ERROR!
B23: =IFERROR(INDEX('MP Referentiel'!B:B,MATCH(A23,'MP Referentiel'!A:A,0)),"") -> #ERROR! | D23: kg | E23: =IFERROR(INDEX('MP Referentiel'!F:F,MATCH(A23,'MP Referentiel'!A:A,0)),"") -> #ERROR! | F23: =IFERROR(C23*E23,"") -> #ERROR!
B24: =IFERROR(INDEX('MP Referentiel'!B:B,MATCH(A24,'MP Referentiel'!A:A,0)),"") -> #ERROR! | D24: kg | E24: =IFERROR(INDEX('MP Referentiel'!F:F,MATCH(A24,'MP Referentiel'!A:A,0)),"") -> #ERROR! | F24: =IFERROR(C24*E24,"") -> #ERROR!
B25: =IFERROR(INDEX('MP Referentiel'!B:B,MATCH(A25,'MP Referentiel'!A:A,0)),"") -> #ERROR! | D25: kg | E25: =IFERROR(INDEX('MP Referentiel'!F:F,MATCH(A25,'MP Referentiel'!A:A,0)),"") -> #ERROR! | F25: =IFERROR(C25*E25,"") -> #ERROR!
B26: =IFERROR(INDEX('MP Referentiel'!B:B,MATCH(A26,'MP Referentiel'!A:A,0)),"") -> #ERROR! | D26: kg | E26: =IFERROR(INDEX('MP Referentiel'!F:F,MATCH(A26,'MP Referentiel'!A:A,0)),"") -> #ERROR! | F26: =IFERROR(C26*E26,"") -> #ERROR!
B27: =IFERROR(INDEX('MP Referentiel'!B:B,MATCH(A27,'MP Referentiel'!A:A,0)),"") -> #ERROR! | D27: kg | E27: =IFERROR(INDEX('MP Referentiel'!F:F,MATCH(A27,'MP Referentiel'!A:A,0)),"") -> #ERROR! | F27: =IFERROR(C27*E27,"") -> #ERROR!
B28: =IFERROR(INDEX('MP Referentiel'!B:B,MATCH(A28,'MP Referentiel'!A:A,0)),"") -> #ERROR! | D28: kg | E28: =IFERROR(INDEX('MP Referentiel'!F:F,MATCH(A28,'MP Referentiel'!A:A,0)),"") -> #ERROR! | F28: =IFERROR(C28*E28,"") -> #ERROR!
B29: =IFERROR(INDEX('MP Referentiel'!B:B,MATCH(A29,'MP Referentiel'!A:A,0)),"") -> #ERROR! | D29: kg | E29: =IFERROR(INDEX('MP Referentiel'!F:F,MATCH(A29,'MP Referentiel'!A:A,0)),"") -> #ERROR! | F29: =IFERROR(C29*E29,"") -> #ERROR!
B30: =IFERROR(INDEX('MP Referentiel'!B:B,MATCH(A30,'MP Referentiel'!A:A,0)),"") -> #ERROR! | D30: kg | E30: =IFERROR(INDEX('MP Referentiel'!F:F,MATCH(A30,'MP Referentiel'!A:A,0)),"") -> #ERROR! | F30: =IFERROR(C30*E30,"") -> #ERROR!
B31: =IFERROR(INDEX('MP Referentiel'!B:B,MATCH(A31,'MP Referentiel'!A:A,0)),"") -> #ERROR! | D31: kg | E31: =IFERROR(INDEX('MP Referentiel'!F:F,MATCH(A31,'MP Referentiel'!A:A,0)),"") -> #ERROR! | F31: =IFERROR(C31*E31,"") -> #ERROR!
... B39: =IFERROR(INDEX('MP Referentiel'!B:B,MATCH(A39,'MP Referentiel'!A:A,0)),"") -> #ERROR! | D39: kg | E39: =IFERROR(INDEX('MP Referentiel'!F:F,MATCH(A39,'MP Referentiel'!A:A,0)),"") -> #ERROR! | F39: =IFERROR(C39*E39,"") -> #ERROR!
A41: TOTAL COUT MP | F41: =SUM(F20:F39) -> #ERROR!

Sheet Referentiel Gamme
A1: MAISON 41 — REFERENTIEL GAMME & DEPARTEMENTS — Gamme Du Chef + references
A2: RC · PC · MC · TC · DC = Gamme Du Chef · R__ P__ M__ T__ D__ S__ = Gamme Departements
A4: GAMME DU CHEF — References fondatrices signees Alexandre
A5: Code | B5: Nom | C5: Gamme | D5: Statut | E5: Description | F5: Formats recommandes | G5: Score | H5: Cout MP/kg
A6: RC | B6: Rillettes du Chef | C6: Rillettes | D6: Actif | E6: Signature Alexandre | F6: Tous formats RR100 + W60 | G6: 10 | H6: 6.1
A7: PC | B7: Pate du Chef | C7: Pates & Terrines | D7: Actif | E7: Signature Alexandre | F7: Tous formats RR100 + W60 | G7: 10 | H7: 5.79
A8: MC | B8: Mousse du Chef | C8: Mousses | D8: Actif | E8: Signature Alexandre | F8: Tous formats RR100 + W60 | G8: 10 | H8: 4.97
A9: TC | B9: Plat Traiteur du Chef | C9: Plats cuisines | D9: Actif | E9: Signature Alexandre | F9: Tous formats RR100 + W60 | G9: 10 | H9: 8.29
A10: DC | B10: Dessert du Chef | C10: Desserts appertises | D10: Actif | E10: Signature Alexandre | F10: Tous formats RR100 + W60 | G10: 10 | H10: 1.48

Sheet Prix Vente
A1: MAISON 41 — GRILLE TARIFAIRE — 1 seule saisie TTC B2C · Welcome Pack · Early Bird Ulule -15%
A2: Cellule JAUNE = seule saisie · Vert = calcule · Bleu = notre prix HT pro
A3: REGLE : PVC conseille au pro TOUJOURS > notre prix TTC B2C
A4: Gamme | B4: Format Weck | C4: B TO C MARCHES (TTC) | G4: E-COMMERCE (TTC) | J4: RESTAURANTS (HT) | M4: EPICERIES FINES (HT) | P4: HOTELS / AIRBNB (HT) | S4: GMS (HT) | V4: Marge directe | W4: WELCOME PACK TTC | X4: EARLY BIRD -15% Ulule
C5: x1 SAISIR | D5: x3 -5% | E5: x6 -8% | F5: x20 -12% | G5: x1 | H5: x3 -3% | I5: x6 -6% | J5: x3 | K5: x10 | L5: x24 | M5: x6 | N5: x12 | O5: x24 | P5: x6 | Q5: x12 | R5: x24 | S5: x100 | T5: x200 | U5: x500 | V5: %
A7: PATES & TERRINES — TVA 5%
A8: Pates & Terrines | B8: RR100-290 | C8: 5.9 | D8: =IFERROR(ROUND(C8*0.95,2),"") -> #ERROR! | E8: =IFERROR(ROUND(C8*0.92,2),"") -> #ERROR! | F8: =IFERROR(ROUND(C8*0.88,2),"") -> #ERROR! | G8: =IFERROR(ROUND(C8*1,2),"") -> #ERROR! | H8: =IFERROR(ROUND(C8*0.97,2),"") -> #ERROR! | I8: =IFERROR(ROUND(C8*0.94,2),"") -> #ERROR! | J8: =IFERROR(ROUND((C8/IFERROR(INDEX(Config!B:B,MATCH("TVA "&A8,Config!A:A,0)),1.055))*0.55,2),"") -> #ERROR! | K8: =IFERROR(ROUND((C8/IFERROR(INDEX(Config!B:B,MATCH("TVA "&A8,Config!A:A,0)),1.055))*0.48,2),"") -> #ERROR! | L8: =IFERROR(ROUND((C8/IFERROR(INDEX(Config!B:B,MATCH("TVA "&A8,Config!A:A,0)),1.055))*0.42,2),"") -> #ERROR! | M8: =IFERROR(ROUND((C8/IFERROR(INDEX(Config!B:B,MATCH("TVA "&A8,Config!A:A,0)),1.055))*0.58,2),"") -> #ERROR! | N8: =IFERROR(ROUND((C8/IFERROR(INDEX(Config!B:B,MATCH("TVA "&A8,Config!A:A,0)),1.055))*0.52,2),"") -> #ERROR! | O8: =IFERROR(ROUND((C8/IFERROR(INDEX(Config!B:B,MATCH("TVA "&A8,Config!A:A,0)),1.055))*0.52,2),"") -> #ERROR! | P8: =IFERROR(ROUND((C8/IFERROR(INDEX(Config!B:B,MATCH("TVA "&A8,Config!A:A,0)),1.055))*0.55,2),"") -> #ERROR! | Q8: =IFERROR(ROUND((C8/IFERROR(INDEX(Config!B:B,MATCH("TVA "&A8,Config!A:A,0)),1.055))*0.5,2),"") -> #ERROR! | R8: =IFERROR(ROUND((C8/IFERROR(INDEX(Config!B:B,MATCH("TVA "&A8,Config!A:A,0)),1.055))*0.5,2),"") -> #ERROR! | S8: =IFERROR(ROUND((C8/IFERROR(INDEX(Config!B:B,MATCH("TVA "&A8,Config!A:A,0)),1.055))*0.62,2),"") -> #ERROR! | T8: =IFERROR(ROUND((C8/IFERROR(INDEX(Config!B:B,MATCH("TVA "&A8,Config!A:A,0)),1.055))*0.58,2),"") -> #ERROR! | U8: =IFERROR(ROUND((C8/IFERROR(INDEX(Config!B:B,MATCH("TVA "&A8,Config!A:A,0)),1.055))*0.58,2),"") -> #ERROR! | V8: =IFERROR(((C8/IFERROR(INDEX(Config!B:B,MATCH("TVA "&A8,Config!A:A,0)),1.055))-IFERROR(INDEX('Cout de Revient'!I:I,MATCH(B8,'Cout de Revient'!C:C,0)),0))/(C8/IFERROR(INDEX(Config!B:B,MATCH("TVA "&A8,Config!A:A,0)),1.055)),"") -> #ERROR! | W8: =IFERROR(C8,"") -> #ERROR! | X8: =IFERROR(ROUND(C8*0.85,2),"") -> #ERROR!
A9: Pates & Terrines | B9: RR100-370 | C9: 7.5 | D9: =IFERROR(ROUND(C9*0.95,2),"") -> #ERROR! | E9: =IFERROR(ROUND(C9*0.92,2),"") -> #ERROR! | F9: =IFERROR(ROUND(C9*0.88,2),"") -> #ERROR! | G9: =IFERROR(ROUND(C9*1,2),"") -> #ERROR! | H9: =IFERROR(ROUND(C9*0.97,2),"") -> #ERROR! | I9: =IFERROR(ROUND(C9*0.94,2),"") -> #ERROR! | J9: =IFERROR(ROUND((C9/IFERROR(INDEX(Config!B:B,MATCH("TVA "&A9,Config!A:A,0)),1.055))*0.55,2),"") -> #ERROR! | K9: =IFERROR(ROUND((C9/IFERROR(INDEX(Config!B:B,MATCH("TVA "&A9,Config!A:A,0)),1.055))*0.48,2),"") -> #ERROR! | L9: =IFERROR(ROUND((C9/IFERROR(INDEX(Config!B:B,MATCH("TVA "&A9,Config!A:A,0)),1.055))*0.42,2),"") -> #ERROR! | M9: =IFERROR(ROUND((C9/IFERROR(INDEX(Config!B:B,MATCH("TVA "&A9,Config!A:A,0)),1.055))*0.58,2),"") -> #ERROR! | N9: =IFERROR(ROUND((C9/IFERROR(INDEX(Config!B:B,MATCH("TVA "&A9,Config!A:A,0)),1.055))*0.52,2),"") -> #ERROR! | O9: =IFERROR(ROUND((C9/IFERROR(INDEX(Config!B:B,MATCH("TVA "&A9,Config!A:A,0)),1.055))*0.52,2),"") -> #ERROR! | P9: =IFERROR(ROUND((C9/IFERROR(INDEX(Config!B:B,MATCH("TVA "&A9,Config!A:A,0)),1.055))*0.55,2),"") -> #ERROR! | Q9: =IFERROR(ROUND((C9/IFERROR(INDEX(Config!B:B,MATCH("TVA "&A9,Config!A:A,0)),1.055))*0.5,2),"") -> #ERROR! | R9: =IFERROR(ROUND((C9/IFERROR(INDEX(Config!B:B,MATCH("TVA "&A9,Config!A:A,0)),1.055))*0.5,2),"") -> #ERROR! | S9: =IFERROR(ROUND((C9/IFERROR(INDEX(Config!B:B,MATCH("TVA "&A9,Config!A:A,0)),1.055))*0.62,2),"") -> #ERROR! | T9: =IFERROR(ROUND((C9/IFERROR(INDEX(Config!B:B,MATCH("TVA "&A9,Config!A:A,0)),1.055))*0.58,2),"") -> #ERROR! | U9: =IFERROR(ROUND((C9/IFERROR(INDEX(Config!B:B,MATCH("TVA "&A9,Config!A:A,0)),1.055))*0.58,2),"") -> #ERROR! | V9: =IFERROR(((C9/IFERROR(INDEX(Config!B:B,MATCH("TVA "&A9,Config!A:A,0)),1.055))-IFERROR(INDEX('Cout de Revient'!I:I,MATCH(B9,'Cout de Revient'!C:C,0)),0))/(C9/IFERROR(INDEX(Config!B:B,MATCH("TVA "&A9,Config!A:A,0)),1.055)),"") -> #ERROR! | W9: =IFERROR(C9,"") -> #ERROR! | X9: =IFERROR(ROUND(C9*0.85,2),"") -> #ERROR!
A10: Pates & Terrines | B10: RR100-580 | C10: 9.9 | D10: =IFERROR(ROUND(C10*0.95,2),"") -> #ERROR! | E10: =IFERROR(ROUND(C10*0.92,2),"") -> #ERROR! | F10: =IFERROR(ROUND(C10*0.88,2),"") -> #ERROR! | G10: =IFERROR(ROUND(C10*1,2),"") -> #ERROR! | H10: =IFERROR(ROUND(C10*0.97,2),"") -> #ERROR! | I10: =IFERROR(ROUND(C10*0.94,2),"") -> #ERROR! | J10: =IFERROR(ROUND((C10/IFERROR(INDEX(Config!B:B,MATCH("TVA "&A10,Config!A:A,0)),1.055))*0.55,2),"") -> #ERROR! | K10: =IFERROR(ROUND((C10/IFERROR(INDEX(Config!B:B,MATCH("TVA "&A10,Config!A:A,0)),1.055))*0.48,2),"") -> #ERROR! | L10: =IFERROR(ROUND((C10/IFERROR(INDEX(Config!B:B,MATCH("TVA "&A10,Config!A:A,0)),1.055))*0.42,2),"") -> #ERROR! | M10: =IFERROR(ROUND((C10/IFERROR(INDEX(Config!B:B,MATCH("TVA "&A10,Config!A:A,0)),1.055))*0.58,2),"") -> #ERROR! | N10: =IFERROR(ROUND((C10/IFERROR(INDEX(Config!B:B,MATCH("TVA "&A10,Config!A:A,0)),1.055))*0.52,2),"") -> #ERROR! | O10: =IFERROR(ROUND((C10/IFERROR(INDEX(Config!B:B,MATCH("TVA "&A10,Config!A:A,0)),1.055))*0.52,2),"") -> #ERROR! | P10: =IFERROR(ROUND((C10/IFERROR(INDEX(Config!B:B,MATCH("TVA "&A10,Config!A:A,0)),1.055))*0.55,2),"") -> #ERROR! | Q10: =IFERROR(ROUND((C10/IFERROR(INDEX(Config!B:B,MATCH("TVA "&A10,Config!A:A,0)),1.055))*0.5,2),"") -> #ERROR! | R10: =IFERROR(ROUND((C10/IFERROR(INDEX(Config!B:B,MATCH("TVA "&A10,Config!A:A,0)),1.055))*0.5,2),"") -> #ERROR! | S10: =IFERROR(ROUND((C10/IFERROR(INDEX(Config!B:B,MATCH("TVA "&A10,Config!A:A,0)),1.055))*0.62,2),"") -> #ERROR! | T10: =IFERROR(ROUND((C10/IFERROR(INDEX(Config!B:B,MATCH("TVA "&A10,Config!A:A,0)),1.055))*0.58,2),"") -> #ERROR! | U10: =IFERROR(ROUND((C10/IFERROR(INDEX(Config!B:B,MATCH("TVA "&A10,Config!A:A,0)),1.055))*0.58,2),"") -> #ERROR! | V10: =IFERROR(((C10/IFERROR(INDEX(Config!B:B,MATCH("TVA "&A10,Config!A:A,0)),1.055))-IFERROR(INDEX('Cout de Revient'!I:I,MATCH(B10,'Cout de Revient'!C:C,0)),0))/(C10/IFERROR(INDEX(Config!B:B,MATCH("TVA "&A10,Config!A:A,0)),1.055)),"") -> #ERROR! | W10: =IFERROR(C10,"") -> #ERROR! | X10: =IFERROR(ROUND(C10*0.85,2),"") -> #ERROR!
A11: Pates & Terrines | B11: RR100-850 | C11: 13.9 | D11: =IFERROR(ROUND(C11*0.95,2),"") -> #ERROR! | E11: =IFERROR(ROUND(C11*0.92,2),"") -> #ERROR! | F11: =IFERROR(ROUND(C11*0.88,2),"") -> #ERROR! | G11: =IFERROR(ROUND(C11*1,2),"") -> #ERROR! | H11: =IFERROR(ROUND(C11*0.97,2),"") -> #ERROR! | I11: =IFERROR(ROUND(C11*0.94,2),"") -> #ERROR! | J11: =IFERROR(ROUND((C11/IFERROR(INDEX(Config!B:B,MATCH("TVA "&A11,Config!A:A,0)),1.055))*0.55,2),"") -> #ERROR! | K11: =IFERROR(ROUND((C11/IFERROR(INDEX(Config!B:B,MATCH("TVA "&A11,Config!A:A,0)),1.055))*0.48,2),"") -> #ERROR! | L11: =IFERROR(ROUND((C11/IFERROR(INDEX(Config!B:B,MATCH("TVA "&A11,Config!A:A,0)),1.055))*0.42,2),"") -> #ERROR! | M11: =IFERROR(ROUND((C11/IFERROR(INDEX(Config!B:B,MATCH("TVA "&A11,Config!A:A,0)),1.055))*0.58,2),"") -> #ERROR! | N11: =IFERROR(ROUND((C11/IFERROR(INDEX(Config!B:B,MATCH("TVA "&A11,Config!A:A,0)),1.055))*0.52,2),"") -> #ERROR! | O11: =IFERROR(ROUND((C11/IFERROR(INDEX(Config!B:B,MATCH("TVA "&A11,Config!A:A,0)),1.055))*0.52,2),"") -> #ERROR! | P11: =IFERROR(ROUND((C11/IFERROR(INDEX(Config!B:B,MATCH("TVA "&A11,Config!A:A,0)),1.055))*0.55,2),"") -> #ERROR! | Q11: =IFERROR(ROUND((C11/IFERROR(INDEX(Config!B:B,MATCH("TVA "&A11,Config!A:A,0)),1.055))*0.5,2),"") -> #ERROR! | R11: =IFERROR(ROUND((C11/IFERROR(INDEX(Config!B:B,MATCH("TVA "&A11,Config!A:A,0)),1.055))*0.5,2),"") -> #ERROR! | S11: =IFERROR(ROUND((C11/IFERROR(INDEX(Config!B:B,MATCH("TVA "&A11,Config!A:A,0)),1.055))*0.62,2),"") -> #ERROR! | T11: =IFERROR(ROUND((C11/IFERROR(INDEX(Config!B:B,MATCH("TVA "&A11,Config!A:A,0)),1.055))*0.58,2),"") -> #ERROR! | U11: =IFERROR(ROUND((C11/IFERROR(INDEX(Config!B:B,MATCH("TVA "&A11,Config!A:A,0)),1.055))*0.58,2),"") -> #ERROR! | V11: =IFERROR(((C11/IFERROR(INDEX(Config!B:B,MATCH("TVA "&A11,Config!A:A,0)),1.055))-IFERROR(INDEX('Cout de Revient'!I:I,MATCH(B11,'Cout de Revient'!C:C,0)),0))/(C11/IFERROR(INDEX(Config!B:B,MATCH("TVA "&A11,Config!A:A,0)),1.055)),"") -> #ERROR! | W11: =IFERROR(C11,"") -> #ERROR! | X11: =IFERROR(ROUND(C11*0.85,2),"") -> #ERROR!
A12: Pates & Terrines | B12: RR100-1050 | C12: 17.9 | D12: =IFERROR(ROUND(C12*0.95,2),"") -> #ERROR! | E12: =IFERROR(ROUND(C12*0.92,2),"") -> #ERROR! | F12: =IFERROR(ROUND(C12*0.88,2),"") -> #ERROR! | G12: =IFERROR(ROUND(C12*1,2),"") -> #ERROR! | H12: =IFERROR(ROUND(C12*0.97,2),"") -> #ERROR! | I12: =IFERROR(ROUND(C12*0.94,2),"") -> #ERROR! | J12: =IFERROR(ROUND((C12/IFERROR(INDEX(Config!B:B,MATCH("TVA "&A12,Config!A:A,0)),1.055))*0.55,2),"") -> #ERROR! | K12: =IFERROR(ROUND((C12/IFERROR(INDEX(Config!B:B,MATCH("TVA "&A12,Config!A:A,0)),1.055))*0.48,2),"") -> #ERROR! | L12: =IFERROR(ROUND((C12/IFERROR(INDEX(Config!B:B,MATCH("TVA "&A12,Config!A:A,0)),1.055))*0.42,2),"") -> #ERROR! | M12: =IFERROR(ROUND((C12/IFERROR(INDEX(Config!B:B,MATCH("TVA "&A12,Config!A:A,0)),1.055))*0.58,2),"") -> #ERROR! | N12: =IFERROR(ROUND((C12/IFERROR(INDEX(Config!B:B,MATCH("TVA "&A12,Config!A:A,0)),1.055))*0.52,2),"") -> #ERROR! | O12: =IFERROR(ROUND((C12/IFERROR(INDEX(Config!B:B,MATCH("TVA "&A12,Config!A:A,0)),1.055))*0.52,2),"") -> #ERROR! | P12: =IFERROR(ROUND((C12/IFERROR(INDEX(Config!B:B,MATCH("TVA "&A12,Config!A:A,0)),1.055))*0.55,2),"") -> #ERROR! | Q12: =IFERROR(ROUND((C12/IFERROR(INDEX(Config!B:B,MATCH("TVA "&A12,Config!A:A,0)),1.055))*0.5,2),"") -> #ERROR! | R12: =IFERROR(ROUND((C12/IFERROR(INDEX(Config!B:B,MATCH("TVA "&A12,Config!A:A,0)),1.055))*0.5,2),"") -> #ERROR! | S12: =IFERROR(ROUND((C12/IFERROR(INDEX(Config!B:B,MATCH("TVA "&A12,Config!A:A,0)),1.055))*0.62,2),"") -> #ERROR! | T12: =IFERROR(ROUND((C12/IFERROR(INDEX(Config!B:B,MATCH("TVA "&A12,Config!A:A,0)),1.055))*0.58,2),"") -> #ERROR! | U12: =IFERROR(ROUND((C12/IFERROR(INDEX(Config!B:B,MATCH("TVA "&A12,Config!A:A,0)),1.055))*0.58,2),"") -> #ERROR! | V12: =IFERROR(((C12/IFERROR(INDEX(Config!B:B,MATCH("TVA "&A12,Config!A:A,0)),1.055))-IFERROR(INDEX('Cout de Revient'!I:I,MATCH(B12,'Cout de Revient'!C:C,0)),0))/(C12/IFERROR(INDEX(Config!B:B,MATCH("TVA "&A12,Config!A:A,0)),1.055)),"") -> #ERROR! | W12: =IFERROR(C12,"") -> #ERROR! | X12: =IFERROR(ROUND(C12*0.85,2),"") -> #ERROR!
A13: Pates & Terrines | B13: RR100-1550 | C13: 24.9 | D13: =IFERROR(ROUND(C13*0.95,2),"") -> #ERROR! | E13: =IFERROR(ROUND(C13*0.92,2),"") -> #ERROR! | F13: =IFERROR(ROUND(C13*0.88,2),"") -> #ERROR! | G13: =IFERROR(ROUND(C13*1,2),"") -> #ERROR! | H13: =IFERROR(ROUND(C13*0.97,2),"") -> #ERROR! | I13: =IFERROR(ROUND(C13*0.94,2),"") -> #ERROR! | J13: =IFERROR(ROUND((C13/IFERROR(INDEX(Config!B:B,MATCH("TVA "&A13,Config!A:A,0)),1.055))*0.55,2),"") -> #ERROR! | K13: =IFERROR(ROUND((C13/IFERROR(INDEX(Config!B:B,MATCH("TVA "&A13,Config!A:A,0)),1.055))*0.48,2),"") -> #ERROR! | L13: =IFERROR(ROUND((C13/IFERROR(INDEX(Config!B:B,MATCH("TVA "&A13,Config!A:A,0)),1.055))*0.42,2),"") -> #ERROR! | M13: =IFERROR(ROUND((C13/IFERROR(INDEX(Config!B:B,MATCH("TVA "&A13,Config!A:A,0)),1.055))*0.58,2),"") -> #ERROR! | N13: =IFERROR(ROUND((C13/IFERROR(INDEX(Config!B:B,MATCH("TVA "&A13,Config!A:A,0)),1.055))*0.52,2),"") -> #ERROR! | O13: =IFERROR(ROUND((C13/IFERROR(INDEX(Config!B:B,MATCH("TVA "&A13,Config!A:A,0)),1.055))*0.52,2),"") -> #ERROR! | P13: =IFERROR(ROUND((C13/IFERROR(INDEX(Config!B:B,MATCH("TVA "&A13,Config!A:A,0)),1.055))*0.55,2),"") -> #ERROR! | Q13: =IFERROR(ROUND((C13/IFERROR(INDEX(Config!B:B,MATCH("TVA "&A13,Config!A:A,0)),1.055))*0.5,2),"") -> #ERROR! | R13: =IFERROR(ROUND((C13/IFERROR(INDEX(Config!B:B,MATCH("TVA "&A13,Config!A:A,0)),1.055))*0.5,2),"") -> #ERROR! | S13: =IFERROR(ROUND((C13/IFERROR(INDEX(Config!B:B,MATCH("TVA "&A13,Config!A:A,0)),1.055))*0.62,2),"") -> #ERROR! | T13: =IFERROR(ROUND((C13/IFERROR(INDEX(Config!B:B,MATCH("TVA "&A13,Config!A:A,0)),1.055))*0.58,2),"") -> #ERROR! | U13: =IFERROR(ROUND((C13/IFERROR(INDEX(Config!B:B,MATCH("TVA "&A13,Config!A:A,0)),1.055))*0.58,2),"") -> #ERROR! | V13: =IFERROR(((C13/IFERROR(INDEX(Config!B:B,MATCH("TVA "&A13,Config!A:A,0)),1.055))-IFERROR(INDEX('Cout de Revient'!I:I,MATCH(B13,'Cout de Revient'!C:C,0)),0))/(C13/IFERROR(INDEX(Config!B:B,MATCH("TVA "&A13,Config!A:A,0)),1.055)),"") -> #ERROR! | W13: =IFERROR(C13,"") -> #ERROR! | X13: =IFERROR(ROUND(C13*0.85,2),"") -> #ERROR!
A14: Pates & Terrines | B14: W60-050 | C14: 2.5 | D14: =IFERROR(ROUND(C14*0.95,2),"") -> #ERROR! | E14: =IFERROR(ROUND(C14*0.92,2),"") -> #ERROR! | F14: =IFERROR(ROUND(C14*0.88,2),"") -> #ERROR! | G14: =IFERROR(ROUND(C14*1,2),"") -> #ERROR! | H14: =IFERROR(ROUND(C14*0.97,2),"") -> #ERROR! | I14: =IFERROR(ROUND(C14*0.94,2),"") -> #ERROR! | J14: =IFERROR(ROUND((C14/IFERROR(INDEX(Config!B:B,MATCH("TVA "&A14,Config!A:A,0)),1.055))*0.55,2),"") -> #ERROR! | K14: =IFERROR(ROUND((C14/IFERROR(INDEX(Config!B:B,MATCH("TVA "&A14,Config!A:A,0)),1.055))*0.48,2),"") -> #ERROR! | L14: =IFERROR(ROUND((C14/IFERROR(INDEX(Config!B:B,MATCH("TVA "&A14,Config!A:A,0)),1.055))*0.42,2),"") -> #ERROR! | M14: =IFERROR(ROUND((C14/IFERROR(INDEX(Config!B:B,MATCH("TVA "&A14,Config!A:A,0)),1.055))*0.58,2),"") -> #ERROR! | N14: =IFERROR(ROUND((C14/IFERROR(INDEX(Config!B:B,MATCH("TVA "&A14,Config!A:A,0)),1.055))*0.52,2),"") -> #ERROR! | O14: =IFERROR(ROUND((C14/IFERROR(INDEX(Config!B:B,MATCH("TVA "&A14,Config!A:A,0)),1.055))*0.52,2),"") -> #ERROR! | P14: =IFERROR(ROUND((C14/IFERROR(INDEX(Config!B:B,MATCH("TVA "&A14,Config!A:A,0)),1.055))*0.55,2),"") -> #ERROR! | Q14: =IFERROR(ROUND((C14/IFERROR(INDEX(Config!B:B,MATCH("TVA "&A14,Config!A:A,0)),1.055))*0.5,2),"") -> #ERROR! | R14: =IFERROR(ROUND((C14/IFERROR(INDEX(Config!B:B,MATCH("TVA "&A14,Config!A:A,0)),1.055))*0.5,2),"") -> #ERROR! | S14: =IFERROR(ROUND((C14/IFERROR(INDEX(Config!B:B,MATCH("TVA "&A14,Config!A:A,0)),1.055))*0.62,2),"") -> #ERROR! | T14: =IFERROR(ROUND((C14/IFERROR(INDEX(Config!B:B,MATCH("TVA "&A14,Config!A:A,0)),1.055))*0.58,2),"") -> #ERROR! | U14: =IFERROR(ROUND((C14/IFERROR(INDEX(Config!B:B,MATCH("TVA "&A14,Config!A:A,0)),1.055))*0.58,2),"") -> #ERROR! | V14: =IFERROR(((C14/IFERROR(INDEX(Config!B:B,MATCH("TVA "&A14,Config!A:A,0)),1.055))-IFERROR(INDEX('Cout de Revient'!I:I,MATCH(B14,'Cout de Revient'!C:C,0)),0))/(C14/IFERROR(INDEX(Config!B:B,MATCH("TVA "&A14,Config!A:A,0)),1.055)),"") -> #ERROR! | W14: =IFERROR(C14,"") -> #ERROR! | X14: =IFERROR(ROUND(C14*0.85,2),"") -> #ERROR!
A15: Pates & Terrines | B15: W60-080 | C15: 3.5 | D15: =IFERROR(ROUND(C15*0.95,2),"") -> #ERROR! | E15: =IFERROR(ROUND(C15*0.92,2),"") -> #ERROR! | F15: =IFERROR(ROUND(C15*0.88,2),"") -> #ERROR! | G15: =IFERROR(ROUND(C15*1,2),"") -> #ERROR! | H15: =IFERROR(ROUND(C15*0.97,2),"") -> #ERROR! | I15: =IFERROR(ROUND(C15*0.94,2),"") -> #ERROR! | J15: =IFERROR(ROUND((C15/IFERROR(INDEX(Config!B:B,MATCH("TVA "&A15,Config!A:A,0)),1.055))*0.55,2),"") -> #ERROR! | K15: =IFERROR(ROUND((C15/IFERROR(INDEX(Config!B:B,MATCH("TVA "&A15,Config!A:A,0)),1.055))*0.48,2),"") -> #ERROR! | L15: =IFERROR(ROUND((C15/IFERROR(INDEX(Config!B:B,MATCH("TVA "&A15,Config!A:A,0)),1.055))*0.42,2),"") -> #ERROR! | M15: =IFERROR(ROUND((C15/IFERROR(INDEX(Config!B:B,MATCH("TVA "&A15,Config!A:A,0)),1.055))*0.58,2),"") -> #ERROR! | N15: =IFERROR(ROUND((C15/IFERROR(INDEX(Config!B:B,MATCH("TVA "&A15,Config!A:A,0)),1.055))*0.52,2),"") -> #ERROR! | O15: =IFERROR(ROUND((C15/IFERROR(INDEX(Config!B:B,MATCH("TVA "&A15,Config!A:A,0)),1.055))*0.52,2),"") -> #ERROR! | P15: =IFERROR(ROUND((C15/IFERROR(INDEX(Config!B:B,MATCH("TVA "&A15,Config!A:A,0)),1.055))*0.55,2),"") -> #ERROR! | Q15: =IFERROR(ROUND((C15/IFERROR(INDEX(Config!B:B,MATCH("TVA "&A15,Config!A:A,0)),1.055))*0.5,2),"") -> #ERROR! | R15: =IFERROR(ROUND((C15/IFERROR(INDEX(Config!B:B,MATCH("TVA "&A15,Config!A:A,0)),1.055))*0.5,2),"") -> #ERROR! | S15: =IFERROR(ROUND((C15/IFERROR(INDEX(Config!B:B,MATCH("TVA "&A15,Config!A:A,0)),1.055))*0.62,2),"") -> #ERROR! | T15: =IFERROR(ROUND((C15/IFERROR(INDEX(Config!B:B,MATCH("TVA "&A15,Config!A:A,0)),1.055))*0.58,2),"") -> #ERROR! | U15: =IFERROR(ROUND((C15/IFERROR(INDEX(Config!B:B,MATCH("TVA "&A15,Config!A:A,0)),1.055))*0.58,2),"") -> #ERROR! | V15: =IFERROR(((C15/IFERROR(INDEX(Config!B:B,MATCH("TVA "&A15,Config!A:A,0)),1.055))-IFERROR(INDEX('Cout de Revient'!I:I,MATCH(B15,'Cout de Revient'!C:C,0)),0))/(C15/IFERROR(INDEX(Config!B:B,MATCH("TVA "&A15,Config!A:A,0)),1.055)),"") -> #ERROR! | W15: =IFERROR(C15,"") -> #ERROR! | X15: =IFERROR(ROUND(C15*0.85,2),"") -> #ERROR!
A16: Pates & Terrines | B16: W60-160 | C16: 4.9 | D16: =IFERROR(ROUND(C16*0.95,2),"") -> #ERROR! | E16: =IFERROR(ROUND(C16*0.92,2),"") -> #ERROR! | F16: =IFERROR(ROUND(C16*0.88,2),"") -> #ERROR! | G16: =IFERROR(ROUND(C16*1,2),"") -> #ERROR! | H16: =IFERROR(ROUND(C16*0.97,2),"") -> #ERROR! | I16: =IFERROR(ROUND(C16*0.94,2),"") -> #ERROR! | J16: =IFERROR(ROUND((C16/IFERROR(INDEX(Config!B:B,MATCH("TVA "&A16,Config!A:A,0)),1.055))*0.55,2),"") -> #ERROR! | K16: =IFERROR(ROUND((C16/IFERROR(INDEX(Config!B:B,MATCH("TVA "&A16,Config!A:A,0)),1.055))*0.48,2),"") -> #ERROR! | L16: =IFERROR(ROUND((C16/IFERROR(INDEX(Config!B:B,MATCH("TVA "&A16,Config!A:A,0)),1.055))*0.42,2),"") -> #ERROR! | M16: =IFERROR(ROUND((C16/IFERROR(INDEX(Config!B:B,MATCH("TVA "&A16,Config!A:A,0)),1.055))*0.58,2),"") -> #ERROR! | N16: =IFERROR(ROUND((C16/IFERROR(INDEX(Config!B:B,MATCH("TVA "&A16,Config!A:A,0)),1.055))*0.52,2),"") -> #ERROR! | O16: =IFERROR(ROUND((C16/IFERROR(INDEX(Config!B:B,MATCH("TVA "&A16,Config!A:A,0)),1.055))*0.52,2),"") -> #ERROR! | P16: =IFERROR(ROUND((C16/IFERROR(INDEX(Config!B:B,MATCH("TVA "&A16,Config!A:A,0)),1.055))*0.55,2),"") -> #ERROR! | Q16: =IFERROR(ROUND((C16/IFERROR(INDEX(Config!B:B,MATCH("TVA "&A16,Config!A:A,0)),1.055))*0.5,2),"") -> #ERROR! | R16: =IFERROR(ROUND((C16/IFERROR(INDEX(Config!B:B,MATCH("TVA "&A16,Config!A:A,0)),1.055))*0.5,2),"") -> #ERROR! | S16: =IFERROR(ROUND((C16/IFERROR(INDEX(Config!B:B,MATCH("TVA "&A16,Config!A:A,0)),1.055))*0.62,2),"") -> #ERROR! | T16: =IFERROR(ROUND((C16/IFERROR(INDEX(Config!B:B,MATCH("TVA "&A16,Config!A:A,0)),1.055))*0.58,2),"") -> #ERROR! | U16: =IFERROR(ROUND((C16/IFERROR(INDEX(Config!B:B,MATCH("TVA "&A16,Config!A:A,0)),1.055))*0.58,2),"") -> #ERROR! | V16: =IFERROR(((C16/IFERROR(INDEX(Config!B:B,MATCH("TVA "&A16,Config!A:A,0)),1.055))-IFERROR(INDEX('Cout de Revient'!I:I,MATCH(B16,'Cout de Revient'!C:C,0)),0))/(C16/IFERROR(INDEX(Config!B:B,MATCH("TVA "&A16,Config!A:A,0)),1.055)),"") -> #ERROR! | W16: =IFERROR(C16,"") -> #ERROR! | X16: =IFERROR(ROUND(C16*0.85,2),"") -> #ERROR!
A17: RILLETTES — TVA 5%
A18: Rillettes | B18: RR100-290 | C18: 5.9 | D18: =IFERROR(ROUND(C18*0.95,2),"") -> #ERROR! | E18: =IFERROR(ROUND(C18*0.92,2),"") -> #ERROR! | F18: =IFERROR(ROUND(C18*0.88,2),"") -> #ERROR! | G18: =IFERROR(ROUND(C18*1,2),"") -> #ERROR! | H18: =IFERROR(ROUND(C18*0.97,2),"") -> #ERROR! | I18: =IFERROR(ROUND(C18*0.94,2),"") -> #ERROR! | J18: =IFERROR(ROUND((C18/IFERROR(INDEX(Config!B:B,MATCH("TVA "&A18,Config!A:A,0)),1.055))*0.55,2),"") -> #ERROR! | K18: =IFERROR(ROUND((C18/IFERROR(INDEX(Config!B:B,MATCH("TVA "&A18,Config!A:A,0)),1.055))*0.48,2),"") -> #ERROR! | L18: =IFERROR(ROUND((C18/IFERROR(INDEX(Config!B:B,MATCH("TVA "&A18,Config!A:A,0)),1.055))*0.42,2),"") -> #ERROR! | M18: =IFERROR(ROUND((C18/IFERROR(INDEX(Config!B:B,MATCH("TVA "&A18,Config!A:A,0)),1.055))*0.58,2),"") -> #ERROR! | N18: =IFERROR(ROUND((C18/IFERROR(INDEX(Config!B:B,MATCH("TVA "&A18,Config!A:A,0)),1.055))*0.52,2),"") -> #ERROR! | O18: =IFERROR(ROUND((C18/IFERROR(INDEX(Config!B:B,MATCH("TVA "&A18,Config!A:A,0)),1.055))*0.52,2),"") -> #ERROR! | P18: =IFERROR(ROUND((C18/IFERROR(INDEX(Config!B:B,MATCH("TVA "&A18,Config!A:A,0)),1.055))*0.55,2),"") -> #ERROR! | Q18: =IFERROR(ROUND((C18/IFERROR(INDEX(Config!B:B,MATCH("TVA "&A18,Config!A:A,0)),1.055))*0.5,2),"") -> #ERROR! | R18: =IFERROR(ROUND((C18/IFERROR(INDEX(Config!B:B,MATCH("TVA "&A18,Config!A:A,0)),1.055))*0.5,2),"") -> #ERROR! | S18: =IFERROR(ROUND((C18/IFERROR(INDEX(Config!B:B,MATCH("TVA "&A18,Config!A:A,0)),1.055))*0.62,2),"") -> #ERROR! | T18: =IFERROR(ROUND((C18/IFERROR(INDEX(Config!B:B,MATCH("TVA "&A18,Config!A:A,0)),1.055))*0.58,2),"") -> #ERROR! | U18: =IFERROR(ROUND((C18/IFERROR(INDEX(Config!B:B,MATCH("TVA "&A18,Config!A:A,0)),1.055))*0.58,2),"") -> #ERROR! | V18: =IFERROR(((C18/IFERROR(INDEX(Config!B:B,MATCH("TVA "&A18,Config!A:A,0)),1.055))-IFERROR(INDEX('Cout de Revient'!I:I,MATCH(B18,'Cout de Revient'!C:C,0)),0))/(C18/IFERROR(INDEX(Config!B:B,MATCH("TVA "&A18,Config!A:A,0)),1.055)),"") -> #ERROR! | W18: =IFERROR(C18,"") -> #ERROR! | X18: =IFERROR(ROUND(C18*0.85,2),"") -> #ERROR!
A19: Rillettes | B19: RR100-370 | C19: 7.5 | D19: =IFERROR(ROUND(C19*0.95,2),"") -> #ERROR! | E19: =IFERROR(ROUND(C19*0.92,2),"") -> #ERROR! | F19: =IFERROR(ROUND(C19*0.88,2),"") -> #ERROR! | G19: =IFERROR(ROUND(C19*1,2),"") -> #ERROR! | H19: =IFERROR(ROUND(C19*0.97,2),"") -> #ERROR! | I19: =IFERROR(ROUND(C19*0.94,2),"") -> #ERROR! | J19: =IFERROR(ROUND((C19/IFERROR(INDEX(Config!B:B,MATCH("TVA "&A19,Config!A:A,0)),1.055))*0.55,2),"") -> #ERROR! | K19: =IFERROR(ROUND((C19/IFERROR(INDEX(Config!B:B,MATCH("TVA "&A19,Config!A:A,0)),1.055))*0.48,2),"") -> #ERROR! | L19: =IFERROR(ROUND((C19/IFERROR(INDEX(Config!B:B,MATCH("TVA "&A19,Config!A:A,0)),1.055))*0.42,2),"") -> #ERROR! | M19: =IFERROR(ROUND((C19/IFERROR(INDEX(Config!B:B,MATCH("TVA "&A19,Config!A:A,0)),1.055))*0.58,2),"") -> #ERROR! | N19: =IFERROR(ROUND((C19/IFERROR(INDEX(Config!B:B,MATCH("TVA "&A19,Config!A:A,0)),1.055))*0.52,2),"") -> #ERROR! | O19: =IFERROR(ROUND((C19/IFERROR(INDEX(Config!B:B,MATCH("TVA "&A19,Config!A:A,0)),1.055))*0.52,2),"") -> #ERROR! | P19: =IFERROR(ROUND((C19/IFERROR(INDEX(Config!B:B,MATCH("TVA "&A19,Config!A:A,0)),1.055))*0.55,2),"") -> #ERROR! | Q19: =IFERROR(ROUND((C19/IFERROR(INDEX(Config!B:B,MATCH("TVA "&A19,Config!A:A,0)),1.055))*0.5,2),"") -> #ERROR! | R19: =IFERROR(ROUND((C19/IFERROR(INDEX(Config!B:B,MATCH("TVA "&A19,Config!A:A,0)),1.055))*0.5,2),"") -> #ERROR! | S19: =IFERROR(ROUND((C19/IFERROR(INDEX(Config!B:B,MATCH("TVA "&A19,Config!A:A,0)),1.055))*0.62,2),"") -> #ERROR! | T19: =IFERROR(ROUND((C19/IFERROR(INDEX(Config!B:B,MATCH("TVA "&A19,Config!A:A,0)),1.055))*0.58,2),"") -> #ERROR! | U19: =IFERROR(ROUND((C19/IFERROR(INDEX(Config!B:B,MATCH("TVA "&A19,Config!A:A,0)),1.055))*0.58,2),"") -> #ERROR! | V19: =IFERROR(((C19/IFERROR(INDEX(Config!B:B,MATCH("TVA "&A19,Config!A:A,0)),1.055))-IFERROR(INDEX('Cout de Revient'!I:I,MATCH(B19,'Cout de Revient'!C:C,0)),0))/(C19/IFERROR(INDEX(Config!B:B,MATCH("TVA "&A19,Config!A:A,0)),1.055)),"") -> #ERROR! | W19: =IFERROR(C19,"") -> #ERROR! | X19: =IFERROR(ROUND(C19*0.85,2),"") -> #ERROR!
A20: Rillettes | B20: RR100-580 | C20: 9.9 | D20: =IFERROR(ROUND(C20*0.95,2),"") -> #ERROR! | E20: =IFERROR(ROUND(C20*0.92,2),"") -> #ERROR! | F20: =IFERROR(ROUND(C20*0.88,2),"") -> #ERROR! | G20: =IFERROR(ROUND(C20*1,2),"") -> #ERROR! | H20: =IFERROR(ROUND(C20*0.97,2),"") -> #ERROR! | I20: =IFERROR(ROUND(C20*0.94,2),"") -> #ERROR! | J20: =IFERROR(ROUND((C20/IFERROR(INDEX(Config!B:B,MATCH("TVA "&A20,Config!A:A,0)),1.055))*0.55,2),"") -> #ERROR! | K20: =IFERROR(ROUND((C20/IFERROR(INDEX(Config!B:B,MATCH("TVA "&A20,Config!A:A,0)),1.055))*0.48,2),"") -> #ERROR! | L20: =IFERROR(ROUND((C20/IFERROR(INDEX(Config!B:B,MATCH("TVA "&A20,Config!A:A,0)),1.055))*0.42,2),"") -> #ERROR! | M20: =IFERROR(ROUND((C20/IFERROR(INDEX(Config!B:B,MATCH("TVA "&A20,Config!A:A,0)),1.055))*0.58,2),"") -> #ERROR! | N20: =IFERROR(ROUND((C20/IFERROR(INDEX(Config!B:B,MATCH("TVA "&A20,Config!A:A,0)),1.055))*0.52,2),"") -> #ERROR! | O20: =IFERROR(ROUND((C20/IFERROR(INDEX(Config!B:B,MATCH("TVA "&A20,Config!A:A,0)),1.055))*0.52,2),"") -> #ERROR! | P20: =IFERROR(ROUND((C20/IFERROR(INDEX(Config!B:B,MATCH("TVA "&A20,Config!A:A,0)),1.055))*0.55,2),"") -> #ERROR! | Q20: =IFERROR(ROUND((C20/IFERROR(INDEX(Config!B:B,MATCH("TVA "&A20,Config!A:A,0)),1.055))*0.5,2),"") -> #ERROR! | R20: =IFERROR(ROUND((C20/IFERROR(INDEX(Config!B:B,MATCH("TVA "&A20,Config!A:A,0)),1.055))*0.5,2),"") -> #ERROR! | S20: =IFERROR(ROUND((C20/IFERROR(INDEX(Config!B:B,MATCH("TVA "&A20,Config!A:A,0)),1.055))*0.62,2),"") -> #ERROR! | T20: =IFERROR(ROUND((C20/IFERROR(INDEX(Config!B:B,MATCH("TVA "&A20,Config!A:A,0)),1.055))*0.58,2),"") -> #ERROR! | U20: =IFERROR(ROUND((C20/IFERROR(INDEX(Config!B:B,MATCH("TVA "&A20,Config!A:A,0)),1.055))*0.58,2),"") -> #ERROR! | V20: =IFERROR(((C20/IFERROR(INDEX(Config!B:B,MATCH("TVA "&A20,Config!A:A,0)),1.055))-IFERROR(INDEX('Cout de Revient'!I:I,MATCH(B20,'Cout de Revient'!C:C,0)),0))/(C20/IFERROR(INDEX(Config!B:B,MATCH("TVA "&A20,Config!A:A,0)),1.055)),"") -> #ERROR! | W20: =IFERROR(C20,"") -> #ERROR! | X20: =IFERROR(ROUND(C20*0.85,2),"") -> #ERROR!
A21: Rillettes | B21: RR100-850 | C21: 13.5 | D21: =IFERROR(ROUND(C21*0.95,2),"") -> #ERROR! | E21: =IFERROR(ROUND(C21*0.92,2),"") -> #ERROR! | F21: =IFERROR(ROUND(C21*0.88,2),"") -> #ERROR! | G21: =IFERROR(ROUND(C21*1,2),"") -> #ERROR! | H21: =IFERROR(ROUND(C21*0.97,2),"") -> #ERROR! | I21: =IFERROR(ROUND(C21*0.94,2),"") -> #ERROR! | J21: =IFERROR(ROUND((C21/IFERROR(INDEX(Config!B:B,MATCH("TVA "&A21,Config!A:A,0)),1.055))*0.55,2),"") -> #ERROR! | K21: =IFERROR(ROUND((C21/IFERROR(INDEX(Config!B:B,MATCH("TVA "&A21,Config!A:A,0)),1.055))*0.48,2),"") -> #ERROR! | L21: =IFERROR(ROUND((C21/IFERROR(INDEX(Config!B:B,MATCH("TVA "&A21,Config!A:A,0)),1.055))*0.42,2),"") -> #ERROR! | M21: =IFERROR(ROUND((C21/IFERROR(INDEX(Config!B:B,MATCH("TVA "&A21,Config!A:A,0)),1.055))*0.58,2),"") -> #ERROR! | N21: =IFERROR(ROUND((C21/IFERROR(INDEX(Config!B:B,MATCH("TVA "&A21,Config!A:A,0)),1.055))*0.52,2),"") -> #ERROR! | O21: =IFERROR(ROUND((C21/IFERROR(INDEX(Config!B:B,MATCH("TVA "&A21,Config!A:A,0)),1.055))*0.52,2),"") -> #ERROR! | P21: =IFERROR(ROUND((C21/IFERROR(INDEX(Config!B:B,MATCH("TVA "&A21,Config!A:A,0)),1.055))*0.55,2),"") -> #ERROR! | Q21: =IFERROR(ROUND((C21/IFERROR(INDEX(Config!B:B,MATCH("TVA "&A21,Config!A:A,0)),1.055))*0.5,2),"") -> #ERROR! | R21: =IFERROR(ROUND((C21/IFERROR(INDEX(Config!B:B,MATCH("TVA "&A21,Config!A:A,0)),1.055))*0.5,2),"") -> #ERROR! | S21: =IFERROR(ROUND((C21/IFERROR(INDEX(Config!B:B,MATCH("TVA "&A21,Config!A:A,0)),1.055))*0.62,2),"") -> #ERROR! | T21: =IFERROR(ROUND((C21/IFERROR(INDEX(Config!B:B,MATCH("TVA "&A21,Config!A:A,0)),1.055))*0.58,2),"") -> #ERROR! | U21: =IFERROR(ROUND((C21/IFERROR(INDEX(Config!B:B,MATCH("TVA "&A21,Config!A:A,0)),1.055))*0.58,2),"") -> #ERROR! | V21: =IFERROR(((C21/IFERROR(INDEX(Config!B:B,MATCH("TVA "&A21,Config!A:A,0)),1.055))-IFERROR(INDEX('Cout de Revient'!I:I,MATCH(B21,'Cout de Revient'!C:C,0)),0))/(C21/IFERROR(INDEX(Config!B:B,MATCH("TVA "&A21,Config!A:A,0)),1.055)),"") -> #ERROR! | W21: =IFERROR(C21,"") -> #ERROR! | X21: =IFERROR(ROUND(C21*0.85,2),"") -> #ERROR!
A22: Rillettes | B22: RR100-1050 | C22: 17.5 | D22: =IFERROR(ROUND(C22*0.95,2),"") -> #ERROR! | E22: =IFERROR(ROUND(C22*0.92,2),"") -> #ERROR! | F22: =IFERROR(ROUND(C22*0.88,2),"") -> #ERROR! | G22: =IFERROR(ROUND(C22*1,2),"") -> #ERROR! | H22: =IFERROR(ROUND(C22*0.97,2),"") -> #ERROR! | I22: =IFERROR(ROUND(C22*0.94,2),"") -> #ERROR! | J22: =IFERROR(ROUND((C22/IFERROR(INDEX(Config!B:B,MATCH("TVA "&A22,Config!A:A,0)),1.055))*0.55,2),"") -> #ERROR! | K22: =IFERROR(ROUND((C22/IFERROR(INDEX(Config!B:B,MATCH("TVA "&A22,Config!A:A,0)),1.055))*0.48,2),"") -> #ERROR! | L22: =IFERROR(ROUND((C22/IFERROR(INDEX(Config!B:B,MATCH("TVA "&A22,Config!A:A,0)),1.055))*0.42,2),"") -> #ERROR! | M22: =IFERROR(ROUND((C22/IFERROR(INDEX(Config!B:B,MATCH("TVA "&A22,Config!A:A,0)),1.055))*0.58,2),"") -> #ERROR! | N22: =IFERROR(ROUND((C22/IFERROR(INDEX(Config!B:B,MATCH("TVA "&A22,Config!A:A,0)),1.055))*0.52,2),"") -> #ERROR! | O22: =IFERROR(ROUND((C22/IFERROR(INDEX(Config!B:B,MATCH("TVA "&A22,Config!A:A,0)),1.055))*0.52,2),"") -> #ERROR! | P22: =IFERROR(ROUND((C22/IFERROR(INDEX(Config!B:B,MATCH("TVA "&A22,Config!A:A,0)),1.055))*0.55,2),"") -> #ERROR! | Q22: =IFERROR(ROUND((C22/IFERROR(INDEX(Config!B:B,MATCH("TVA "&A22,Config!A:A,0)),1.055))*0.5,2),"") -> #ERROR! | R22: =IFERROR(ROUND((C22/IFERROR(INDEX(Config!B:B,MATCH("TVA "&A22,Config!A:A,0)),1.055))*0.5,2),"") -> #ERROR! | S22: =IFERROR(ROUND((C22/IFERROR(INDEX(Config!B:B,MATCH("TVA "&A22,Config!A:A,0)),1.055))*0.62,2),"") -> #ERROR! | T22: =IFERROR(ROUND((C22/IFERROR(INDEX(Config!B:B,MATCH("TVA "&A22,Config!A:A,0)),1.055))*0.58,2),"") -> #ERROR! | U22: =IFERROR(ROUND((C22/IFERROR(INDEX(Config!B:B,MATCH("TVA "&A22,Config!A:A,0)),1.055))*0.58,2),"") -> #ERROR! | V22: =IFERROR(((C22/IFERROR(INDEX(Config!B:B,MATCH("TVA "&A22,Config!A:A,0)),1.055))-IFERROR(INDEX('Cout de Revient'!I:I,MATCH(B22,'Cout de Revient'!C:C,0)),0))/(C22/IFERROR(INDEX(Config!B:B,MATCH("TVA "&A22,Config!A:A,0)),1.055)),"") -> #ERROR! | W22: =IFERROR(C22,"") -> #ERROR! | X22: =IFERROR(ROUND(C22*0.85,2),"") -> #ERROR!
A23: Rillettes | B23: RR100-1550 | C23: 24.5 | D23: =IFERROR(ROUND(C23*0.95,2),"") -> #ERROR! | E23: =IFERROR(ROUND(C23*0.92,2),"") -> #ERROR! | F23: =IFERROR(ROUND(C23*0.88,2),"") -> #ERROR! | G23: =IFERROR(ROUND(C23*1,2),"") -> #ERROR! | H23: =IFERROR(ROUND(C23*0.97,2),"") -> #ERROR! | I23: =IFERROR(ROUND(C23*0.94,2),"") -> #ERROR! | J23: =IFERROR(ROUND((C23/IFERROR(INDEX(Config!B:B,MATCH("TVA "&A23,Config!A:A,0)),1.055))*0.55,2),"") -> #ERROR! | K23: =IFERROR(ROUND((C23/IFERROR(INDEX(Config!B:B,MATCH("TVA "&A23,Config!A:A,0)),1.055))*0.48,2),"") -> #ERROR! | L23: =IFERROR(ROUND((C23/IFERROR(INDEX(Config!B:B,MATCH("TVA "&A23,Config!A:A,0)),1.055))*0.42,2),"") -> #ERROR! | M23: =IFERROR(ROUND((C23/IFERROR(INDEX(Config!B:B,MATCH("TVA "&A23,Config!A:A,0)),1.055))*0.58,2),"") -> #ERROR! | N23: =IFERROR(ROUND((C23/IFERROR(INDEX(Config!B:B,MATCH("TVA "&A23,Config!A:A,0)),1.055))*0.52,2),"") -> #ERROR! | O23: =IFERROR(ROUND((C23/IFERROR(INDEX(Config!B:B,MATCH("TVA "&A23,Config!A:A,0)),1.055))*0.52,2),"") -> #ERROR! | P23: =IFERROR(ROUND((C23/IFERROR(INDEX(Config!B:B,MATCH("TVA "&A23,Config!A:A,0)),1.055))*0.55,2),"") -> #ERROR! | Q23: =IFERROR(ROUND((C23/IFERROR(INDEX(Config!B:B,MATCH("TVA "&A23,Config!A:A,0)),1.055))*0.5,2),"") -> #ERROR! | R23: =IFERROR(ROUND((C23/IFERROR(INDEX(Config!B:B,MATCH("TVA "&A23,Config!A:A,0)),1.055))*0.5,2),"") -> #ERROR! | S23: =IFERROR(ROUND((C23/IFERROR(INDEX(Config!B:B,MATCH("TVA "&A23,Config!A:A,0)),1.055))*0.62,2),"") -> #ERROR! | T23: =IFERROR(ROUND((C23/IFERROR(INDEX(Config!B:B,MATCH("TVA "&A23,Config!A:A,0)),1.055))*0.58,2),"") -> #ERROR! | U23: =IFERROR(ROUND((C23/IFERROR(INDEX(Config!B:B,MATCH("TVA "&A23,Config!A:A,0)),1.055))*0.58,2),"") -> #ERROR! | V23: =IFERROR(((C23/IFERROR(INDEX(Config!B:B,MATCH("TVA "&A23,Config!A:A,0)),1.055))-IFERROR(INDEX('Cout de Revient'!I:I,MATCH(B23,'Cout de Revient'!C:C,0)),0))/(C23/IFERROR(INDEX(Config!B:B,MATCH("TVA "&A23,Config!A:A,0)),1.055)),"") -> #ERROR! | W23: =IFERROR(C23,"") -> #ERROR! | X23: =IFERROR(ROUND(C23*0.85,2),"") -> #ERROR!
A24: Rillettes | B24: W60-050 | C24: 2.5 | D24: =IFERROR(ROUND(C24*0.95,2),"") -> #ERROR! | E24: =IFERROR(ROUND(C24*0.92,2),"") -> #ERROR! | F24: =IFERROR(ROUND(C24*0.88,2),"") -> #ERROR! | G24: =IFERROR(ROUND(C24*1,2),"") -> #ERROR! | H24: =IFERROR(ROUND(C24*0.97,2),"") -> #ERROR! | I24: =IFERROR(ROUND(C24*0.94,2),"") -> #ERROR! | J24: =IFERROR(ROUND((C24/IFERROR(INDEX(Config!B:B,MATCH("TVA "&A24,Config!A:A,0)),1.055))*0.55,2),"") -> #ERROR! | K24: =IFERROR(ROUND((C24/IFERROR(INDEX(Config!B:B,MATCH("TVA "&A24,Config!A:A,0)),1.055))*0.48,2),"") -> #ERROR! | L24: =IFERROR(ROUND((C24/IFERROR(INDEX(Config!B:B,MATCH("TVA "&A24,Config!A:A,0)),1.055))*0.42,2),"") -> #ERROR! | M24: =IFERROR(ROUND((C24/IFERROR(INDEX(Config!B:B,MATCH("TVA "&A24,Config!A:A,0)),1.055))*0.58,2),"") -> #ERROR! | N24: =IFERROR(ROUND((C24/IFERROR(INDEX(Config!B:B,MATCH("TVA "&A24,Config!A:A,0)),1.055))*0.52,2),"") -> #ERROR! | O24: =IFERROR(ROUND((C24/IFERROR(INDEX(Config!B:B,MATCH("TVA "&A24,Config!A:A,0)),1.055))*0.52,2),"") -> #ERROR! | P24: =IFERROR(ROUND((C24/IFERROR(INDEX(Config!B:B,MATCH("TVA "&A24,Config!A:A,0)),1.055))*0.55,2),"") -> #ERROR! | Q24: =IFERROR(ROUND((C24/IFERROR(INDEX(Config!B:B,MATCH("TVA "&A24,Config!A:A,0)),1.055))*0.5,2),"") -> #ERROR! | R24: =IFERROR(ROUND((C24/IFERROR(INDEX(Config!B:B,MATCH("TVA "&A24,Config!A:A,0)),1.055))*0.5,2),"") -> #ERROR! | S24: =IFERROR(ROUND((C24/IFERROR(INDEX(Config!B:B,MATCH("TVA "&A24,Config!A:A,0)),1.055))*0.62,2),"") -> #ERROR! | T24: =IFERROR(ROUND((C24/IFERROR(INDEX(Config!B:B,MATCH("TVA "&A24,Config!A:A,0)),1.055))*0.58,2),"") -> #ERROR! | U24: =IFERROR(ROUND((C24/IFERROR(INDEX(Config!B:B,MATCH("TVA "&A24,Config!A:A,0)),1.055))*0.58,2),"") -> #ERROR! | V24: =IFERROR(((C24/IFERROR(INDEX(Config!B:B,MATCH("TVA "&A24,Config!A:A,0)),1.055))-IFERROR(INDEX('Cout de Revient'!I:I,MATCH(B24,'Cout de Revient'!C:C,0)),0))/(C24/IFERROR(INDEX(Config!B:B,MATCH("TVA "&A24,Config!A:A,0)),1.055)),"") -> #ERROR! | W24: =IFERROR(C24,"") -> #ERROR! | X24: =IFERROR(ROUND(C24*0.85,2),"") -> #ERROR!
A25: Rillettes | B25: W60-080 | C25: 3.5 | D25: =IFERROR(ROUND(C25*0.95,2),"") -> #ERROR! | E25: =IFERROR(ROUND(C25*0.92,2),"") -> #ERROR! | F25: =IFERROR(ROUND(C25*0.88,2),"") -> #ERROR! | G25: =IFERROR(ROUND(C25*1,2),"") -> #ERROR! | H25: =IFERROR(ROUND(C25*0.97,2),"") -> #ERROR! | I25: =IFERROR(ROUND(C25*0.94,2),"") -> #ERROR! | J25: =IFERROR(ROUND((C25/IFERROR(INDEX(Config!B:B,MATCH("TVA "&A25,Config!A:A,0)),1.055))*0.55,2),"") -> #ERROR! | K25: =IFERROR(ROUND((C25/IFERROR(INDEX(Config!B:B,MATCH("TVA "&A25,Config!A:A,0)),1.055))*0.48,2),"") -> #ERROR! | L25: =IFERROR(ROUND((C25/IFERROR(INDEX(Config!B:B,MATCH("TVA "&A25,Config!A:A,0)),1.055))*0.42,2),"") -> #ERROR! | M25: =IFERROR(ROUND((C25/IFERROR(INDEX(Config!B:B,MATCH("TVA "&A25,Config!A:A,0)),1.055))*0.58,2),"") -> #ERROR! | N25: =IFERROR(ROUND((C25/IFERROR(INDEX(Config!B:B,MATCH("TVA "&A25,Config!A:A,0)),1.055))*0.52,2),"") -> #ERROR! | O25: =IFERROR(ROUND((C25/IFERROR(INDEX(Config!B:B,MATCH("TVA "&A25,Config!A:A,0)),1.055))*0.52,2),"") -> #ERROR! | P25: =IFERROR(ROUND((C25/IFERROR(INDEX(Config!B:B,MATCH("TVA "&A25,Config!A:A,0)),1.055))*0.55,2),"") -> #ERROR! | Q25: =IFERROR(ROUND((C25/IFERROR(INDEX(Config!B:B,MATCH("TVA "&A25,Config!A:A,0)),1.055))*0.5,2),"") -> #ERROR! | R25: =IFERROR(ROUND((C25/IFERROR(INDEX(Config!B:B,MATCH("TVA "&A25,Config!A:A,0)),1.055))*0.5,2),"") -> #ERROR! | S25: =IFERROR(ROUND((C25/IFERROR(INDEX(Config!B:B,MATCH("TVA "&A25,Config!A:A,0)),1.055))*0.62,2),"") -> #ERROR! | T25: =IFERROR(ROUND((C25/IFERROR(INDEX(Config!B:B,MATCH("TVA "&A25,Config!A:A,0)),1.055))*0.58,2),"") -> #ERROR! | U25: =IFERROR(ROUND((C25/IFERROR(INDEX(Config!B:B,MATCH("TVA "&A25,Config!A:A,0)),1.055))*0.58,2),"") -> #ERROR! | V25: =IFERROR(((C25/IFERROR(INDEX(Config!B:B,MATCH("TVA "&A25,Config!A:A,0)),1.055))-IFERROR(INDEX('Cout de Revient'!I:I,MATCH(B25,'Cout de Revient'!C:C,0)),0))/(C25/IFERROR(INDEX(Config!B:B,MATCH("TVA "&A25,Config!A:A,0)),1.055)),"") -> #ERROR! | W25: =IFERROR(C25,"") -> #ERROR! | X25: =IFERROR(ROUND(C25*0.85,2),"") -> #ERROR!
A26: Rillettes | B26: W60-160 | C26: 4.9 | D26: =IFERROR(ROUND(C26*0.95,2),"") -> #ERROR! | E26: =IFERROR(ROUND(C26*0.92,2),"") -> #ERROR! | F26: =IFERROR(ROUND(C26*0.88,2),"") -> #ERROR! | G26: =IFERROR(ROUND(C26*1,2),"") -> #ERROR! | H26: =IFERROR(ROUND(C26*0.97,2),"") -> #ERROR! | I26: =IFERROR(ROUND(C26*0.94,2),"") -> #ERROR! | J26: =IFERROR(ROUND((C26/IFERROR(INDEX(Config!B:B,MATCH("TVA "&A26,Config!A:A,0)),1.055))*0.55,2),"") -> #ERROR! | K26: =IFERROR(ROUND((C26/IFERROR(INDEX(Config!B:B,MATCH("TVA "&A26,Config!A:A,0)),1.055))*0.48,2),"") -> #ERROR! | L26: =IFERROR(ROUND((C26/IFERROR(INDEX(Config!B:B,MATCH("TVA "&A26,Config!A:A,0)),1.055))*0.42,2),"") -> #ERROR! | M26: =IFERROR(ROUND((C26/IFERROR(INDEX(Config!B:B,MATCH("TVA "&A26,Config!A:A,0)),1.055))*0.58,2),"") -> #ERROR! | N26: =IFERROR(ROUND((C26/IFERROR(INDEX(Config!B:B,MATCH("TVA "&A26,Config!A:A,0)),1.055))*0.52,2),"") -> #ERROR! | O26: =IFERROR(ROUND((C26/IFERROR(INDEX(Config!B:B,MATCH("TVA "&A26,Config!A:A,0)),1.055))*0.52,2),"") -> #ERROR! | P26: =IFERROR(ROUND((C26/IFERROR(INDEX(Config!B:B,MATCH("TVA "&A26,Config!A:A,0)),1.055))*0.55,2),"") -> #ERROR! | Q26: =IFERROR(ROUND((C26/IFERROR(INDEX(Config!B:B,MATCH("TVA "&A26,Config!A:A,0)),1.055))*0.5,2),"") -> #ERROR! | R26: =IFERROR(ROUND((C26/IFERROR(INDEX(Config!B:B,MATCH("TVA "&A26,Config!A:A,0)),1.055))*0.5,2),"") -> #ERROR! | S26: =IFERROR(ROUND((C26/IFERROR(INDEX(Config!B:B,MATCH("TVA "&A26,Config!A:A,0)),1.055))*0.62,2),"") -> #ERROR! | T26: =IFERROR(ROUND((C26/IFERROR(INDEX(Config!B:B,MATCH("TVA "&A26,Config!A:A,0)),1.055))*0.58,2),"") -> #ERROR! | U26: =IFERROR(ROUND((C26/IFERROR(INDEX(Config!B:B,MATCH("TVA "&A26,Config!A:A,0)),1.055))*0.58,2),"") -> #ERROR! | V26: =IFERROR(((C26/IFERROR(INDEX(Config!B:B,MATCH("TVA "&A26,Config!A:A,0)),1.055))-IFERROR(INDEX('Cout de Revient'!I:I,MATCH(B26,'Cout de Revient'!C:C,0)),0))/(C26/IFERROR(INDEX(Config!B:B,MATCH("TVA "&A26,Config!A:A,0)),1.055)),"") -> #ERROR! | W26: =IFERROR(C26,"") -> #ERROR! | X26: =IFERROR(ROUND(C26*0.85,2),"") -> #ERROR!
A27: MOUSSES — TVA 5%
A28: Mousses | B28: RR100-290 | C28: 5.5 | D28: =IFERROR(ROUND(C28*0.95,2),"") -> #ERROR! | E28: =IFERROR(ROUND(C28*0.92,2),"") -> #ERROR! | F28: =IFERROR(ROUND(C28*0.88,2),"") -> #ERROR! | G28: =IFERROR(ROUND(C28*1,2),"") -> #ERROR! | H28: =IFERROR(ROUND(C28*0.97,2),"") -> #ERROR! | I28: =IFERROR(ROUND(C28*0.94,2),"") -> #ERROR! | J28: =IFERROR(ROUND((C28/IFERROR(INDEX(Config!B:B,MATCH("TVA "&A28,Config!A:A,0)),1.055))*0.55,2),"") -> #ERROR! | K28: =IFERROR(ROUND((C28/IFERROR(INDEX(Config!B:B,MATCH("TVA "&A28,Config!A:A,0)),1.055))*0.48,2),"") -> #ERROR! | L28: =IFERROR(ROUND((C28/IFERROR(INDEX(Config!B:B,MATCH("TVA "&A28,Config!A:A,0)),1.055))*0.42,2),"") -> #ERROR! | M28: =IFERROR(ROUND((C28/IFERROR(INDEX(Config!B:B,MATCH("TVA "&A28,Config!A:A,0)),1.055))*0.58,2),"") -> #ERROR! | N28: =IFERROR(ROUND((C28/IFERROR(INDEX(Config!B:B,MATCH("TVA "&A28,Config!A:A,0)),1.055))*0.52,2),"") -> #ERROR! | O28: =IFERROR(ROUND((C28/IFERROR(INDEX(Config!B:B,MATCH("TVA "&A28,Config!A:A,0)),1.055))*0.52,2),"") -> #ERROR! | P28: =IFERROR(ROUND((C28/IFERROR(INDEX(Config!B:B,MATCH("TVA "&A28,Config!A:A,0)),1.055))*0.55,2),"") -> #ERROR! | Q28: =IFERROR(ROUND((C28/IFERROR(INDEX(Config!B:B,MATCH("TVA "&A28,Config!A:A,0)),1.055))*0.5,2),"") -> #ERROR! | R28: =IFERROR(ROUND((C28/IFERROR(INDEX(Config!B:B,MATCH("TVA "&A28,Config!A:A,0)),1.055))*0.5,2),"") -> #ERROR! | S28: =IFERROR(ROUND((C28/IFERROR(INDEX(Config!B:B,MATCH("TVA "&A28,Config!A:A,0)),1.055))*0.62,2),"") -> #ERROR! | T28: =IFERROR(ROUND((C28/IFERROR(INDEX(Config!B:B,MATCH("TVA "&A28,Config!A:A,0)),1.055))*0.58,2),"") -> #ERROR! | U28: =IFERROR(ROUND((C28/IFERROR(INDEX(Config!B:B,MATCH("TVA "&A28,Config!A:A,0)),1.055))*0.58,2),"") -> #ERROR! | V28: =IFERROR(((C28/IFERROR(INDEX(Config!B:B,MATCH("TVA "&A28,Config!A:A,0)),1.055))-IFERROR(INDEX('Cout de Revient'!I:I,MATCH(B28,'Cout de Revient'!C:C,0)),0))/(C28/IFERROR(INDEX(Config!B:B,MATCH("TVA "&A28,Config!A:A,0)),1.055)),"") -> #ERROR! | W28: =IFERROR(C28,"") -> #ERROR! | X28: =IFERROR(ROUND(C28*0.85,2),"") -> #ERROR!
A29: Mousses | B29: RR100-370 | C29: 6.9 | D29: =IFERROR(ROUND(C29*0.95,2),"") -> #ERROR! | E29: =IFERROR(ROUND(C29*0.92,2),"") -> #ERROR! | F29: =IFERROR(ROUND(C29*0.88,2),"") -> #ERROR! | G29: =IFERROR(ROUND(C29*1,2),"") -> #ERROR! | H29: =IFERROR(ROUND(C29*0.97,2),"") -> #ERROR! | I29: =IFERROR(ROUND(C29*0.94,2),"") -> #ERROR! | J29: =IFERROR(ROUND((C29/IFERROR(INDEX(Config!B:B,MATCH("TVA "&A29,Config!A:A,0)),1.055))*0.55,2),"") -> #ERROR! | K29: =IFERROR(ROUND((C29/IFERROR(INDEX(Config!B:B,MATCH("TVA "&A29,Config!A:A,0)),1.055))*0.48,2),"") -> #ERROR! | L29: =IFERROR(ROUND((C29/IFERROR(INDEX(Config!B:B,MATCH("TVA "&A29,Config!A:A,0)),1.055))*0.42,2),"") -> #ERROR! | M29: =IFERROR(ROUND((C29/IFERROR(INDEX(Config!B:B,MATCH("TVA "&A29,Config!A:A,0)),1.055))*0.58,2),"") -> #ERROR! | N29: =IFERROR(ROUND((C29/IFERROR(INDEX(Config!B:B,MATCH("TVA "&A29,Config!A:A,0)),1.055))*0.52,2),"") -> #ERROR! | O29: =IFERROR(ROUND((C29/IFERROR(INDEX(Config!B:B,MATCH("TVA "&A29,Config!A:A,0)),1.055))*0.52,2),"") -> #ERROR! | P29: =IFERROR(ROUND((C29/IFERROR(INDEX(Config!B:B,MATCH("TVA "&A29,Config!A:A,0)),1.055))*0.55,2),"") -> #ERROR! | Q29: =IFERROR(ROUND((C29/IFERROR(INDEX(Config!B:B,MATCH("TVA "&A29,Config!A:A,0)),1.055))*0.5,2),"") -> #ERROR! | R29: =IFERROR(ROUND((C29/IFERROR(INDEX(Config!B:B,MATCH("TVA "&A29,Config!A:A,0)),1.055))*0.5,2),"") -> #ERROR! | S29: =IFERROR(ROUND((C29/IFERROR(INDEX(Config!B:B,MATCH("TVA "&A29,Config!A:A,0)),1.055))*0.62,2),"") -> #ERROR! | T29: =IFERROR(ROUND((C29/IFERROR(INDEX(Config!B:B,MATCH("TVA "&A29,Config!A:A,0)),1.055))*0.58,2),"") -> #ERROR! | U29: =IFERROR(ROUND((C29/IFERROR(INDEX(Config!B:B,MATCH("TVA "&A29,Config!A:A,0)),1.055))*0.58,2),"") -> #ERROR! | V29: =IFERROR(((C29/IFERROR(INDEX(Config!B:B,MATCH("TVA "&A29,Config!A:A,0)),1.055))-IFERROR(INDEX('Cout de Revient'!I:I,MATCH(B29,'Cout de Revient'!C:C,0)),0))/(C29/IFERROR(INDEX(Config!B:B,MATCH("TVA "&A29,Config!A:A,0)),1.055)),"") -> #ERROR! | W29: =IFERROR(C29,"") -> #ERROR! | X29: =IFERROR(ROUND(C29*0.85,2),"") -> #ERROR!
A30: Mousses | B30: RR100-580 | C30: 8.9 | D30: =IFERROR(ROUND(C30*0.95,2),"") -> #ERROR! | E30: =IFERROR(ROUND(C30*0.92,2),"") -> #ERROR! | F30: =IFERROR(ROUND(C30*0.88,2),"") -> #ERROR! | G30: =IFERROR(ROUND(C30*1,2),"") -> #ERROR! | H30: =IFERROR(ROUND(C30*0.97,2),"") -> #ERROR! | I30: =IFERROR(ROUND(C30*0.94,2),"") -> #ERROR! | J30: =IFERROR(ROUND((C30/IFERROR(INDEX(Config!B:B,MATCH("TVA "&A30,Config!A:A,0)),1.055))*0.55,2),"") -> #ERROR! | K30: =IFERROR(ROUND((C30/IFERROR(INDEX(Config!B:B,MATCH("TVA "&A30,Config!A:A,0)),1.055))*0.48,2),"") -> #ERROR! | L30: =IFERROR(ROUND((C30/IFERROR(INDEX(Config!B:B,MATCH("TVA "&A30,Config!A:A,0)),1.055))*0.42,2),"") -> #ERROR! | M30: =IFERROR(ROUND((C30/IFERROR(INDEX(Config!B:B,MATCH("TVA "&A30,Config!A:A,0)),1.055))*0.58,2),"") -> #ERROR! | N30: =IFERROR(ROUND((C30/IFERROR(INDEX(Config!B:B,MATCH("TVA "&A30,Config!A:A,0)),1.055))*0.52,2),"") -> #ERROR! | O30: =IFERROR(ROUND((C30/IFERROR(INDEX(Config!B:B,MATCH("TVA "&A30,Config!A:A,0)),1.055))*0.52,2),"") -> #ERROR! | P30: =IFERROR(ROUND((C30/IFERROR(INDEX(Config!B:B,MATCH("TVA "&A30,Config!A:A,0)),1.055))*0.55,2),"") -> #ERROR! | Q30: =IFERROR(ROUND((C30/IFERROR(INDEX(Config!B:B,MATCH("TVA "&A30,Config!A:A,0)),1.055))*0.5,2),"") -> #ERROR! | R30: =IFERROR(ROUND((C30/IFERROR(INDEX(Config!B:B,MATCH("TVA "&A30,Config!A:A,0)),1.055))*0.5,2),"") -> #ERROR! | S30: =IFERROR(ROUND((C30/IFERROR(INDEX(Config!B:B,MATCH("TVA "&A30,Config!A:A,0)),1.055))*0.62,2),"") -> #ERROR! | T30: =IFERROR(ROUND((C30/IFERROR(INDEX(Config!B:B,MATCH("TVA "&A30,Config!A:A,0)),1.055))*0.58,2),"") -> #ERROR! | U30: =IFERROR(ROUND((C30/IFERROR(INDEX(Config!B:B,MATCH("TVA "&A30,Config!A:A,0)),1.055))*0.58,2),"") -> #ERROR! | V30: =IFERROR(((C30/IFERROR(INDEX(Config!B:B,MATCH("TVA "&A30,Config!A:A,0)),1.055))-IFERROR(INDEX('Cout de Revient'!I:I,MATCH(B30,'Cout de Revient'!C:C,0)),0))/(C30/IFERROR(INDEX(Config!B:B,MATCH("TVA "&A30,Config!A:A,0)),1.055)),"") -> #ERROR! | W30: =IFERROR(C30,"") -> #ERROR! | X30: =IFERROR(ROUND(C30*0.85,2),"") -> #ERROR!
A31: Mousses | B31: RR100-850 | C31: 12.9 | D31: =IFERROR(ROUND(C31*0.95,2),"") -> #ERROR! | E31: =IFERROR(ROUND(C31*0.92,2),"") -> #ERROR! | F31: =IFERROR(ROUND(C31*0.88,2),"") -> #ERROR! | G31: =IFERROR(ROUND(C31*1,2),"") -> #ERROR! | H31: =IFERROR(ROUND(C31*0.97,2),"") -> #ERROR! | I31: =IFERROR(ROUND(C31*0.94,2),"") -> #ERROR! | J31: =IFERROR(ROUND((C31/IFERROR(INDEX(Config!B:B,MATCH("TVA "&A31,Config!A:A,0)),1.055))*0.55,2),"") -> #ERROR! | K31: =IFERROR(ROUND((C31/IFERROR(INDEX(Config!B:B,MATCH("TVA "&A31,Config!A:A,0)),1.055))*0.48,2),"") -> #ERROR! | L31: =IFERROR(ROUND((C31/IFERROR(INDEX(Config!B:B,MATCH("TVA "&A31,Config!A:A,0)),1.055))*0.42,2),"") -> #ERROR! | M31: =IFERROR(ROUND((C31/IFERROR(INDEX(Config!B:B,MATCH("TVA "&A31,Config!A:A,0)),1.055))*0.58,2),"") -> #ERROR! | N31: =IFERROR(ROUND((C31/IFERROR(INDEX(Config!B:B,MATCH("TVA "&A31,Config!A:A,0)),1.055))*0.52,2),"") -> #ERROR! | O31: =IFERROR(ROUND((C31/IFERROR(INDEX(Config!B:B,MATCH("TVA "&A31,Config!A:A,0)),1.055))*0.52,2),"") -> #ERROR! | P31: =IFERROR(ROUND((C31/IFERROR(INDEX(Config!B:B,MATCH("TVA "&A31,Config!A:A,0)),1.055))*0.55,2),"") -> #ERROR! | Q31: =IFERROR(ROUND((C31/IFERROR(INDEX(Config!B:B,MATCH("TVA "&A31,Config!A:A,0)),1.055))*0.5,2),"") -> #ERROR! | R31: =IFERROR(ROUND((C31/IFERROR(INDEX(Config!B:B,MATCH("TVA "&A31,Config!A:A,0)),1.055))*0.5,2),"") -> #ERROR! | S31: =IFERROR(ROUND((C31/IFERROR(INDEX(Config!B:B,MATCH("TVA "&A31,Config!A:A,0)),1.055))*0.62,2),"") -> #ERROR! | T31: =IFERROR(ROUND((C31/IFERROR(INDEX(Config!B:B,MATCH("TVA "&A31,Config!A:A,0)),1.055))*0.58,2),"") -> #ERROR! | U31: =IFERROR(ROUND((C31/IFERROR(INDEX(Config!B:B,MATCH("TVA "&A31,Config!A:A,0)),1.055))*0.58,2),"") -> #ERROR! | V31: =IFERROR(((C31/IFERROR(INDEX(Config!B:B,MATCH("TVA "&A31,Config!A:A,0)),1.055))-IFERROR(INDEX('Cout de Revient'!I:I,MATCH(B31,'Cout de Revient'!C:C,0)),0))/(C31/IFERROR(INDEX(Config!B:B,MATCH("TVA "&A31,Config!A:A,0)),1.055)),"") -> #ERROR! | W31: =IFERROR(C31,"") -> #ERROR! | X31: =IFERROR(ROUND(C31*0.85,2),"") -> #ERROR!
A32: Mousses | B32: RR100-1050 | C32: 16.9 | D32: =IFERROR(ROUND(C32*0.95,2),"") -> #ERROR! | E32: =IFERROR(ROUND(C32*0.92,2),"") -> #ERROR! | F32: =IFERROR(ROUND(C32*0.88,2),"") -> #ERROR! | G32: =IFERROR(ROUND(C32*1,2),"") -> #ERROR! | H32: =IFERROR(ROUND(C32*0.97,2),"") -> #ERROR! | I32: =IFERROR(ROUND(C32*0.94,2),"") -> #ERROR! | J32: =IFERROR(ROUND((C32/IFERROR(INDEX(Config!B:B,MATCH("TVA "&A32,Config!A:A,0)),1.055))*0.55,2),"") -> #ERROR! | K32: =IFERROR(ROUND((C32/IFERROR(INDEX(Config!B:B,MATCH("TVA "&A32,Config!A:A,0)),1.055))*0.48,2),"") -> #ERROR! | L32: =IFERROR(ROUND((C32/IFERROR(INDEX(Config!B:B,MATCH("TVA "&A32,Config!A:A,0)),1.055))*0.42,2),"") -> #ERROR! | M32: =IFERROR(ROUND((C32/IFERROR(INDEX(Config!B:B,MATCH("TVA "&A32,Config!A:A,0)),1.055))*0.58,2),"") -> #ERROR! | N32: =IFERROR(ROUND((C32/IFERROR(INDEX(Config!B:B,MATCH("TVA "&A32,Config!A:A,0)),1.055))*0.52,2),"") -> #ERROR! | O32: =IFERROR(ROUND((C32/IFERROR(INDEX(Config!B:B,MATCH("TVA "&A32,Config!A:A,0)),1.055))*0.52,2),"") -> #ERROR! | P32: =IFERROR(ROUND((C32/IFERROR(INDEX(Config!B:B,MATCH("TVA "&A32,Config!A:A,0)),1.055))*0.55,2),"") -> #ERROR! | Q32: =IFERROR(ROUND((C32/IFERROR(INDEX(Config!B:B,MATCH("TVA "&A32,Config!A:A,0)),1.055))*0.5,2),"") -> #ERROR! | R32: =IFERROR(ROUND((C32/IFERROR(INDEX(Config!B:B,MATCH("TVA "&A32,Config!A:A,0)),1.055))*0.5,2),"") -> #ERROR! | S32: =IFERROR(ROUND((C32/IFERROR(INDEX(Config!B:B,MATCH("TVA "&A32,Config!A:A,0)),1.055))*0.62,2),"") -> #ERROR! | T32: =IFERROR(ROUND((C32/IFERROR(INDEX(Config!B:B,MATCH("TVA "&A32,Config!A:A,0)),1.055))*0.58,2),"") -> #ERROR! | U32: =IFERROR(ROUND((C32/IFERROR(INDEX(Config!B:B,MATCH("TVA "&A32,Config!A:A,0)),1.055))*0.58,2),"") -> #ERROR! | V32: =IFERROR(((C32/IFERROR(INDEX(Config!B:B,MATCH("TVA "&A32,Config!A:A,0)),1.055))-IFERROR(INDEX('Cout de Revient'!I:I,MATCH(B32,'Cout de Revient'!C:C,0)),0))/(C32/IFERROR(INDEX(Config!B:B,MATCH("TVA "&A32,Config!A:A,0)),1.055)),"") -> #ERROR! | W32: =IFERROR(C32,"") -> #ERROR! | X32: =IFERROR(ROUND(C32*0.85,2),"") -> #ERROR!
A33: Mousses | B33: RR100-1550 | C33: 22.9 | D33: =IFERROR(ROUND(C33*0.95,2),"") -> #ERROR! | E33: =IFERROR(ROUND(C33*0.92,2),"") -> #ERROR! | F33: =IFERROR(ROUND(C33*0.88,2),"") -> #ERROR! | G33: =IFERROR(ROUND(C33*1,2),"") -> #ERROR! | H33: =IFERROR(ROUND(C33*0.97,2),"") -> #ERROR! | I33: =IFERROR(ROUND(C33*0.94,2),"") -> #ERROR! | J33: =IFERROR(ROUND((C33/IFERROR(INDEX(Config!B:B,MATCH("TVA "&A33,Config!A:A,0)),1.055))*0.55,2),"") -> #ERROR! | K33: =IFERROR(ROUND((C33/IFERROR(INDEX(Config!B:B,MATCH("TVA "&A33,Config!A:A,0)),1.055))*0.48,2),"") -> #ERROR! | L33: =IFERROR(ROUND((C33/IFERROR(INDEX(Config!B:B,MATCH("TVA "&A33,Config!A:A,0)),1.055))*0.42,2),"") -> #ERROR! | M33: =IFERROR(ROUND((C33/IFERROR(INDEX(Config!B:B,MATCH("TVA "&A33,Config!A:A,0)),1.055))*0.58,2),"") -> #ERROR! | N33: =IFERROR(ROUND((C33/IFERROR(INDEX(Config!B:B,MATCH("TVA "&A33,Config!A:A,0)),1.055))*0.52,2),"") -> #ERROR! | O33: =IFERROR(ROUND((C33/IFERROR(INDEX(Config!B:B,MATCH("TVA "&A33,Config!A:A,0)),1.055))*0.52,2),"") -> #ERROR! | P33: =IFERROR(ROUND((C33/IFERROR(INDEX(Config!B:B,MATCH("TVA "&A33,Config!A:A,0)),1.055))*0.55,2),"") -> #ERROR! | Q33: =IFERROR(ROUND((C33/IFERROR(INDEX(Config!B:B,MATCH("TVA "&A33,Config!A:A,0)),1.055))*0.5,2),"") -> #ERROR! | R33: =IFERROR(ROUND((C33/IFERROR(INDEX(Config!B:B,MATCH("TVA "&A33,Config!A:A,0)),1.055))*0.5,2),"") -> #ERROR! | S33: =IFERROR(ROUND((C33/IFERROR(INDEX(Config!B:B,MATCH("TVA "&A33,Config!A:A,0)),1.055))*0.62,2),"") -> #ERROR! | T33: =IFERROR(ROUND((C33/IFERROR(INDEX(Config!B:B,MATCH("TVA "&A33,Config!A:A,0)),1.055))*0.58,2),"") -> #ERROR! | U33: =IFERROR(ROUND((C33/IFERROR(INDEX(Config!B:B,MATCH("TVA "&A33,Config!A:A,0)),1.055))*0.58,2),"") -> #ERROR! | V33: =IFERROR(((C33/IFERROR(INDEX(Config!B:B,MATCH("TVA "&A33,Config!A:A,0)),1.055))-IFERROR(INDEX('Cout de Revient'!I:I,MATCH(B33,'Cout de Revient'!C:C,0)),0))/(C33/IFERROR(INDEX(Config!B:B,MATCH("TVA "&A33,Config!A:A,0)),1.055)),"") -> #ERROR! | W33: =IFERROR(C33,"") -> #ERROR! | X33: =IFERROR(ROUND(C33*0.85,2),"") -> #ERROR!
A34: Mousses | B34: W60-050 | C34: 2.2 | D34: =IFERROR(ROUND(C34*0.95,2),"") -> #ERROR! | E34: =IFERROR(ROUND(C34*0.92,2),"") -> #ERROR! | F34: =IFERROR(ROUND(C34*0.88,2),"") -> #ERROR! | G34: =IFERROR(ROUND(C34*1,2),"") -> #ERROR! | H34: =IFERROR(ROUND(C34*0.97,2),"") -> #ERROR! | I34: =IFERROR(ROUND(C34*0.94,2),"") -> #ERROR! | J34: =IFERROR(ROUND((C34/IFERROR(INDEX(Config!B:B,MATCH("TVA "&A34,Config!A:A,0)),1.055))*0.55,2),"") -> #ERROR! | K34: =IFERROR(ROUND((C34/IFERROR(INDEX(Config!B:B,MATCH("TVA "&A34,Config!A:A,0)),1.055))*0.48,2),"") -> #ERROR! | L34: =IFERROR(ROUND((C34/IFERROR(INDEX(Config!B:B,MATCH("TVA "&A34,Config!A:A,0)),1.055))*0.42,2),"") -> #ERROR! | M34: =IFERROR(ROUND((C34/IFERROR(INDEX(Config!B:B,MATCH("TVA "&A34,Config!A:A,0)),1.055))*0.58,2),"") -> #ERROR! | N34: =IFERROR(ROUND((C34/IFERROR(INDEX(Config!B:B,MATCH("TVA "&A34,Config!A:A,0)),1.055))*0.52,2),"") -> #ERROR! | O34: =IFERROR(ROUND((C34/IFERROR(INDEX(Config!B:B,MATCH("TVA "&A34,Config!A:A,0)),1.055))*0.52,2),"") -> #ERROR! | P34: =IFERROR(ROUND((C34/IFERROR(INDEX(Config!B:B,MATCH("TVA "&A34,Config!A:A,0)),1.055))*0.55,2),"") -> #ERROR! | Q34: =IFERROR(ROUND((C34/IFERROR(INDEX(Config!B:B,MATCH("TVA "&A34,Config!A:A,0)),1.055))*0.5,2),"") -> #ERROR! | R34: =IFERROR(ROUND((C34/IFERROR(INDEX(Config!B:B,MATCH("TVA "&A34,Config!A:A,0)),1.055))*0.5,2),"") -> #ERROR! | S34: =IFERROR(ROUND((C34/IFERROR(INDEX(Config!B:B,MATCH("TVA "&A34,Config!A:A,0)),1.055))*0.62,2),"") -> #ERROR! | T34: =IFERROR(ROUND((C34/IFERROR(INDEX(Config!B:B,MATCH("TVA "&A34,Config!A:A,0)),1.055))*0.58,2),"") -> #ERROR! | U34: =IFERROR(ROUND((C34/IFERROR(INDEX(Config!B:B,MATCH("TVA "&A34,Config!A:A,0)),1.055))*0.58,2),"") -> #ERROR! | V34: =IFERROR(((C34/IFERROR(INDEX(Config!B:B,MATCH("TVA "&A34,Config!A:A,0)),1.055))-IFERROR(INDEX('Cout de Revient'!I:I,MATCH(B34,'Cout de Revient'!C:C,0)),0))/(C34/IFERROR(INDEX(Config!B:B,MATCH("TVA "&A34,Config!A:A,0)),1.055)),"") -> #ERROR! | W34: =IFERROR(C34,"") -> #ERROR! | X34: =IFERROR(ROUND(C34*0.85,2),"") -> #ERROR!
A35: Mousses | B35: W60-080 | C35: 3.2 | D35: =IFERROR(ROUND(C35*0.95,2),"") -> #ERROR! | E35: =IFERROR(ROUND(C35*0.92,2),"") -> #ERROR! | F35: =IFERROR(ROUND(C35*0.88,2),"") -> #ERROR! | G35: =IFERROR(ROUND(C35*1,2),"") -> #ERROR! | H35: =IFERROR(ROUND(C35*0.97,2),"") -> #ERROR! | I35: =IFERROR(ROUND(C35*0.94,2),"") -> #ERROR! | J35: =IFERROR(ROUND((C35/IFERROR(INDEX(Config!B:B,MATCH("TVA "&A35,Config!A:A,0)),1.055))*0.55,2),"") -> #ERROR! | K35: =IFERROR(ROUND((C35/IFERROR(INDEX(Config!B:B,MATCH("TVA "&A35,Config!A:A,0)),1.055))*0.48,2),"") -> #ERROR! | L35: =IFERROR(ROUND((C35/IFERROR(INDEX(Config!B:B,MATCH("TVA "&A35,Config!A:A,0)),1.055))*0.42,2),"") -> #ERROR! | M35: =IFERROR(ROUND((C35/IFERROR(INDEX(Config!B:B,MATCH("TVA "&A35,Config!A:A,0)),1.055))*0.58,2),"") -> #ERROR! | N35: =IFERROR(ROUND((C35/IFERROR(INDEX(Config!B:B,MATCH("TVA "&A35,Config!A:A,0)),1.055))*0.52,2),"") -> #ERROR! | O35: =IFERROR(ROUND((C35/IFERROR(INDEX(Config!B:B,MATCH("TVA "&A35,Config!A:A,0)),1.055))*0.52,2),"") -> #ERROR! | P35: =IFERROR(ROUND((C35/IFERROR(INDEX(Config!B:B,MATCH("TVA "&A35,Config!A:A,0)),1.055))*0.55,2),"") -> #ERROR! | Q35: =IFERROR(ROUND((C35/IFERROR(INDEX(Config!B:B,MATCH("TVA "&A35,Config!A:A,0)),1.055))*0.5,2),"") -> #ERROR! | R35: =IFERROR(ROUND((C35/IFERROR(INDEX(Config!B:B,MATCH("TVA "&A35,Config!A:A,0)),1.055))*0.5,2),"") -> #ERROR! | S35: =IFERROR(ROUND((C35/IFERROR(INDEX(Config!B:B,MATCH("TVA "&A35,Config!A:A,0)),1.055))*0.62,2),"") -> #ERROR! | T35: =IFERROR(ROUND((C35/IFERROR(INDEX(Config!B:B,MATCH("TVA "&A35,Config!A:A,0)),1.055))*0.58,2),"") -> #ERROR! | U35: =IFERROR(ROUND((C35/IFERROR(INDEX(Config!B:B,MATCH("TVA "&A35,Config!A:A,0)),1.055))*0.58,2),"") -> #ERROR! | V35: =IFERROR(((C35/IFERROR(INDEX(Config!B:B,MATCH("TVA "&A35,Config!A:A,0)),1.055))-IFERROR(INDEX('Cout de Revient'!I:I,MATCH(B35,'Cout de Revient'!C:C,0)),0))/(C35/IFERROR(INDEX(Config!B:B,MATCH("TVA "&A35,Config!A:A,0)),1.055)),"") -> #ERROR! | W35: =IFERROR(C35,"") -> #ERROR! | X35: =IFERROR(ROUND(C35*0.85,2),"") -> #ERROR!
A36: Mousses | B36: W60-160 | C36: 4.5 | D36: =IFERROR(ROUND(C36*0.95,2),"") -> #ERROR! | E36: =IFERROR(ROUND(C36*0.92,2),"") -> #ERROR! | F36: =IFERROR(ROUND(C36*0.88,2),"") -> #ERROR! | G36: =IFERROR(ROUND(C36*1,2),"") -> #ERROR! | H36: =IFERROR(ROUND(C36*0.97,2),"") -> #ERROR! | I36: =IFERROR(ROUND(C36*0.94,2),"") -> #ERROR! | J36: =IFERROR(ROUND((C36/IFERROR(INDEX(Config!B:B,MATCH("TVA "&A36,Config!A:A,0)),1.055))*0.55,2),"") -> #ERROR! | K36: =IFERROR(ROUND((C36/IFERROR(INDEX(Config!B:B,MATCH("TVA "&A36,Config!A:A,0)),1.055))*0.48,2),"") -> #ERROR! | L36: =IFERROR(ROUND((C36/IFERROR(INDEX(Config!B:B,MATCH("TVA "&A36,Config!A:A,0)),1.055))*0.42,2),"") -> #ERROR! | M36: =IFERROR(ROUND((C36/IFERROR(INDEX(Config!B:B,MATCH("TVA "&A36,Config!A:A,0)),1.055))*0.58,2),"") -> #ERROR! | N36: =IFERROR(ROUND((C36/IFERROR(INDEX(Config!B:B,MATCH("TVA "&A36,Config!A:A,0)),1.055))*0.52,2),"") -> #ERROR! | O36: =IFERROR(ROUND((C36/IFERROR(INDEX(Config!B:B,MATCH("TVA "&A36,Config!A:A,0)),1.055))*0.52,2),"") -> #ERROR! | P36: =IFERROR(ROUND((C36/IFERROR(INDEX(Config!B:B,MATCH("TVA "&A36,Config!A:A,0)),1.055))*0.55,2),"") -> #ERROR! | Q36: =IFERROR(ROUND((C36/IFERROR(INDEX(Config!B:B,MATCH("TVA "&A36,Config!A:A,0)),1.055))*0.5,2),"") -> #ERROR! | R36: =IFERROR(ROUND((C36/IFERROR(INDEX(Config!B:B,MATCH("TVA "&A36,Config!A:A,0)),1.055))*0.5,2),"") -> #ERROR! | S36: =IFERROR(ROUND((C36/IFERROR(INDEX(Config!B:B,MATCH("TVA "&A36,Config!A:A,0)),1.055))*0.62,2),"") -> #ERROR! | T36: =IFERROR(ROUND((C36/IFERROR(INDEX(Config!B:B,MATCH("TVA "&A36,Config!A:A,0)),1.055))*0.58,2),"") -> #ERROR! | U36: =IFERROR(ROUND((C36/IFERROR(INDEX(Config!B:B,MATCH("TVA "&A36,Config!A:A,0)),1.055))*0.58,2),"") -> #ERROR! | V36: =IFERROR(((C36/IFERROR(INDEX(Config!B:B,MATCH("TVA "&A36,Config!A:A,0)),1.055))-IFERROR(INDEX('Cout de Revient'!I:I,MATCH(B36,'Cout de Revient'!C:C,0)),0))/(C36/IFERROR(INDEX(Config!B:B,MATCH("TVA "&A36,Config!A:A,0)),1.055)),"") -> #ERROR! | W36: =IFERROR(C36,"") -> #ERROR! | X36: =IFERROR(ROUND(C36*0.85,2),"") -> #ERROR!
A37: PLATS CUISINES — TVA 10%
A38: Plats cuisines | B38: RR100-290 | C38: 5.5 | D38: =IFERROR(ROUND(C38*0.95,2),"") -> #ERROR! | E38: =IFERROR(ROUND(C38*0.92,2),"") -> #ERROR! | F38: =IFERROR(ROUND(C38*0.88,2),"") -> #ERROR! | G38: =IFERROR(ROUND(C38*1,2),"") -> #ERROR! | H38: =IFERROR(ROUND(C38*0.97,2),"") -> #ERROR! | I38: =IFERROR(ROUND(C38*0.94,2),"") -> #ERROR! | J38: =IFERROR(ROUND((C38/IFERROR(INDEX(Config!B:B,MATCH("TVA "&A38,Config!A:A,0)),1.1))*0.55,2),"") -> #ERROR! | K38: =IFERROR(ROUND((C38/IFERROR(INDEX(Config!B:B,MATCH("TVA "&A38,Config!A:A,0)),1.1))*0.48,2),"") -> #ERROR! | L38: =IFERROR(ROUND((C38/IFERROR(INDEX(Config!B:B,MATCH("TVA "&A38,Config!A:A,0)),1.1))*0.42,2),"") -> #ERROR! | M38: =IFERROR(ROUND((C38/IFERROR(INDEX(Config!B:B,MATCH("TVA "&A38,Config!A:A,0)),1.1))*0.58,2),"") -> #ERROR! | N38: =IFERROR(ROUND((C38/IFERROR(INDEX(Config!B:B,MATCH("TVA "&A38,Config!A:A,0)),1.1))*0.52,2),"") -> #ERROR! | O38: =IFERROR(ROUND((C38/IFERROR(INDEX(Config!B:B,MATCH("TVA "&A38,Config!A:A,0)),1.1))*0.52,2),"") -> #ERROR! | P38: =IFERROR(ROUND((C38/IFERROR(INDEX(Config!B:B,MATCH("TVA "&A38,Config!A:A,0)),1.1))*0.55,2),"") -> #ERROR! | Q38: =IFERROR(ROUND((C38/IFERROR(INDEX(Config!B:B,MATCH("TVA "&A38,Config!A:A,0)),1.1))*0.5,2),"") -> #ERROR! | R38: =IFERROR(ROUND((C38/IFERROR(INDEX(Config!B:B,MATCH("TVA "&A38,Config!A:A,0)),1.1))*0.5,2),"") -> #ERROR! | S38: =IFERROR(ROUND((C38/IFERROR(INDEX(Config!B:B,MATCH("TVA "&A38,Config!A:A,0)),1.1))*0.62,2),"") -> #ERROR! | T38: =IFERROR(ROUND((C38/IFERROR(INDEX(Config!B:B,MATCH("TVA "&A38,Config!A:A,0)),1.1))*0.58,2),"") -> #ERROR! | U38: =IFERROR(ROUND((C38/IFERROR(INDEX(Config!B:B,MATCH("TVA "&A38,Config!A:A,0)),1.1))*0.58,2),"") -> #ERROR! | V38: =IFERROR(((C38/IFERROR(INDEX(Config!B:B,MATCH("TVA "&A38,Config!A:A,0)),1.1))-IFERROR(INDEX('Cout de Revient'!I:I,MATCH(B38,'Cout de Revient'!C:C,0)),0))/(C38/IFERROR(INDEX(Config!B:B,MATCH("TVA "&A38,Config!A:A,0)),1.1)),"") -> #ERROR! | W38: =IFERROR(C38,"") -> #ERROR! | X38: =IFERROR(ROUND(C38*0.85,2),"") -> #ERROR!
A39: Plats cuisines | B39: RR100-370 | C39: 7.2 | D39: =IFERROR(ROUND(C39*0.95,2),"") -> #ERROR! | E39: =IFERROR(ROUND(C39*0.92,2),"") -> #ERROR! | F39: =IFERROR(ROUND(C39*0.88,2),"") -> #ERROR! | G39: =IFERROR(ROUND(C39*1,2),"") -> #ERROR! | H39: =IFERROR(ROUND(C39*0.97,2),"") -> #ERROR! | I39: =IFERROR(ROUND(C39*0.94,2),"") -> #ERROR! | J39: =IFERROR(ROUND((C39/IFERROR(INDEX(Config!B:B,MATCH("TVA "&A39,Config!A:A,0)),1.1))*0.55,2),"") -> #ERROR! | K39: =IFERROR(ROUND((C39/IFERROR(INDEX(Config!B:B,MATCH("TVA "&A39,Config!A:A,0)),1.1))*0.48,2),"") -> #ERROR! | L39: =IFERROR(ROUND((C39/IFERROR(INDEX(Config!B:B,MATCH("TVA "&A39,Config!A:A,0)),1.1))*0.42,2),"") -> #ERROR! | M39: =IFERROR(ROUND((C39/IFERROR(INDEX(Config!B:B,MATCH("TVA "&A39,Config!A:A,0)),1.1))*0.58,2),"") -> #ERROR! | N39: =IFERROR(ROUND((C39/IFERROR(INDEX(Config!B:B,MATCH("TVA "&A39,Config!A:A,0)),1.1))*0.52,2),"") -> #ERROR! | O39: =IFERROR(ROUND((C39/IFERROR(INDEX(Config!B:B,MATCH("TVA "&A39,Config!A:A,0)),1.1))*0.52,2),"") -> #ERROR! | P39: =IFERROR(ROUND((C39/IFERROR(INDEX(Config!B:B,MATCH("TVA "&A39,Config!A:A,0)),1.1))*0.55,2),"") -> #ERROR! | Q39: =IFERROR(ROUND((C39/IFERROR(INDEX(Config!B:B,MATCH("TVA "&A39,Config!A:A,0)),1.1))*0.5,2),"") -> #ERROR! | R39: =IFERROR(ROUND((C39/IFERROR(INDEX(Config!B:B,MATCH("TVA "&A39,Config!A:A,0)),1.1))*0.5,2),"") -> #ERROR! | S39: =IFERROR(ROUND((C39/IFERROR(INDEX(Config!B:B,MATCH("TVA "&A39,Config!A:A,0)),1.1))*0.62,2),"") -> #ERROR! | T39: =IFERROR(ROUND((C39/IFERROR(INDEX(Config!B:B,MATCH("TVA "&A39,Config!A:A,0)),1.1))*0.58,2),"") -> #ERROR! | U39: =IFERROR(ROUND((C39/IFERROR(INDEX(Config!B:B,MATCH("TVA "&A39,Config!A:A,0)),1.1))*0.58,2),"") -> #ERROR! | V39: =IFERROR(((C39/IFERROR(INDEX(Config!B:B,MATCH("TVA "&A39,Config!A:A,0)),1.1))-IFERROR(INDEX('Cout de Revient'!I:I,MATCH(B39,'Cout de Revient'!C:C,0)),0))/(C39/IFERROR(INDEX(Config!B:B,MATCH("TVA "&A39,Config!A:A,0)),1.1)),"") -> #ERROR! | W39: =IFERROR(C39,"") -> #ERROR! | X39: =IFERROR(ROUND(C39*0.85,2),"") -> #ERROR!
A40: Plats cuisines | B40: RR100-580 | C40: 9.5 | D40: =IFERROR(ROUND(C40*0.95,2),"") -> #ERROR! | E40: =IFERROR(ROUND(C40*0.92,2),"") -> #ERROR! | F40: =IFERROR(ROUND(C40*0.88,2),"") -> #ERROR! | G40: =IFERROR(ROUND(C40*1,2),"") -> #ERROR! | H40: =IFERROR(ROUND(C40*0.97,2),"") -> #ERROR! | I40: =IFERROR(ROUND(C40*0.94,2),"") -> #ERROR! | J40: =IFERROR(ROUND((C40/IFERROR(INDEX(Config!B:B,MATCH("TVA "&A40,Config!A:A,0)),1.1))*0.55,2),"") -> #ERROR! | K40: =IFERROR(ROUND((C40/IFERROR(INDEX(Config!B:B,MATCH("TVA "&A40,Config!A:A,0)),1.1))*0.48,2),"") -> #ERROR! | L40: =IFERROR(ROUND((C40/IFERROR(INDEX(Config!B:B,MATCH("TVA "&A40,Config!A:A,0)),1.1))*0.42,2),"") -> #ERROR! | M40: =IFERROR(ROUND((C40/IFERROR(INDEX(Config!B:B,MATCH("TVA "&A40,Config!A:A,0)),1.1))*0.58,2),"") -> #ERROR! | N40: =IFERROR(ROUND((C40/IFERROR(INDEX(Config!B:B,MATCH("TVA "&A40,Config!A:A,0)),1.1))*0.52,2),"") -> #ERROR! | O40: =IFERROR(ROUND((C40/IFERROR(INDEX(Config!B:B,MATCH("TVA "&A40,Config!A:A,0)),1.1))*0.52,2),"") -> #ERROR! | P40: =IFERROR(ROUND((C40/IFERROR(INDEX(Config!B:B,MATCH("TVA "&A40,Config!A:A,0)),1.1))*0.55,2),"") -> #ERROR! | Q40: =IFERROR(ROUND((C40/IFERROR(INDEX(Config!B:B,MATCH("TVA "&A40,Config!A:A,0)),1.1))*0.5,2),"") -> #ERROR! | R40: =IFERROR(ROUND((C40/IFERROR(INDEX(Config!B:B,MATCH("TVA "&A40,Config!A:A,0)),1.1))*0.5,2),"") -> #ERROR! | S40: =IFERROR(ROUND((C40/IFERROR(INDEX(Config!B:B,MATCH("TVA "&A40,Config!A:A,0)),1.1))*0.62,2),"") -> #ERROR! | T40: =IFERROR(ROUND((C40/IFERROR(INDEX(Config!B:B,MATCH("TVA "&A40,Config!A:A,0)),1.1))*0.58,2),"") -> #ERROR! | U40: =IFERROR(ROUND((C40/IFERROR(INDEX(Config!B:B,MATCH("TVA "&A40,Config!A:A,0)),1.1))*0.58,2),"") -> #ERROR! | V40: =IFERROR(((C40/IFERROR(INDEX(Config!B:B,MATCH("TVA "&A40,Config!A:A,0)),1.1))-IFERROR(INDEX('Cout de Revient'!I:I,MATCH(B40,'Cout de Revient'!C:C,0)),0))/(C40/IFERROR(INDEX(Config!B:B,MATCH("TVA "&A40,Config!A:A,0)),1.1)),"") -> #ERROR! | W40: =IFERROR(C40,"") -> #ERROR! | X40: =IFERROR(ROUND(C40*0.85,2),"") -> #ERROR!
A41: Plats cuisines | B41: RR100-850 | C41: 14.5 | D41: =IFERROR(ROUND(C41*0.95,2),"") -> #ERROR! | E41: =IFERROR(ROUND(C41*0.92,2),"") -> #ERROR! | F41: =IFERROR(ROUND(C41*0.88,2),"") -> #ERROR! | G41: =IFERROR(ROUND(C41*1,2),"") -> #ERROR! | H41: =IFERROR(ROUND(C41*0.97,2),"") -> #ERROR! | I41: =IFERROR(ROUND(C41*0.94,2),"") -> #ERROR! | J41: =IFERROR(ROUND((C41/IFERROR(INDEX(Config!B:B,MATCH("TVA "&A41,Config!A:A,0)),1.1))*0.55,2),"") -> #ERROR! | K41: =IFERROR(ROUND((C41/IFERROR(INDEX(Config!B:B,MATCH("TVA "&A41,Config!A:A,0)),1.1))*0.48,2),"") -> #ERROR! | L41: =IFERROR(ROUND((C41/IFERROR(INDEX(Config!B:B,MATCH("TVA "&A41,Config!A:A,0)),1.1))*0.42,2),"") -> #ERROR! | M41: =IFERROR(ROUND((C41/IFERROR(INDEX(Config!B:B,MATCH("TVA "&A41,Config!A:A,0)),1.1))*0.58,2),"") -> #ERROR! | N41: =IFERROR(ROUND((C41/IFERROR(INDEX(Config!B:B,MATCH("TVA "&A41,Config!A:A,0)),1.1))*0.52,2),"") -> #ERROR! | O41: =IFERROR(ROUND((C41/IFERROR(INDEX(Config!B:B,MATCH("TVA "&A41,Config!A:A,0)),1.1))*0.52,2),"") -> #ERROR! | P41: =IFERROR(ROUND((C41/IFERROR(INDEX(Config!B:B,MATCH("TVA "&A41,Config!A:A,0)),1.1))*0.55,2),"") -> #ERROR! | Q41: =IFERROR(ROUND((C41/IFERROR(INDEX(Config!B:B,MATCH("TVA "&A41,Config!A:A,0)),1.1))*0.5,2),"") -> #ERROR! | R41: =IFERROR(ROUND((C41/IFERROR(INDEX(Config!B:B,MATCH("TVA "&A41,Config!A:A,0)),1.1))*0.5,2),"") -> #ERROR! | S41: =IFERROR(ROUND((C41/IFERROR(INDEX(Config!B:B,MATCH("TVA "&A41,Config!A:A,0)),1.1))*0.62,2),"") -> #ERROR! | T41: =IFERROR(ROUND((C41/IFERROR(INDEX(Config!B:B,MATCH("TVA "&A41,Config!A:A,0)),1.1))*0.58,2),"") -> #ERROR! | U41: =IFERROR(ROUND((C41/IFERROR(INDEX(Config!B:B,MATCH("TVA "&A41,Config!A:A,0)),1.1))*0.58,2),"") -> #ERROR! | V41: =IFERROR(((C41/IFERROR(INDEX(Config!B:B,MATCH("TVA "&A41,Config!A:A,0)),1.1))-IFERROR(INDEX('Cout de Revient'!I:I,MATCH(B41,'Cout de Revient'!C:C,0)),0))/(C41/IFERROR(INDEX(Config!B:B,MATCH("TVA "&A41,Config!A:A,0)),1.1)),"") -> #ERROR! | W41: =IFERROR(C41,"") -> #ERROR! | X41: =IFERROR(ROUND(C41*0.85,2),"") -> #ERROR!
A42: Plats cuisines | B42: RR100-1050 | C42: 18.9 | D42: =IFERROR(ROUND(C42*0.95,2),"") -> #ERROR! | E42: =IFERROR(ROUND(C42*0.92,2),"") -> #ERROR! | F42: =IFERROR(ROUND(C42*0.88,2),"") -> #ERROR! | G42: =IFERROR(ROUND(C42*1,2),"") -> #ERROR! | H42: =IFERROR(ROUND(C42*0.97,2),"") -> #ERROR! | I42: =IFERROR(ROUND(C42*0.94,2),"") -> #ERROR! | J42: =IFERROR(ROUND((C42/IFERROR(INDEX(Config!B:B,MATCH("TVA "&A42,Config!A:A,0)),1.1))*0.55,2),"") -> #ERROR! | K42: =IFERROR(ROUND((C42/IFERROR(INDEX(Config!B:B,MATCH("TVA "&A42,Config!A:A,0)),1.1))*0.48,2),"") -> #ERROR! | L42: =IFERROR(ROUND((C42/IFERROR(INDEX(Config!B:B,MATCH("TVA "&A42,Config!A:A,0)),1.1))*0.42,2),"") -> #ERROR! | M42: =IFERROR(ROUND((C42/IFERROR(INDEX(Config!B:B,MATCH("TVA "&A42,Config!A:A,0)),1.1))*0.58,2),"") -> #ERROR! | N42: =IFERROR(ROUND((C42/IFERROR(INDEX(Config!B:B,MATCH("TVA "&A42,Config!A:A,0)),1.1))*0.52,2),"") -> #ERROR! | O42: =IFERROR(ROUND((C42/IFERROR(INDEX(Config!B:B,MATCH("TVA "&A42,Config!A:A,0)),1.1))*0.52,2),"") -> #ERROR! | P42: =IFERROR(ROUND((C42/IFERROR(INDEX(Config!B:B,MATCH("TVA "&A42,Config!A:A,0)),1.1))*0.55,2),"") -> #ERROR! | Q42: =IFERROR(ROUND((C42/IFERROR(INDEX(Config!B:B,MATCH("TVA "&A42,Config!A:A,0)),1.1))*0.5,2),"") -> #ERROR! | R42: =IFERROR(ROUND((C42/IFERROR(INDEX(Config!B:B,MATCH("TVA "&A42,Config!A:A,0)),1.1))*0.5,2),"") -> #ERROR! | S42: =IFERROR(ROUND((C42/IFERROR(INDEX(Config!B:B,MATCH("TVA "&A42,Config!A:A,0)),1.1))*0.62,2),"") -> #ERROR! | T42: =IFERROR(ROUND((C42/IFERROR(INDEX(Config!B:B,MATCH("TVA "&A42,Config!A:A,0)),1.1))*0.58,2),"") -> #ERROR! | U42: =IFERROR(ROUND((C42/IFERROR(INDEX(Config!B:B,MATCH("TVA "&A42,Config!A:A,0)),1.1))*0.58,2),"") -> #ERROR! | V42: =IFERROR(((C42/IFERROR(INDEX(Config!B:B,MATCH("TVA "&A42,Config!A:A,0)),1.1))-IFERROR(INDEX('Cout de Revient'!I:I,MATCH(B42,'Cout de Revient'!C:C,0)),0))/(C42/IFERROR(INDEX(Config!B:B,MATCH("TVA "&A42,Config!A:A,0)),1.1)),"") -> #ERROR! | W42: =IFERROR(C42,"") -> #ERROR! | X42: =IFERROR(ROUND(C42*0.85,2),"") -> #ERROR!
A43: Plats cuisines | B43: RR100-1550 | C43: 26.9 | D43: =IFERROR(ROUND(C43*0.95,2),"") -> #ERROR! | E43: =IFERROR(ROUND(C43*0.92,2),"") -> #ERROR! | F43: =IFERROR(ROUND(C43*0.88,2),"") -> #ERROR! | G43: =IFERROR(ROUND(C43*1,2),"") -> #ERROR! | H43: =IFERROR(ROUND(C43*0.97,2),"") -> #ERROR! | I43: =IFERROR(ROUND(C43*0.94,2),"") -> #ERROR! | J43: =IFERROR(ROUND((C43/IFERROR(INDEX(Config!B:B,MATCH("TVA "&A43,Config!A:A,0)),1.1))*0.55,2),"") -> #ERROR! | K43: =IFERROR(ROUND((C43/IFERROR(INDEX(Config!B:B,MATCH("TVA "&A43,Config!A:A,0)),1.1))*0.48,2),"") -> #ERROR! | L43: =IFERROR(ROUND((C43/IFERROR(INDEX(Config!B:B,MATCH("TVA "&A43,Config!A:A,0)),1.1))*0.42,2),"") -> #ERROR! | M43: =IFERROR(ROUND((C43/IFERROR(INDEX(Config!B:B,MATCH("TVA "&A43,Config!A:A,0)),1.1))*0.58,2),"") -> #ERROR! | N43: =IFERROR(ROUND((C43/IFERROR(INDEX(Config!B:B,MATCH("TVA "&A43,Config!A:A,0)),1.1))*0.52,2),"") -> #ERROR! | O43: =IFERROR(ROUND((C43/IFERROR(INDEX(Config!B:B,MATCH("TVA "&A43,Config!A:A,0)),1.1))*0.52,2),"") -> #ERROR! | P43: =IFERROR(ROUND((C43/IFERROR(INDEX(Config!B:B,MATCH("TVA "&A43,Config!A:A,0)),1.1))*0.55,2),"") -> #ERROR! | Q43: =IFERROR(ROUND((C43/IFERROR(INDEX(Config!B:B,MATCH("TVA "&A43,Config!A:A,0)),1.1))*0.5,2),"") -> #ERROR! | R43: =IFERROR(ROUND((C43/IFERROR(INDEX(Config!B:B,MATCH("TVA "&A43,Config!A:A,0)),1.1))*0.5,2),"") -> #ERROR! | S43: =IFERROR(ROUND((C43/IFERROR(INDEX(Config!B:B,MATCH("TVA "&A43,Config!A:A,0)),1.1))*0.62,2),"") -> #ERROR! | T43: =IFERROR(ROUND((C43/IFERROR(INDEX(Config!B:B,MATCH("TVA "&A43,Config!A:A,0)),1.1))*0.58,2),"") -> #ERROR! | U43: =IFERROR(ROUND((C43/IFERROR(INDEX(Config!B:B,MATCH("TVA "&A43,Config!A:A,0)),1.1))*0.58,2),"") -> #ERROR! | V43: =IFERROR(((C43/IFERROR(INDEX(Config!B:B,MATCH("TVA "&A43,Config!A:A,0)),1.1))-IFERROR(INDEX('Cout de Revient'!I:I,MATCH(B43,'Cout de Revient'!C:C,0)),0))/(C43/IFERROR(INDEX(Config!B:B,MATCH("TVA "&A43,Config!A:A,0)),1.1)),"") -> #ERROR! | W43: =IFERROR(C43,"") -> #ERROR! | X43: =IFERROR(ROUND(C43*0.85,2),"") -> #ERROR!
A44: Plats cuisines | B44: W60-050 | C44: 2.2 | D44: =IFERROR(ROUND(C44*0.95,2),"") -> #ERROR! | E44: =IFERROR(ROUND(C44*0.92,2),"") -> #ERROR! | F44: =IFERROR(ROUND(C44*0.88,2),"") -> #ERROR! | G44: =IFERROR(ROUND(C44*1,2),"") -> #ERROR! | H44: =IFERROR(ROUND(C44*0.97,2),"") -> #ERROR! | I44: =IFERROR(ROUND(C44*0.94,2),"") -> #ERROR! | J44: =IFERROR(ROUND((C44/IFERROR(INDEX(Config!B:B,MATCH("TVA "&A44,Config!A:A,0)),1.1))*0.55,2),"") -> #ERROR! | K44: =IFERROR(ROUND((C44/IFERROR(INDEX(Config!B:B,MATCH("TVA "&A44,Config!A:A,0)),1.1))*0.48,2),"") -> #ERROR! | L44: =IFERROR(ROUND((C44/IFERROR(INDEX(Config!B:B,MATCH("TVA "&A44,Config!A:A,0)),1.1))*0.42,2),"") -> #ERROR! | M44: =IFERROR(ROUND((C44/IFERROR(INDEX(Config!B:B,MATCH("TVA "&A44,Config!A:A,0)),1.1))*0.58,2),"") -> #ERROR! | N44: =IFERROR(ROUND((C44/IFERROR(INDEX(Config!B:B,MATCH("TVA "&A44,Config!A:A,0)),1.1))*0.52,2),"") -> #ERROR! | O44: =IFERROR(ROUND((C44/IFERROR(INDEX(Config!B:B,MATCH("TVA "&A44,Config!A:A,0)),1.1))*0.52,2),"") -> #ERROR! | P44: =IFERROR(ROUND((C44/IFERROR(INDEX(Config!B:B,MATCH("TVA "&A44,Config!A:A,0)),1.1))*0.55,2),"") -> #ERROR! | Q44: =IFERROR(ROUND((C44/IFERROR(INDEX(Config!B:B,MATCH("TVA "&A44,Config!A:A,0)),1.1))*0.5,2),"") -> #ERROR! | R44: =IFERROR(ROUND((C44/IFERROR(INDEX(Config!B:B,MATCH("TVA "&A44,Config!A:A,0)),1.1))*0.5,2),"") -> #ERROR! | S44: =IFERROR(ROUND((C44/IFERROR(INDEX(Config!B:B,MATCH("TVA "&A44,Config!A:A,0)),1.1))*0.62,2),"") -> #ERROR! | T44: =IFERROR(ROUND((C44/IFERROR(INDEX(Config!B:B,MATCH("TVA "&A44,Config!A:A,0)),1.1))*0.58,2),"") -> #ERROR! | U44: =IFERROR(ROUND((C44/IFERROR(INDEX(Config!B:B,MATCH("TVA "&A44,Config!A:A,0)),1.1))*0.58,2),"") -> #ERROR! | V44: =IFERROR(((C44/IFERROR(INDEX(Config!B:B,MATCH("TVA "&A44,Config!A:A,0)),1.1))-IFERROR(INDEX('Cout de Revient'!I:I,MATCH(B44,'Cout de Revient'!C:C,0)),0))/(C44/IFERROR(INDEX(Config!B:B,MATCH("TVA "&A44,Config!A:A,0)),1.1)),"") -> #ERROR! | W44: =IFERROR(C44,"") -> #ERROR! | X44: =IFERROR(ROUND(C44*0.85,2),"") -> #ERROR!
A45: Plats cuisines | B45: W60-080 | C45: 3.2 | D45: =IFERROR(ROUND(C45*0.95,2),"") -> #ERROR! | E45: =IFERROR(ROUND(C45*0.92,2),"") -> #ERROR! | F45: =IFERROR(ROUND(C45*0.88,2),"") -> #ERROR! | G45: =IFERROR(ROUND(C45*1,2),"") -> #ERROR! | H45: =IFERROR(ROUND(C45*0.97,2),"") -> #ERROR! | I45: =IFERROR(ROUND(C45*0.94,2),"") -> #ERROR! | J45: =IFERROR(ROUND((C45/IFERROR(INDEX(Config!B:B,MATCH("TVA "&A45,Config!A:A,0)),1.1))*0.55,2),"") -> #ERROR! | K45: =IFERROR(ROUND((C45/IFERROR(INDEX(Config!B:B,MATCH("TVA "&A45,Config!A:A,0)),1.1))*0.48,2),"") -> #ERROR! | L45: =IFERROR(ROUND((C45/IFERROR(INDEX(Config!B:B,MATCH("TVA "&A45,Config!A:A,0)),1.1))*0.42,2),"") -> #ERROR! | M45: =IFERROR(ROUND((C45/IFERROR(INDEX(Config!B:B,MATCH("TVA "&A45,Config!A:A,0)),1.1))*0.58,2),"") -> #ERROR! | N45: =IFERROR(ROUND((C45/IFERROR(INDEX(Config!B:B,MATCH("TVA "&A45,Config!A:A,0)),1.1))*0.52,2),"") -> #ERROR! | O45: =IFERROR(ROUND((C45/IFERROR(INDEX(Config!B:B,MATCH("TVA "&A45,Config!A:A,0)),1.1))*0.52,2),"") -> #ERROR! | P45: =IFERROR(ROUND((C45/IFERROR(INDEX(Config!B:B,MATCH("TVA "&A45,Config!A:A,0)),1.1))*0.55,2),"") -> #ERROR! | Q45: =IFERROR(ROUND((C45/IFERROR(INDEX(Config!B:B,MATCH("TVA "&A45,Config!A:A,0)),1.1))*0.5,2),"") -> #ERROR! | R45: =IFERROR(ROUND((C45/IFERROR(INDEX(Config!B:B,MATCH("TVA "&A45,Config!A:A,0)),1.1))*0.5,2),"") -> #ERROR! | S45: =IFERROR(ROUND((C45/IFERROR(INDEX(Config!B:B,MATCH("TVA "&A45,Config!A:A,0)),1.1))*0.62,2),"") -> #ERROR! | T45: =IFERROR(ROUND((C45/IFERROR(INDEX(Config!B:B,MATCH("TVA "&A45,Config!A:A,0)),1.1))*0.58,2),"") -> #ERROR! | U45: =IFERROR(ROUND((C45/IFERROR(INDEX(Config!B:B,MATCH("TVA "&A45,Config!A:A,0)),1.1))*0.58,2),"") -> #ERROR! | V45: =IFERROR(((C45/IFERROR(INDEX(Config!B:B,MATCH("TVA "&A45,Config!A:A,0)),1.1))-IFERROR(INDEX('Cout de Revient'!I:I,MATCH(B45,'Cout de Revient'!C:C,0)),0))/(C45/IFERROR(INDEX(Config!B:B,MATCH("TVA "&A45,Config!A:A,0)),1.1)),"") -> #ERROR! | W45: =IFERROR(C45,"") -> #ERROR! | X45: =IFERROR(ROUND(C45*0.85,2),"") -> #ERROR!
A46: Plats cuisines | B46: W60-160 | C46: 4.5 | D46: =IFERROR(ROUND(C46*0.95,2),"") -> #ERROR! | E46: =IFERROR(ROUND(C46*0.92,2),"") -> #ERROR! | F46: =IFERROR(ROUND(C46*0.88,2),"") -> #ERROR! | G46: =IFERROR(ROUND(C46*1,2),"") -> #ERROR! | H46: =IFERROR(ROUND(C46*0.97,2),"") -> #ERROR! | I46: =IFERROR(ROUND(C46*0.94,2),"") -> #ERROR! | J46: =IFERROR(ROUND((C46/IFERROR(INDEX(Config!B:B,MATCH("TVA "&A46,Config!A:A,0)),1.1))*0.55,2),"") -> #ERROR! | K46: =IFERROR(ROUND((C46/IFERROR(INDEX(Config!B:B,MATCH("TVA "&A46,Config!A:A,0)),1.1))*0.48,2),"") -> #ERROR! | L46: =IFERROR(ROUND((C46/IFERROR(INDEX(Config!B:B,MATCH("TVA "&A46,Config!A:A,0)),1.1))*0.42,2),"") -> #ERROR! | M46: =IFERROR(ROUND((C46/IFERROR(INDEX(Config!B:B,MATCH("TVA "&A46,Config!A:A,0)),1.1))*0.58,2),"") -> #ERROR! | N46: =IFERROR(ROUND((C46/IFERROR(INDEX(Config!B:B,MATCH("TVA "&A46,Config!A:A,0)),1.1))*0.52,2),"") -> #ERROR! | O46: =IFERROR(ROUND((C46/IFERROR(INDEX(Config!B:B,MATCH("TVA "&A46,Config!A:A,0)),1.1))*0.52,2),"") -> #ERROR! | P46: =IFERROR(ROUND((C46/IFERROR(INDEX(Config!B:B,MATCH("TVA "&A46,Config!A:A,0)),1.1))*0.55,2),"") -> #ERROR! | Q46: =IFERROR(ROUND((C46/IFERROR(INDEX(Config!B:B,MATCH("TVA "&A46,Config!A:A,0)),1.1))*0.5,2),"") -> #ERROR! | R46: =IFERROR(ROUND((C46/IFERROR(INDEX(Config!B:B,MATCH("TVA "&A46,Config!A:A,0)),1.1))*0.5,2),"") -> #ERROR! | S46: =IFERROR(ROUND((C46/IFERROR(INDEX(Config!B:B,MATCH("TVA "&A46,Config!A:A,0)),1.1))*0.62,2),"") -> #ERROR! | T46: =IFERROR(ROUND((C46/IFERROR(INDEX(Config!B:B,MATCH("TVA "&A46,Config!A:A,0)),1.1))*0.58,2),"") -> #ERROR! | U46: =IFERROR(ROUND((C46/IFERROR(INDEX(Config!B:B,MATCH("TVA "&A46,Config!A:A,0)),1.1))*0.58,2),"") -> #ERROR! | V46: =IFERROR(((C46/IFERROR(INDEX(Config!B:B,MATCH("TVA "&A46,Config!A:A,0)),1.1))-IFERROR(INDEX('Cout de Revient'!I:I,MATCH(B46,'Cout de Revient'!C:C,0)),0))/(C46/IFERROR(INDEX(Config!B:B,MATCH("TVA "&A46,Config!A:A,0)),1.1)),"") -> #ERROR! | W46: =IFERROR(C46,"") -> #ERROR! | X46: =IFERROR(ROUND(C46*0.85,2),"") -> #ERROR!
A47: DESSERTS APPERTISES — TVA 5%
A48: Desserts appertises | B48: RR100-290 | C48: 4.9 | D48: =IFERROR(ROUND(C48*0.95,2),"") -> #ERROR! | E48: =IFERROR(ROUND(C48*0.92,2),"") -> #ERROR! | F48: =IFERROR(ROUND(C48*0.88,2),"") -> #ERROR! | G48: =IFERROR(ROUND(C48*1,2),"") -> #ERROR! | H48: =IFERROR(ROUND(C48*0.97,2),"") -> #ERROR! | I48: =IFERROR(ROUND(C48*0.94,2),"") -> #ERROR! | J48: =IFERROR(ROUND((C48/IFERROR(INDEX(Config!B:B,MATCH("TVA "&A48,Config!A:A,0)),1.055))*0.55,2),"") -> #ERROR! | K48: =IFERROR(ROUND((C48/IFERROR(INDEX(Config!B:B,MATCH("TVA "&A48,Config!A:A,0)),1.055))*0.48,2),"") -> #ERROR! | L48: =IFERROR(ROUND((C48/IFERROR(INDEX(Config!B:B,MATCH("TVA "&A48,Config!A:A,0)),1.055))*0.42,2),"") -> #ERROR! | M48: =IFERROR(ROUND((C48/IFERROR(INDEX(Config!B:B,MATCH("TVA "&A48,Config!A:A,0)),1.055))*0.58,2),"") -> #ERROR! | N48: =IFERROR(ROUND((C48/IFERROR(INDEX(Config!B:B,MATCH("TVA "&A48,Config!A:A,0)),1.055))*0.52,2),"") -> #ERROR! | O48: =IFERROR(ROUND((C48/IFERROR(INDEX(Config!B:B,MATCH("TVA "&A48,Config!A:A,0)),1.055))*0.52,2),"") -> #ERROR! | P48: =IFERROR(ROUND((C48/IFERROR(INDEX(Config!B:B,MATCH("TVA "&A48,Config!A:A,0)),1.055))*0.55,2),"") -> #ERROR! | Q48: =IFERROR(ROUND((C48/IFERROR(INDEX(Config!B:B,MATCH("TVA "&A48,Config!A:A,0)),1.055))*0.5,2),"") -> #ERROR! | R48: =IFERROR(ROUND((C48/IFERROR(INDEX(Config!B:B,MATCH("TVA "&A48,Config!A:A,0)),1.055))*0.5,2),"") -> #ERROR! | S48: =IFERROR(ROUND((C48/IFERROR(INDEX(Config!B:B,MATCH("TVA "&A48,Config!A:A,0)),1.055))*0.62,2),"") -> #ERROR! | T48: =IFERROR(ROUND((C48/IFERROR(INDEX(Config!B:B,MATCH("TVA "&A48,Config!A:A,0)),1.055))*0.58,2),"") -> #ERROR! | U48: =IFERROR(ROUND((C48/IFERROR(INDEX(Config!B:B,MATCH("TVA "&A48,Config!A:A,0)),1.055))*0.58,2),"") -> #ERROR! | V48: =IFERROR(((C48/IFERROR(INDEX(Config!B:B,MATCH("TVA "&A48,Config!A:A,0)),1.055))-IFERROR(INDEX('Cout de Revient'!I:I,MATCH(B48,'Cout de Revient'!C:C,0)),0))/(C48/IFERROR(INDEX(Config!B:B,MATCH("TVA "&A48,Config!A:A,0)),1.055)),"") -> #ERROR! | W48: =IFERROR(C48,"") -> #ERROR! | X48: =IFERROR(ROUND(C48*0.85,2),"") -> #ERROR!
A49: Desserts appertises | B49: RR100-370 | C49: 5.9 | D49: =IFERROR(ROUND(C49*0.95,2),"") -> #ERROR! | E49: =IFERROR(ROUND(C49*0.92,2),"") -> #ERROR! | F49: =IFERROR(ROUND(C49*0.88,2),"") -> #ERROR! | G49: =IFERROR(ROUND(C49*1,2),"") -> #ERROR! | H49: =IFERROR(ROUND(C49*0.97,2),"") -> #ERROR! | I49: =IFERROR(ROUND(C49*0.94,2),"") -> #ERROR! | J49: =IFERROR(ROUND((C49/IFERROR(INDEX(Config!B:B,MATCH("TVA "&A49,Config!A:A,0)),1.055))*0.55,2),"") -> #ERROR! | K49: =IFERROR(ROUND((C49/IFERROR(INDEX(Config!B:B,MATCH("TVA "&A49,Config!A:A,0)),1.055))*0.48,2),"") -> #ERROR! | L49: =IFERROR(ROUND((C49/IFERROR(INDEX(Config!B:B,MATCH("TVA "&A49,Config!A:A,0)),1.055))*0.42,2),"") -> #ERROR! | M49: =IFERROR(ROUND((C49/IFERROR(INDEX(Config!B:B,MATCH("TVA "&A49,Config!A:A,0)),1.055))*0.58,2),"") -> #ERROR! | N49: =IFERROR(ROUND((C49/IFERROR(INDEX(Config!B:B,MATCH("TVA "&A49,Config!A:A,0)),1.055))*0.52,2),"") -> #ERROR! | O49: =IFERROR(ROUND((C49/IFERROR(INDEX(Config!B:B,MATCH("TVA "&A49,Config!A:A,0)),1.055))*0.52,2),"") -> #ERROR! | P49: =IFERROR(ROUND((C49/IFERROR(INDEX(Config!B:B,MATCH("TVA "&A49,Config!A:A,0)),1.055))*0.55,2),"") -> #ERROR! | Q49: =IFERROR(ROUND((C49/IFERROR(INDEX(Config!B:B,MATCH("TVA "&A49,Config!A:A,0)),1.055))*0.5,2),"") -> #ERROR! | R49: =IFERROR(ROUND((C49/IFERROR(INDEX(Config!B:B,MATCH("TVA "&A49,Config!A:A,0)),1.055))*0.5,2),"") -> #ERROR! | S49: =IFERROR(ROUND((C49/IFERROR(INDEX(Config!B:B,MATCH("TVA "&A49,Config!A:A,0)),1.055))*0.62,2),"") -> #ERROR! | T49: =IFERROR(ROUND((C49/IFERROR(INDEX(Config!B:B,MATCH("TVA "&A49,Config!A:A,0)),1.055))*0.58,2),"") -> #ERROR! | U49: =IFERROR(ROUND((C49/IFERROR(INDEX(Config!B:B,MATCH("TVA "&A49,Config!A:A,0)),1.055))*0.58,2),"") -> #ERROR! | V49: =IFERROR(((C49/IFERROR(INDEX(Config!B:B,MATCH("TVA "&A49,Config!A:A,0)),1.055))-IFERROR(INDEX('Cout de Revient'!I:I,MATCH(B49,'Cout de Revient'!C:C,0)),0))/(C49/IFERROR(INDEX(Config!B:B,MATCH("TVA "&A49,Config!A:A,0)),1.055)),"") -> #ERROR! | W49: =IFERROR(C49,"") -> #ERROR! | X49: =IFERROR(ROUND(C49*0.85,2),"") -> #ERROR!
A50: Desserts appertises | B50: RR100-580 | C50: 7.9 | D50: =IFERROR(ROUND(C50*0.95,2),"") -> #ERROR! | E50: =IFERROR(ROUND(C50*0.92,2),"") -> #ERROR! | F50: =IFERROR(ROUND(C50*0.88,2),"") -> #ERROR! | G50: =IFERROR(ROUND(C50*1,2),"") -> #ERROR! | H50: =IFERROR(ROUND(C50*0.97,2),"") -> #ERROR! | I50: =IFERROR(ROUND(C50*0.94,2),"") -> #ERROR! | J50: =IFERROR(ROUND((C50/IFERROR(INDEX(Config!B:B,MATCH("TVA "&A50,Config!A:A,0)),1.055))*0.55,2),"") -> #ERROR! | K50: =IFERROR(ROUND((C50/IFERROR(INDEX(Config!B:B,MATCH("TVA "&A50,Config!A:A,0)),1.055))*0.48,2),"") -> #ERROR! | L50: =IFERROR(ROUND((C50/IFERROR(INDEX(Config!B:B,MATCH("TVA "&A50,Config!A:A,0)),1.055))*0.42,2),"") -> #ERROR! | M50: =IFERROR(ROUND((C50/IFERROR(INDEX(Config!B:B,MATCH("TVA "&A50,Config!A:A,0)),1.055))*0.58,2),"") -> #ERROR! | N50: =IFERROR(ROUND((C50/IFERROR(INDEX(Config!B:B,MATCH("TVA "&A50,Config!A:A,0)),1.055))*0.52,2),"") -> #ERROR! | O50: =IFERROR(ROUND((C50/IFERROR(INDEX(Config!B:B,MATCH("TVA "&A50,Config!A:A,0)),1.055))*0.52,2),"") -> #ERROR! | P50: =IFERROR(ROUND((C50/IFERROR(INDEX(Config!B:B,MATCH("TVA "&A50,Config!A:A,0)),1.055))*0.55,2),"") -> #ERROR! | Q50: =IFERROR(ROUND((C50/IFERROR(INDEX(Config!B:B,MATCH("TVA "&A50,Config!A:A,0)),1.055))*0.5,2),"") -> #ERROR! | R50: =IFERROR(ROUND((C50/IFERROR(INDEX(Config!B:B,MATCH("TVA "&A50,Config!A:A,0)),1.055))*0.5,2),"") -> #ERROR! | S50: =IFERROR(ROUND((C50/IFERROR(INDEX(Config!B:B,MATCH("TVA "&A50,Config!A:A,0)),1.055))*0.62,2),"") -> #ERROR! | T50: =IFERROR(ROUND((C50/IFERROR(INDEX(Config!B:B,MATCH("TVA "&A50,Config!A:A,0)),1.055))*0.58,2),"") -> #ERROR! | U50: =IFERROR(ROUND((C50/IFERROR(INDEX(Config!B:B,MATCH("TVA "&A50,Config!A:A,0)),1.055))*0.58,2),"") -> #ERROR! | V50: =IFERROR(((C50/IFERROR(INDEX(Config!B:B,MATCH("TVA "&A50,Config!A:A,0)),1.055))-IFERROR(INDEX('Cout de Revient'!I:I,MATCH(B50,'Cout de Revient'!C:C,0)),0))/(C50/IFERROR(INDEX(Config!B:B,MATCH("TVA "&A50,Config!A:A,0)),1.055)),"") -> #ERROR! | W50: =IFERROR(C50,"") -> #ERROR! | X50: =IFERROR(ROUND(C50*0.85,2),"") -> #ERROR!
A51: Desserts appertises | B51: RR100-850 | C51: 10.9 | D51: =IFERROR(ROUND(C51*0.95,2),"") -> #ERROR! | E51: =IFERROR(ROUND(C51*0.92,2),"") -> #ERROR! | F51: =IFERROR(ROUND(C51*0.88,2),"") -> #ERROR! | G51: =IFERROR(ROUND(C51*1,2),"") -> #ERROR! | H51: =IFERROR(ROUND(C51*0.97,2),"") -> #ERROR! | I51: =IFERROR(ROUND(C51*0.94,2),"") -> #ERROR! | J51: =IFERROR(ROUND((C51/IFERROR(INDEX(Config!B:B,MATCH("TVA "&A51,Config!A:A,0)),1.055))*0.55,2),"") -> #ERROR! | K51: =IFERROR(ROUND((C51/IFERROR(INDEX(Config!B:B,MATCH("TVA "&A51,Config!A:A,0)),1.055))*0.48,2),"") -> #ERROR! | L51: =IFERROR(ROUND((C51/IFERROR(INDEX(Config!B:B,MATCH("TVA "&A51,Config!A:A,0)),1.055))*0.42,2),"") -> #ERROR! | M51: =IFERROR(ROUND((C51/IFERROR(INDEX(Config!B:B,MATCH("TVA "&A51,Config!A:A,0)),1.055))*0.58,2),"") -> #ERROR! | N51: =IFERROR(ROUND((C51/IFERROR(INDEX(Config!B:B,MATCH("TVA "&A51,Config!A:A,0)),1.055))*0.52,2),"") -> #ERROR! | O51: =IFERROR(ROUND((C51/IFERROR(INDEX(Config!B:B,MATCH("TVA "&A51,Config!A:A,0)),1.055))*0.52,2),"") -> #ERROR! | P51: =IFERROR(ROUND((C51/IFERROR(INDEX(Config!B:B,MATCH("TVA "&A51,Config!A:A,0)),1.055))*0.55,2),"") -> #ERROR! | Q51: =IFERROR(ROUND((C51/IFERROR(INDEX(Config!B:B,MATCH("TVA "&A51,Config!A:A,0)),1.055))*0.5,2),"") -> #ERROR! | R51: =IFERROR(ROUND((C51/IFERROR(INDEX(Config!B:B,MATCH("TVA "&A51,Config!A:A,0)),1.055))*0.5,2),"") -> #ERROR! | S51: =IFERROR(ROUND((C51/IFERROR(INDEX(Config!B:B,MATCH("TVA "&A51,Config!A:A,0)),1.055))*0.62,2),"") -> #ERROR! | T51: =IFERROR(ROUND((C51/IFERROR(INDEX(Config!B:B,MATCH("TVA "&A51,Config!A:A,0)),1.055))*0.58,2),"") -> #ERROR! | U51: =IFERROR(ROUND((C51/IFERROR(INDEX(Config!B:B,MATCH("TVA "&A51,Config!A:A,0)),1.055))*0.58,2),"") -> #ERROR! | V51: =IFERROR(((C51/IFERROR(INDEX(Config!B:B,MATCH("TVA "&A51,Config!A:A,0)),1.055))-IFERROR(INDEX('Cout de Revient'!I:I,MATCH(B51,'Cout de Revient'!C:C,0)),0))/(C51/IFERROR(INDEX(Config!B:B,MATCH("TVA "&A51,Config!A:A,0)),1.055)),"") -> #ERROR! | W51: =IFERROR(C51,"") -> #ERROR! | X51: =IFERROR(ROUND(C51*0.85,2),"") -> #ERROR!
A52: Desserts appertises | B52: RR100-1050 | C52: 14.9 | D52: =IFERROR(ROUND(C52*0.95,2),"") -> #ERROR! | E52: =IFERROR(ROUND(C52*0.92,2),"") -> #ERROR! | F52: =IFERROR(ROUND(C52*0.88,2),"") -> #ERROR! | G52: =IFERROR(ROUND(C52*1,2),"") -> #ERROR! | H52: =IFERROR(ROUND(C52*0.97,2),"") -> #ERROR! | I52: =IFERROR(ROUND(C52*0.94,2),"") -> #ERROR! | J52: =IFERROR(ROUND((C52/IFERROR(INDEX(Config!B:B,MATCH("TVA "&A52,Config!A:A,0)),1.055))*0.55,2),"") -> #ERROR! | K52: =IFERROR(ROUND((C52/IFERROR(INDEX(Config!B:B,MATCH("TVA "&A52,Config!A:A,0)),1.055))*0.48,2),"") -> #ERROR! | L52: =IFERROR(ROUND((C52/IFERROR(INDEX(Config!B:B,MATCH("TVA "&A52,Config!A:A,0)),1.055))*0.42,2),"") -> #ERROR! | M52: =IFERROR(ROUND((C52/IFERROR(INDEX(Config!B:B,MATCH("TVA "&A52,Config!A:A,0)),1.055))*0.58,2),"") -> #ERROR! | N52: =IFERROR(ROUND((C52/IFERROR(INDEX(Config!B:B,MATCH("TVA "&A52,Config!A:A,0)),1.055))*0.52,2),"") -> #ERROR! | O52: =IFERROR(ROUND((C52/IFERROR(INDEX(Config!B:B,MATCH("TVA "&A52,Config!A:A,0)),1.055))*0.52,2),"") -> #ERROR! | P52: =IFERROR(ROUND((C52/IFERROR(INDEX(Config!B:B,MATCH("TVA "&A52,Config!A:A,0)),1.055))*0.55,2),"") -> #ERROR! | Q52: =IFERROR(ROUND((C52/IFERROR(INDEX(Config!B:B,MATCH("TVA "&A52,Config!A:A,0)),1.055))*0.5,2),"") -> #ERROR! | R52: =IFERROR(ROUND((C52/IFERROR(INDEX(Config!B:B,MATCH("TVA "&A52,Config!A:A,0)),1.055))*0.5,2),"") -> #ERROR! | S52: =IFERROR(ROUND((C52/IFERROR(INDEX(Config!B:B,MATCH("TVA "&A52,Config!A:A,0)),1.055))*0.62,2),"") -> #ERROR! | T52: =IFERROR(ROUND((C52/IFERROR(INDEX(Config!B:B,MATCH("TVA "&A52,Config!A:A,0)),1.055))*0.58,2),"") -> #ERROR! | U52: =IFERROR(ROUND((C52/IFERROR(INDEX(Config!B:B,MATCH("TVA "&A52,Config!A:A,0)),1.055))*0.58,2),"") -> #ERROR! | V52: =IFERROR(((C52/IFERROR(INDEX(Config!B:B,MATCH("TVA "&A52,Config!A:A,0)),1.055))-IFERROR(INDEX('Cout de Revient'!I:I,MATCH(B52,'Cout de Revient'!C:C,0)),0))/(C52/IFERROR(INDEX(Config!B:B,MATCH("TVA "&A52,Config!A:A,0)),1.055)),"") -> #ERROR! | W52: =IFERROR(C52,"") -> #ERROR! | X52: =IFERROR(ROUND(C52*0.85,2),"") -> #ERROR!
A53: Desserts appertises | B53: RR100-1550 | C53: 19.9 | D53: =IFERROR(ROUND(C53*0.95,2),"") -> #ERROR! | E53: =IFERROR(ROUND(C53*0.92,2),"") -> #ERROR! | F53: =IFERROR(ROUND(C53*0.88,2),"") -> #ERROR! | G53: =IFERROR(ROUND(C53*1,2),"") -> #ERROR! | H53: =IFERROR(ROUND(C53*0.97,2),"") -> #ERROR! | I53: =IFERROR(ROUND(C53*0.94,2),"") -> #ERROR! | J53: =IFERROR(ROUND((C53/IFERROR(INDEX(Config!B:B,MATCH("TVA "&A53,Config!A:A,0)),1.055))*0.55,2),"") -> #ERROR! | K53: =IFERROR(ROUND((C53/IFERROR(INDEX(Config!B:B,MATCH("TVA "&A53,Config!A:A,0)),1.055))*0.48,2),"") -> #ERROR! | L53: =IFERROR(ROUND((C53/IFERROR(INDEX(Config!B:B,MATCH("TVA "&A53,Config!A:A,0)),1.055))*0.42,2),"") -> #ERROR! | M53: =IFERROR(ROUND((C53/IFERROR(INDEX(Config!B:B,MATCH("TVA "&A53,Config!A:A,0)),1.055))*0.58,2),"") -> #ERROR! | N53: =IFERROR(ROUND((C53/IFERROR(INDEX(Config!B:B,MATCH("TVA "&A53,Config!A:A,0)),1.055))*0.52,2),"") -> #ERROR! | O53: =IFERROR(ROUND((C53/IFERROR(INDEX(Config!B:B,MATCH("TVA "&A53,Config!A:A,0)),1.055))*0.52,2),"") -> #ERROR! | P53: =IFERROR(ROUND((C53/IFERROR(INDEX(Config!B:B,MATCH("TVA "&A53,Config!A:A,0)),1.055))*0.55,2),"") -> #ERROR! | Q53: =IFERROR(ROUND((C53/IFERROR(INDEX(Config!B:B,MATCH("TVA "&A53,Config!A:A,0)),1.055))*0.5,2),"") -> #ERROR! | R53: =IFERROR(ROUND((C53/IFERROR(INDEX(Config!B:B,MATCH("TVA "&A53,Config!A:A,0)),1.055))*0.5,2),"") -> #ERROR! | S53: =IFERROR(ROUND((C53/IFERROR(INDEX(Config!B:B,MATCH("TVA "&A53,Config!A:A,0)),1.055))*0.62,2),"") -> #ERROR! | T53: =IFERROR(ROUND((C53/IFERROR(INDEX(Config!B:B,MATCH("TVA "&A53,Config!A:A,0)),1.055))*0.58,2),"") -> #ERROR! | U53: =IFERROR(ROUND((C53/IFERROR(INDEX(Config!B:B,MATCH("TVA "&A53,Config!A:A,0)),1.055))*0.58,2),"") -> #ERROR! | V53: =IFERROR(((C53/IFERROR(INDEX(Config!B:B,MATCH("TVA "&A53,Config!A:A,0)),1.055))-IFERROR(INDEX('Cout de Revient'!I:I,MATCH(B53,'Cout de Revient'!C:C,0)),0))/(C53/IFERROR(INDEX(Config!B:B,MATCH("TVA "&A53,Config!A:A,0)),1.055)),"") -> #ERROR! | W53: =IFERROR(C53,"") -> #ERROR! | X53: =IFERROR(ROUND(C53*0.85,2),"") -> #ERROR!
A54: Desserts appertises | B54: W60-050 | C54: 2.2 | D54: =IFERROR(ROUND(C54*0.95,2),"") -> #ERROR! | E54: =IFERROR(ROUND(C54*0.92,2),"") -> #ERROR! | F54: =IFERROR(ROUND(C54*0.88,2),"") -> #ERROR! | G54: =IFERROR(ROUND(C54*1,2),"") -> #ERROR! | H54: =IFERROR(ROUND(C54*0.97,2),"") -> #ERROR! | I54: =IFERROR(ROUND(C54*0.94,2),"") -> #ERROR! | J54: =IFERROR(ROUND((C54/IFERROR(INDEX(Config!B:B,MATCH("TVA "&A54,Config!A:A,0)),1.055))*0.55,2),"") -> #ERROR! | K54: =IFERROR(ROUND((C54/IFERROR(INDEX(Config!B:B,MATCH("TVA "&A54,Config!A:A,0)),1.055))*0.48,2),"") -> #ERROR! | L54: =IFERROR(ROUND((C54/IFERROR(INDEX(Config!B:B,MATCH("TVA "&A54,Config!A:A,0)),1.055))*0.42,2),"") -> #ERROR! | M54: =IFERROR(ROUND((C54/IFERROR(INDEX(Config!B:B,MATCH("TVA "&A54,Config!A:A,0)),1.055))*0.58,2),"") -> #ERROR! | N54: =IFERROR(ROUND((C54/IFERROR(INDEX(Config!B:B,MATCH("TVA "&A54,Config!A:A,0)),1.055))*0.52,2),"") -> #ERROR! | O54: =IFERROR(ROUND((C54/IFERROR(INDEX(Config!B:B,MATCH("TVA "&A54,Config!A:A,0)),1.055))*0.52,2),"") -> #ERROR! | P54: =IFERROR(ROUND((C54/IFERROR(INDEX(Config!B:B,MATCH("TVA "&A54,Config!A:A,0)),1.055))*0.55,2),"") -> #ERROR! | Q54: =IFERROR(ROUND((C54/IFERROR(INDEX(Config!B:B,MATCH("TVA "&A54,Config!A:A,0)),1.055))*0.5,2),"") -> #ERROR! | R54: =IFERROR(ROUND((C54/IFERROR(INDEX(Config!B:B,MATCH("TVA "&A54,Config!A:A,0)),1.055))*0.5,2),"") -> #ERROR! | S54: =IFERROR(ROUND((C54/IFERROR(INDEX(Config!B:B,MATCH("TVA "&A54,Config!A:A,0)),1.055))*0.62,2),"") -> #ERROR! | T54: =IFERROR(ROUND((C54/IFERROR(INDEX(Config!B:B,MATCH("TVA "&A54,Config!A:A,0)),1.055))*0.58,2),"") -> #ERROR! | U54: =IFERROR(ROUND((C54/IFERROR(INDEX(Config!B:B,MATCH("TVA "&A54,Config!A:A,0)),1.055))*0.58,2),"") -> #ERROR! | V54: =IFERROR(((C54/IFERROR(INDEX(Config!B:B,MATCH("TVA "&A54,Config!A:A,0)),1.055))-IFERROR(INDEX('Cout de Revient'!I:I,MATCH(B54,'Cout de Revient'!C:C,0)),0))/(C54/IFERROR(INDEX(Config!B:B,MATCH("TVA "&A54,Config!A:A,0)),1.055)),"") -> #ERROR! | W54: =IFERROR(C54,"") -> #ERROR! | X54: =IFERROR(ROUND(C54*0.85,2),"") -> #ERROR!
A55: Desserts appertises | B55: W60-080 | C55: 2.9 | D55: =IFERROR(ROUND(C55*0.95,2),"") -> #ERROR! | E55: =IFERROR(ROUND(C55*0.92,2),"") -> #ERROR! | F55: =IFERROR(ROUND(C55*0.88,2),"") -> #ERROR! | G55: =IFERROR(ROUND(C55*1,2),"") -> #ERROR! | H55: =IFERROR(ROUND(C55*0.97,2),"") -> #ERROR! | I55: =IFERROR(ROUND(C55*0.94,2),"") -> #ERROR! | J55: =IFERROR(ROUND((C55/IFERROR(INDEX(Config!B:B,MATCH("TVA "&A55,Config!A:A,0)),1.055))*0.55,2),"") -> #ERROR! | K55: =IFERROR(ROUND((C55/IFERROR(INDEX(Config!B:B,MATCH("TVA "&A55,Config!A:A,0)),1.055))*0.48,2),"") -> #ERROR! | L55: =IFERROR(ROUND((C55/IFERROR(INDEX(Config!B:B,MATCH("TVA "&A55,Config!A:A,0)),1.055))*0.42,2),"") -> #ERROR! | M55: =IFERROR(ROUND((C55/IFERROR(INDEX(Config!B:B,MATCH("TVA "&A55,Config!A:A,0)),1.055))*0.58,2),"") -> #ERROR! | N55: =IFERROR(ROUND((C55/IFERROR(INDEX(Config!B:B,MATCH("TVA "&A55,Config!A:A,0)),1.055))*0.52,2),"") -> #ERROR! | O55: =IFERROR(ROUND((C55/IFERROR(INDEX(Config!B:B,MATCH("TVA "&A55,Config!A:A,0)),1.055))*0.52,2),"") -> #ERROR! | P55: =IFERROR(ROUND((C55/IFERROR(INDEX(Config!B:B,MATCH("TVA "&A55,Config!A:A,0)),1.055))*0.55,2),"") -> #ERROR! | Q55: =IFERROR(ROUND((C55/IFERROR(INDEX(Config!B:B,MATCH("TVA "&A55,Config!A:A,0)),1.055))*0.5,2),"") -> #ERROR! | R55: =IFERROR(ROUND((C55/IFERROR(INDEX(Config!B:B,MATCH("TVA "&A55,Config!A:A,0)),1.055))*0.5,2),"") -> #ERROR! | S55: =IFERROR(ROUND((C55/IFERROR(INDEX(Config!B:B,MATCH("TVA "&A55,Config!A:A,0)),1.055))*0.62,2),"") -> #ERROR! | T55: =IFERROR(ROUND((C55/IFERROR(INDEX(Config!B:B,MATCH("TVA "&A55,Config!A:A,0)),1.055))*0.58,2),"") -> #ERROR! | U55: =IFERROR(ROUND((C55/IFERROR(INDEX(Config!B:B,MATCH("TVA "&A55,Config!A:A,0)),1.055))*0.58,2),"") -> #ERROR! | V55: =IFERROR(((C55/IFERROR(INDEX(Config!B:B,MATCH("TVA "&A55,Config!A:A,0)),1.055))-IFERROR(INDEX('Cout de Revient'!I:I,MATCH(B55,'Cout de Revient'!C:C,0)),0))/(C55/IFERROR(INDEX(Config!B:B,MATCH("TVA "&A55,Config!A:A,0)),1.055)),"") -> #ERROR! | W55: =IFERROR(C55,"") -> #ERROR! | X55: =IFERROR(ROUND(C55*0.85,2),"") -> #ERROR!
A56: Desserts appertises | B56: W60-160 | C56: 3.9 | D56: =IFERROR(ROUND(C56*0.95,2),"") -> #ERROR! | E56: =IFERROR(ROUND(C56*0.92,2),"") -> #ERROR! | F56: =IFERROR(ROUND(C56*0.88,2),"") -> #ERROR! | G56: =IFERROR(ROUND(C56*1,2),"") -> #ERROR! | H56: =IFERROR(ROUND(C56*0.97,2),"") -> #ERROR! | I56: =IFERROR(ROUND(C56*0.94,2),"") -> #ERROR! | J56: =IFERROR(ROUND((C56/IFERROR(INDEX(Config!B:B,MATCH("TVA "&A56,Config!A:A,0)),1.055))*0.55,2),"") -> #ERROR! | K56: =IFERROR(ROUND((C56/IFERROR(INDEX(Config!B:B,MATCH("TVA "&A56,Config!A:A,0)),1.055))*0.48,2),"") -> #ERROR! | L56: =IFERROR(ROUND((C56/IFERROR(INDEX(Config!B:B,MATCH("TVA "&A56,Config!A:A,0)),1.055))*0.42,2),"") -> #ERROR! | M56: =IFERROR(ROUND((C56/IFERROR(INDEX(Config!B:B,MATCH("TVA "&A56,Config!A:A,0)),1.055))*0.58,2),"") -> #ERROR! | N56: =IFERROR(ROUND((C56/IFERROR(INDEX(Config!B:B,MATCH("TVA "&A56,Config!A:A,0)),1.055))*0.52,2),"") -> #ERROR! | O56: =IFERROR(ROUND((C56/IFERROR(INDEX(Config!B:B,MATCH("TVA "&A56,Config!A:A,0)),1.055))*0.52,2),"") -> #ERROR! | P56: =IFERROR(ROUND((C56/IFERROR(INDEX(Config!B:B,MATCH("TVA "&A56,Config!A:A,0)),1.055))*0.55,2),"") -> #ERROR! | Q56: =IFERROR(ROUND((C56/IFERROR(INDEX(Config!B:B,MATCH("TVA "&A56,Config!A:A,0)),1.055))*0.5,2),"") -> #ERROR! | R56: =IFERROR(ROUND((C56/IFERROR(INDEX(Config!B:B,MATCH("TVA "&A56,Config!A:A,0)),1.055))*0.5,2),"") -> #ERROR! | S56: =IFERROR(ROUND((C56/IFERROR(INDEX(Config!B:B,MATCH("TVA "&A56,Config!A:A,0)),1.055))*0.62,2),"") -> #ERROR! | T56: =IFERROR(ROUND((C56/IFERROR(INDEX(Config!B:B,MATCH("TVA "&A56,Config!A:A,0)),1.055))*0.58,2),"") -> #ERROR! | U56: =IFERROR(ROUND((C56/IFERROR(INDEX(Config!B:B,MATCH("TVA "&A56,Config!A:A,0)),1.055))*0.58,2),"") -> #ERROR! | V56: =IFERROR(((C56/IFERROR(INDEX(Config!B:B,MATCH("TVA "&A56,Config!A:A,0)),1.055))-IFERROR(INDEX('Cout de Revient'!I:I,MATCH(B56,'Cout de Revient'!C:C,0)),0))/(C56/IFERROR(INDEX(Config!B:B,MATCH("TVA "&A56,Config!A:A,0)),1.055)),"") -> #ERROR! | W56: =IFERROR(C56,"") -> #ERROR! | X56: =IFERROR(ROUND(C56*0.85,2),"") -> #ERROR!
A57: SOUPES — TVA 5%
A58: Soupes | B58: RR100-290 | C58: 3.9 | D58: =IFERROR(ROUND(C58*0.95,2),"") -> #ERROR! | E58: =IFERROR(ROUND(C58*0.92,2),"") -> #ERROR! | F58: =IFERROR(ROUND(C58*0.88,2),"") -> #ERROR! | G58: =IFERROR(ROUND(C58*1,2),"") -> #ERROR! | H58: =IFERROR(ROUND(C58*0.97,2),"") -> #ERROR! | I58: =IFERROR(ROUND(C58*0.94,2),"") -> #ERROR! | J58: =IFERROR(ROUND((C58/IFERROR(INDEX(Config!B:B,MATCH("TVA "&A58,Config!A:A,0)),1.055))*0.55,2),"") -> #ERROR! | K58: =IFERROR(ROUND((C58/IFERROR(INDEX(Config!B:B,MATCH("TVA "&A58,Config!A:A,0)),1.055))*0.48,2),"") -> #ERROR! | L58: =IFERROR(ROUND((C58/IFERROR(INDEX(Config!B:B,MATCH("TVA "&A58,Config!A:A,0)),1.055))*0.42,2),"") -> #ERROR! | M58: =IFERROR(ROUND((C58/IFERROR(INDEX(Config!B:B,MATCH("TVA "&A58,Config!A:A,0)),1.055))*0.58,2),"") -> #ERROR! | N58: =IFERROR(ROUND((C58/IFERROR(INDEX(Config!B:B,MATCH("TVA "&A58,Config!A:A,0)),1.055))*0.52,2),"") -> #ERROR! | O58: =IFERROR(ROUND((C58/IFERROR(INDEX(Config!B:B,MATCH("TVA "&A58,Config!A:A,0)),1.055))*0.52,2),"") -> #ERROR! | P58: =IFERROR(ROUND((C58/IFERROR(INDEX(Config!B:B,MATCH("TVA "&A58,Config!A:A,0)),1.055))*0.55,2),"") -> #ERROR! | Q58: =IFERROR(ROUND((C58/IFERROR(INDEX(Config!B:B,MATCH("TVA "&A58,Config!A:A,0)),1.055))*0.5,2),"") -> #ERROR! | R58: =IFERROR(ROUND((C58/IFERROR(INDEX(Config!B:B,MATCH("TVA "&A58,Config!A:A,0)),1.055))*0.5,2),"") -> #ERROR! | S58: =IFERROR(ROUND((C58/IFERROR(INDEX(Config!B:B,MATCH("TVA "&A58,Config!A:A,0)),1.055))*0.62,2),"") -> #ERROR! | T58: =IFERROR(ROUND((C58/IFERROR(INDEX(Config!B:B,MATCH("TVA "&A58,Config!A:A,0)),1.055))*0.58,2),"") -> #ERROR! | U58: =IFERROR(ROUND((C58/IFERROR(INDEX(Config!B:B,MATCH("TVA "&A58,Config!A:A,0)),1.055))*0.58,2),"") -> #ERROR! | V58: =IFERROR(((C58/IFERROR(INDEX(Config!B:B,MATCH("TVA "&A58,Config!A:A,0)),1.055))-IFERROR(INDEX('Cout de Revient'!I:I,MATCH(B58,'Cout de Revient'!C:C,0)),0))/(C58/IFERROR(INDEX(Config!B:B,MATCH("TVA "&A58,Config!A:A,0)),1.055)),"") -> #ERROR! | W58: =IFERROR(C58,"") -> #ERROR! | X58: =IFERROR(ROUND(C58*0.85,2),"") -> #ERROR!
A59: Soupes | B59: RR100-370 | C59: 4.9 | D59: =IFERROR(ROUND(C59*0.95,2),"") -> #ERROR! | E59: =IFERROR(ROUND(C59*0.92,2),"") -> #ERROR! | F59: =IFERROR(ROUND(C59*0.88,2),"") -> #ERROR! | G59: =IFERROR(ROUND(C59*1,2),"") -> #ERROR! | H59: =IFERROR(ROUND(C59*0.97,2),"") -> #ERROR! | I59: =IFERROR(ROUND(C59*0.94,2),"") -> #ERROR! | J59: =IFERROR(ROUND((C59/IFERROR(INDEX(Config!B:B,MATCH("TVA "&A59,Config!A:A,0)),1.055))*0.55,2),"") -> #ERROR! | K59: =IFERROR(ROUND((C59/IFERROR(INDEX(Config!B:B,MATCH("TVA "&A59,Config!A:A,0)),1.055))*0.48,2),"") -> #ERROR! | L59: =IFERROR(ROUND((C59/IFERROR(INDEX(Config!B:B,MATCH("TVA "&A59,Config!A:A,0)),1.055))*0.42,2),"") -> #ERROR! | M59: =IFERROR(ROUND((C59/IFERROR(INDEX(Config!B:B,MATCH("TVA "&A59,Config!A:A,0)),1.055))*0.58,2),"") -> #ERROR! | N59: =IFERROR(ROUND((C59/IFERROR(INDEX(Config!B:B,MATCH("TVA "&A59,Config!A:A,0)),1.055))*0.52,2),"") -> #ERROR! | O59: =IFERROR(ROUND((C59/IFERROR(INDEX(Config!B:B,MATCH("TVA "&A59,Config!A:A,0)),1.055))*0.52,2),"") -> #ERROR! | P59: =IFERROR(ROUND((C59/IFERROR(INDEX(Config!B:B,MATCH("TVA "&A59,Config!A:A,0)),1.055))*0.55,2),"") -> #ERROR! | Q59: =IFERROR(ROUND((C59/IFERROR(INDEX(Config!B:B,MATCH("TVA "&A59,Config!A:A,0)),1.055))*0.5,2),"") -> #ERROR! | R59: =IFERROR(ROUND((C59/IFERROR(INDEX(Config!B:B,MATCH("TVA "&A59,Config!A:A,0)),1.055))*0.5,2),"") -> #ERROR! | S59: =IFERROR(ROUND((C59/IFERROR(INDEX(Config!B:B,MATCH("TVA "&A59,Config!A:A,0)),1.055))*0.62,2),"") -> #ERROR! | T59: =IFERROR(ROUND((C59/IFERROR(INDEX(Config!B:B,MATCH("TVA "&A59,Config!A:A,0)),1.055))*0.58,2),"") -> #ERROR! | U59: =IFERROR(ROUND((C59/IFERROR(INDEX(Config!B:B,MATCH("TVA "&A59,Config!A:A,0)),1.055))*0.58,2),"") -> #ERROR! | V59: =IFERROR(((C59/IFERROR(INDEX(Config!B:B,MATCH("TVA "&A59,Config!A:A,0)),1.055))-IFERROR(INDEX('Cout de Revient'!I:I,MATCH(B59,'Cout de Revient'!C:C,0)),0))/(C59/IFERROR(INDEX(Config!B:B,MATCH("TVA "&A59,Config!A:A,0)),1.055)),"") -> #ERROR! | W59: =IFERROR(C59,"") -> #ERROR! | X59: =IFERROR(ROUND(C59*0.85,2),"") -> #ERROR!
A60: Soupes | B60: RR100-580 | C60: 6.9 | D60: =IFERROR(ROUND(C60*0.95,2),"") -> #ERROR! | E60: =IFERROR(ROUND(C60*0.92,2),"") -> #ERROR! | F60: =IFERROR(ROUND(C60*0.88,2),"") -> #ERROR! | G60: =IFERROR(ROUND(C60*1,2),"") -> #ERROR! | H60: =IFERROR(ROUND(C60*0.97,2),"") -> #ERROR! | I60: =IFERROR(ROUND(C60*0.94,2),"") -> #ERROR! | J60: =IFERROR(ROUND((C60/IFERROR(INDEX(Config!B:B,MATCH("TVA "&A60,Config!A:A,0)),1.055))*0.55,2),"") -> #ERROR! | K60: =IFERROR(ROUND((C60/IFERROR(INDEX(Config!B:B,MATCH("TVA "&A60,Config!A:A,0)),1.055))*0.48,2),"") -> #ERROR! | L60: =IFERROR(ROUND((C60/IFERROR(INDEX(Config!B:B,MATCH("TVA "&A60,Config!A:A,0)),1.055))*0.42,2),"") -> #ERROR! | M60: =IFERROR(ROUND((C60/IFERROR(INDEX(Config!B:B,MATCH("TVA "&A60,Config!A:A,0)),1.055))*0.58,2),"") -> #ERROR! | N60: =IFERROR(ROUND((C60/IFERROR(INDEX(Config!B:B,MATCH("TVA "&A60,Config!A:A,0)),1.055))*0.52,2),"") -> #ERROR! | O60: =IFERROR(ROUND((C60/IFERROR(INDEX(Config!B:B,MATCH("TVA "&A60,Config!A:A,0)),1.055))*0.52,2),"") -> #ERROR! | P60: =IFERROR(ROUND((C60/IFERROR(INDEX(Config!B:B,MATCH("TVA "&A60,Config!A:A,0)),1.055))*0.55,2),"") -> #ERROR! | Q60: =IFERROR(ROUND((C60/IFERROR(INDEX(Config!B:B,MATCH("TVA "&A60,Config!A:A,0)),1.055))*0.5,2),"") -> #ERROR! | R60: =IFERROR(ROUND((C60/IFERROR(INDEX(Config!B:B,MATCH("TVA "&A60,Config!A:A,0)),1.055))*0.5,2),"") -> #ERROR! | S60: =IFERROR(ROUND((C60/IFERROR(INDEX(Config!B:B,MATCH("TVA "&A60,Config!A:A,0)),1.055))*0.62,2),"") -> #ERROR! | T60: =IFERROR(ROUND((C60/IFERROR(INDEX(Config!B:B,MATCH("TVA "&A60,Config!A:A,0)),1.055))*0.58,2),"") -> #ERROR! | U60: =IFERROR(ROUND((C60/IFERROR(INDEX(Config!B:B,MATCH("TVA "&A60,Config!A:A,0)),1.055))*0.58,2),"") -> #ERROR! | V60: =IFERROR(((C60/IFERROR(INDEX(Config!B:B,MATCH("TVA "&A60,Config!A:A,0)),1.055))-IFERROR(INDEX('Cout de Revient'!I:I,MATCH(B60,'Cout de Revient'!C:C,0)),0))/(C60/IFERROR(INDEX(Config!B:B,MATCH("TVA "&A60,Config!A:A,0)),1.055)),"") -> #ERROR! | W60: =IFERROR(C60,"") -> #ERROR! | X60: =IFERROR(ROUND(C60*0.85,2),"") -> #ERROR!
A61: Soupes | B61: RR100-850 | C61: 9.9 | D61: =IFERROR(ROUND(C61*0.95,2),"") -> #ERROR! | E61: =IFERROR(ROUND(C61*0.92,2),"") -> #ERROR! | F61: =IFERROR(ROUND(C61*0.88,2),"") -> #ERROR! | G61: =IFERROR(ROUND(C61*1,2),"") -> #ERROR! | H61: =IFERROR(ROUND(C61*0.97,2),"") -> #ERROR! | I61: =IFERROR(ROUND(C61*0.94,2),"") -> #ERROR! | J61: =IFERROR(ROUND((C61/IFERROR(INDEX(Config!B:B,MATCH("TVA "&A61,Config!A:A,0)),1.055))*0.55,2),"") -> #ERROR! | K61: =IFERROR(ROUND((C61/IFERROR(INDEX(Config!B:B,MATCH("TVA "&A61,Config!A:A,0)),1.055))*0.48,2),"") -> #ERROR! | L61: =IFERROR(ROUND((C61/IFERROR(INDEX(Config!B:B,MATCH("TVA "&A61,Config!A:A,0)),1.055))*0.42,2),"") -> #ERROR! | M61: =IFERROR(ROUND((C61/IFERROR(INDEX(Config!B:B,MATCH("TVA "&A61,Config!A:A,0)),1.055))*0.58,2),"") -> #ERROR! | N61: =IFERROR(ROUND((C61/IFERROR(INDEX(Config!B:B,MATCH("TVA "&A61,Config!A:A,0)),1.055))*0.52,2),"") -> #ERROR! | O61: =IFERROR(ROUND((C61/IFERROR(INDEX(Config!B:B,MATCH("TVA "&A61,Config!A:A,0)),1.055))*0.52,2),"") -> #ERROR! | P61: =IFERROR(ROUND((C61/IFERROR(INDEX(Config!B:B,MATCH("TVA "&A61,Config!A:A,0)),1.055))*0.55,2),"") -> #ERROR! | Q61: =IFERROR(ROUND((C61/IFERROR(INDEX(Config!B:B,MATCH("TVA "&A61,Config!A:A,0)),1.055))*0.5,2),"") -> #ERROR! | R61: =IFERROR(ROUND((C61/IFERROR(INDEX(Config!B:B,MATCH("TVA "&A61,Config!A:A,0)),1.055))*0.5,2),"") -> #ERROR! | S61: =IFERROR(ROUND((C61/IFERROR(INDEX(Config!B:B,MATCH("TVA "&A61,Config!A:A,0)),1.055))*0.62,2),"") -> #ERROR! | T61: =IFERROR(ROUND((C61/IFERROR(INDEX(Config!B:B,MATCH("TVA "&A61,Config!A:A,0)),1.055))*0.58,2),"") -> #ERROR! | U61: =IFERROR(ROUND((C61/IFERROR(INDEX(Config!B:B,MATCH("TVA "&A61,Config!A:A,0)),1.055))*0.58,2),"") -> #ERROR! | V61: =IFERROR(((C61/IFERROR(INDEX(Config!B:B,MATCH("TVA "&A61,Config!A:A,0)),1.055))-IFERROR(INDEX('Cout de Revient'!I:I,MATCH(B61,'Cout de Revient'!C:C,0)),0))/(C61/IFERROR(INDEX(Config!B:B,MATCH("TVA "&A61,Config!A:A,0)),1.055)),"") -> #ERROR! | W61: =IFERROR(C61,"") -> #ERROR! | X61: =IFERROR(ROUND(C61*0.85,2),"") -> #ERROR!
A62: Soupes | B62: RR100-1050 | C62: 12.9 | D62: =IFERROR(ROUND(C62*0.95,2),"") -> #ERROR! | E62: =IFERROR(ROUND(C62*0.92,2),"") -> #ERROR! | F62: =IFERROR(ROUND(C62*0.88,2),"") -> #ERROR! | G62: =IFERROR(ROUND(C62*1,2),"") -> #ERROR! | H62: =IFERROR(ROUND(C62*0.97,2),"") -> #ERROR! | I62: =IFERROR(ROUND(C62*0.94,2),"") -> #ERROR! | J62: =IFERROR(ROUND((C62/IFERROR(INDEX(Config!B:B,MATCH("TVA "&A62,Config!A:A,0)),1.055))*0.55,2),"") -> #ERROR! | K62: =IFERROR(ROUND((C62/IFERROR(INDEX(Config!B:B,MATCH("TVA "&A62,Config!A:A,0)),1.055))*0.48,2),"") -> #ERROR! | L62: =IFERROR(ROUND((C62/IFERROR(INDEX(Config!B:B,MATCH("TVA "&A62,Config!A:A,0)),1.055))*0.42,2),"") -> #ERROR! | M62: =IFERROR(ROUND((C62/IFERROR(INDEX(Config!B:B,MATCH("TVA "&A62,Config!A:A,0)),1.055))*0.58,2),"") -> #ERROR! | N62: =IFERROR(ROUND((C62/IFERROR(INDEX(Config!B:B,MATCH("TVA "&A62,Config!A:A,0)),1.055))*0.52,2),"") -> #ERROR! | O62: =IFERROR(ROUND((C62/IFERROR(INDEX(Config!B:B,MATCH("TVA "&A62,Config!A:A,0)),1.055))*0.52,2),"") -> #ERROR! | P62: =IFERROR(ROUND((C62/IFERROR(INDEX(Config!B:B,MATCH("TVA "&A62,Config!A:A,0)),1.055))*0.55,2),"") -> #ERROR! | Q62: =IFERROR(ROUND((C62/IFERROR(INDEX(Config!B:B,MATCH("TVA "&A62,Config!A:A,0)),1.055))*0.5,2),"") -> #ERROR! | R62: =IFERROR(ROUND((C62/IFERROR(INDEX(Config!B:B,MATCH("TVA "&A62,Config!A:A,0)),1.055))*0.5,2),"") -> #ERROR! | S62: =IFERROR(ROUND((C62/IFERROR(INDEX(Config!B:B,MATCH("TVA "&A62,Config!A:A,0)),1.055))*0.62,2),"") -> #ERROR! | T62: =IFERROR(ROUND((C62/IFERROR(INDEX(Config!B:B,MATCH("TVA "&A62,Config!A:A,0)),1.055))*0.58,2),"") -> #ERROR! | U62: =IFERROR(ROUND((C62/IFERROR(INDEX(Config!B:B,MATCH("TVA "&A62,Config!A:A,0)),1.055))*0.58,2),"") -> #ERROR! | V62: =IFERROR(((C62/IFERROR(INDEX(Config!B:B,MATCH("TVA "&A62,Config!A:A,0)),1.055))-IFERROR(INDEX('Cout de Revient'!I:I,MATCH(B62,'Cout de Revient'!C:C,0)),0))/(C62/IFERROR(INDEX(Config!B:B,MATCH("TVA "&A62,Config!A:A,0)),1.055)),"") -> #ERROR! | W62: =IFERROR(C62,"") -> #ERROR! | X62: =IFERROR(ROUND(C62*0.85,2),"") -> #ERROR!
A63: Soupes | B63: RR100-1550 | C63: 17.9 | D63: =IFERROR(ROUND(C63*0.95,2),"") -> #ERROR! | E63: =IFERROR(ROUND(C63*0.92,2),"") -> #ERROR! | F63: =IFERROR(ROUND(C63*0.88,2),"") -> #ERROR! | G63: =IFERROR(ROUND(C63*1,2),"") -> #ERROR! | H63: =IFERROR(ROUND(C63*0.97,2),"") -> #ERROR! | I63: =IFERROR(ROUND(C63*0.94,2),"") -> #ERROR! | J63: =IFERROR(ROUND((C63/IFERROR(INDEX(Config!B:B,MATCH("TVA "&A63,Config!A:A,0)),1.055))*0.55,2),"") -> #ERROR! | K63: =IFERROR(ROUND((C63/IFERROR(INDEX(Config!B:B,MATCH("TVA "&A63,Config!A:A,0)),1.055))*0.48,2),"") -> #ERROR! | L63: =IFERROR(ROUND((C63/IFERROR(INDEX(Config!B:B,MATCH("TVA "&A63,Config!A:A,0)),1.055))*0.42,2),"") -> #ERROR! | M63: =IFERROR(ROUND((C63/IFERROR(INDEX(Config!B:B,MATCH("TVA "&A63,Config!A:A,0)),1.055))*0.58,2),"") -> #ERROR! | N63: =IFERROR(ROUND((C63/IFERROR(INDEX(Config!B:B,MATCH("TVA "&A63,Config!A:A,0)),1.055))*0.52,2),"") -> #ERROR! | O63: =IFERROR(ROUND((C63/IFERROR(INDEX(Config!B:B,MATCH("TVA "&A63,Config!A:A,0)),1.055))*0.52,2),"") -> #ERROR! | P63: =IFERROR(ROUND((C63/IFERROR(INDEX(Config!B:B,MATCH("TVA "&A63,Config!A:A,0)),1.055))*0.55,2),"") -> #ERROR! | Q63: =IFERROR(ROUND((C63/IFERROR(INDEX(Config!B:B,MATCH("TVA "&A63,Config!A:A,0)),1.055))*0.5,2),"") -> #ERROR! | R63: =IFERROR(ROUND((C63/IFERROR(INDEX(Config!B:B,MATCH("TVA "&A63,Config!A:A,0)),1.055))*0.5,2),"") -> #ERROR! | S63: =IFERROR(ROUND((C63/IFERROR(INDEX(Config!B:B,MATCH("TVA "&A63,Config!A:A,0)),1.055))*0.62,2),"") -> #ERROR! | T63: =IFERROR(ROUND((C63/IFERROR(INDEX(Config!B:B,MATCH("TVA "&A63,Config!A:A,0)),1.055))*0.58,2),"") -> #ERROR! | U63: =IFERROR(ROUND((C63/IFERROR(INDEX(Config!B:B,MATCH("TVA "&A63,Config!A:A,0)),1.055))*0.58,2),"") -> #ERROR! | V63: =IFERROR(((C63/IFERROR(INDEX(Config!B:B,MATCH("TVA "&A63,Config!A:A,0)),1.055))-IFERROR(INDEX('Cout de Revient'!I:I,MATCH(B63,'Cout de Revient'!C:C,0)),0))/(C63/IFERROR(INDEX(Config!B:B,MATCH("TVA "&A63,Config!A:A,0)),1.055)),"") -> #ERROR! | W63: =IFERROR(C63,"") -> #ERROR! | X63: =IFERROR(ROUND(C63*0.85,2),"") -> #ERROR!

Sheet Analyse Marges
A1: MAISON 41 — ANALYSE DES MARGES PAR CANAL — Calcul dynamique depuis Cout de Revient
A2: Source : Prix Vente + Cout de Revient · Selectionner gamme et format pour voir les marges
A4: PARAMETRES
A5: Gamme analysee | B5: Rillettes | C5: Format analyse | D5: RR100-370 | E5: Cout/bocal (EUR) | F5: 3.7
A7: MARGES PAR CANAL ET PAR PALIER
A8: Canal | B8: Type prix | C8: Palier | D8: Qte min | E8: Prix TTC | F8: Prix HT | G8: Cout/boc | H8: Marge EUR/boc | I8: Marge %
A9: B to C Marches | B9: TTC | C9: x1 | D9: 1 | E9: =IFERROR(INDEX('Prix Vente'!C:C,MATCH($B$5&$D$5,'Prix Vente'!A:A&'Prix Vente'!B:B,0))*(1-0/100),"") -> #ERROR! | F9: =IFERROR(INDEX('Prix Vente'!C:C,MATCH($B$5&$D$5,'Prix Vente'!A:A&'Prix Vente'!B:B,0))/1.055*(1-0/100),"") -> #ERROR! | G9: =$F$5 -> 3.7 | H9: =IFERROR(F9-G9,"") -> #ERROR! | I9: =IFERROR(H9/F9,"") -> #ERROR!
A10: B to C Marches | B10: TTC | C10: x3 -5% | D10: 3 | E10: =IFERROR(INDEX('Prix Vente'!C:C,MATCH($B$5&$D$5,'Prix Vente'!A:A&'Prix Vente'!B:B,0))*(1-5/100),"") -> #ERROR! | F10: =IFERROR(INDEX('Prix Vente'!C:C,MATCH($B$5&$D$5,'Prix Vente'!A:A&'Prix Vente'!B:B,0))/1.055*(1-5/100),"") -> #ERROR! | G10: =$F$5 -> 3.7 | H10: =IFERROR(F10-G10,"") -> #ERROR! | I10: =IFERROR(H10/F10,"") -> #ERROR!
A11: B to C Marches | B11: TTC | C11: x6 -8% | D11: 6 | E11: =IFERROR(INDEX('Prix Vente'!C:C,MATCH($B$5&$D$5,'Prix Vente'!A:A&'Prix Vente'!B:B,0))*(1-8/100),"") -> #ERROR! | F11: =IFERROR(INDEX('Prix Vente'!C:C,MATCH($B$5&$D$5,'Prix Vente'!A:A&'Prix Vente'!B:B,0))/1.055*(1-8/100),"") -> #ERROR! | G11: =$F$5 -> 3.7 | H11: =IFERROR(F11-G11,"") -> #ERROR! | I11: =IFERROR(H11/F11,"") -> #ERROR!
A12: B to C Marches | B12: TTC | C12: x20 -12% | D12: 20 | E12: =IFERROR(INDEX('Prix Vente'!C:C,MATCH($B$5&$D$5,'Prix Vente'!A:A&'Prix Vente'!B:B,0))*(1-12/100),"") -> #ERROR! | F12: =IFERROR(INDEX('Prix Vente'!C:C,MATCH($B$5&$D$5,'Prix Vente'!A:A&'Prix Vente'!B:B,0))/1.055*(1-12/100),"") -> #ERROR! | G12: =$F$5 -> 3.7 | H12: =IFERROR(F12-G12,"") -> #ERROR! | I12: =IFERROR(H12/F12,"") -> #ERROR!
A13: E-commerce | B13: TTC | C13: x1 | D13: 1 | E13: =IFERROR(INDEX('Prix Vente'!C:C,MATCH($B$5&$D$5,'Prix Vente'!A:A&'Prix Vente'!B:B,0))*(1-0/100),"") -> #ERROR! | F13: =IFERROR(INDEX('Prix Vente'!C:C,MATCH($B$5&$D$5,'Prix Vente'!A:A&'Prix Vente'!B:B,0))/1.055*(1-0/100),"") -> #ERROR! | G13: =$F$5 -> 3.7 | H13: =IFERROR(F13-G13,"") -> #ERROR! | I13: =IFERROR(H13/F13,"") -> #ERROR!
A14: E-commerce | B14: TTC | C14: x3 -3% | D14: 3 | E14: =IFERROR(INDEX('Prix Vente'!C:C,MATCH($B$5&$D$5,'Prix Vente'!A:A&'Prix Vente'!B:B,0))*(1-3/100),"") -> #ERROR! | F14: =IFERROR(INDEX('Prix Vente'!C:C,MATCH($B$5&$D$5,'Prix Vente'!A:A&'Prix Vente'!B:B,0))/1.055*(1-3/100),"") -> #ERROR! | G14: =$F$5 -> 3.7 | H14: =IFERROR(F14-G14,"") -> #ERROR! | I14: =IFERROR(H14/F14,"") -> #ERROR!
A15: E-commerce | B15: TTC | C15: x6 -6% | D15: 6 | E15: =IFERROR(INDEX('Prix Vente'!C:C,MATCH($B$5&$D$5,'Prix Vente'!A:A&'Prix Vente'!B:B,0))*(1-6/100),"") -> #ERROR! | F15: =IFERROR(INDEX('Prix Vente'!C:C,MATCH($B$5&$D$5,'Prix Vente'!A:A&'Prix Vente'!B:B,0))/1.055*(1-6/100),"") -> #ERROR! | G15: =$F$5 -> 3.7 | H15: =IFERROR(F15-G15,"") -> #ERROR! | I15: =IFERROR(H15/F15,"") -> #ERROR!
A16: Restaurants | B16: HT | C16: x3 -5% | D16: 3 | E16: =IFERROR(INDEX('Prix Vente'!C:C,MATCH($B$5&$D$5,'Prix Vente'!A:A&'Prix Vente'!B:B,0))*(1-5/100),"") -> #ERROR! | F16: =IFERROR(INDEX('Prix Vente'!C:C,MATCH($B$5&$D$5,'Prix Vente'!A:A&'Prix Vente'!B:B,0))*(1-5/100),"") -> #ERROR! | G16: =$F$5 -> 3.7 | H16: =IFERROR(F16-G16,"") -> #ERROR! | I16: =IFERROR(H16/F16,"") -> #ERROR!
A17: Restaurants | B17: HT | C17: x5 -10% | D17: 5 | E17: =IFERROR(INDEX('Prix Vente'!C:C,MATCH($B$5&$D$5,'Prix Vente'!A:A&'Prix Vente'!B:B,0))*(1-10/100),"") -> #ERROR! | F17: =IFERROR(INDEX('Prix Vente'!C:C,MATCH($B$5&$D$5,'Prix Vente'!A:A&'Prix Vente'!B:B,0))*(1-10/100),"") -> #ERROR! | G17: =$F$5 -> 3.7 | H17: =IFERROR(F17-G17,"") -> #ERROR! | I17: =IFERROR(H17/F17,"") -> #ERROR!
A18: Restaurants | B18: HT | C18: x10 -15% | D18: 10 | E18: =IFERROR(INDEX('Prix Vente'!C:C,MATCH($B$5&$D$5,'Prix Vente'!A:A&'Prix Vente'!B:B,0))*(1-15/100),"") -> #ERROR! | F18: =IFERROR(INDEX('Prix Vente'!C:C,MATCH($B$5&$D$5,'Prix Vente'!A:A&'Prix Vente'!B:B,0))*(1-15/100),"") -> #ERROR! | G18: =$F$5 -> 3.7 | H18: =IFERROR(F18-G18,"") -> #ERROR! | I18: =IFERROR(H18/F18,"") -> #ERROR!
A19: Restaurants | B19: HT | C19: x24 -20% | D19: 24 | E19: =IFERROR(INDEX('Prix Vente'!C:C,MATCH($B$5&$D$5,'Prix Vente'!A:A&'Prix Vente'!B:B,0))*(1-20/100),"") -> #ERROR! | F19: =IFERROR(INDEX('Prix Vente'!C:C,MATCH($B$5&$D$5,'Prix Vente'!A:A&'Prix Vente'!B:B,0))*(1-20/100),"") -> #ERROR! | G19: =$F$5 -> 3.7 | H19: =IFERROR(F19-G19,"") -> #ERROR! | I19: =IFERROR(H19/F19,"") -> #ERROR!
A20: Epiceries fines | B20: HT | C20: x6 -10% | D20: 6 | E20: =IFERROR(INDEX('Prix Vente'!C:C,MATCH($B$5&$D$5,'Prix Vente'!A:A&'Prix Vente'!B:B,0))*(1-10/100),"") -> #ERROR! | F20: =IFERROR(INDEX('Prix Vente'!C:C,MATCH($B$5&$D$5,'Prix Vente'!A:A&'Prix Vente'!B:B,0))*(1-10/100),"") -> #ERROR! | G20: =$F$5 -> 3.7 | H20: =IFERROR(F20-G20,"") -> #ERROR! | I20: =IFERROR(H20/F20,"") -> #ERROR!
A21: Epiceries fines | B21: HT | C21: x12 -15% | D21: 12 | E21: =IFERROR(INDEX('Prix Vente'!C:C,MATCH($B$5&$D$5,'Prix Vente'!A:A&'Prix Vente'!B:B,0))*(1-15/100),"") -> #ERROR! | F21: =IFERROR(INDEX('Prix Vente'!C:C,MATCH($B$5&$D$5,'Prix Vente'!A:A&'Prix Vente'!B:B,0))*(1-15/100),"") -> #ERROR! | G21: =$F$5 -> 3.7 | H21: =IFERROR(F21-G21,"") -> #ERROR! | I21: =IFERROR(H21/F21,"") -> #ERROR!
A22: Epiceries fines | B22: HT | C22: x24 -20% | D22: 24 | E22: =IFERROR(INDEX('Prix Vente'!C:C,MATCH($B$5&$D$5,'Prix Vente'!A:A&'Prix Vente'!B:B,0))*(1-20/100),"") -> #ERROR! | F22: =IFERROR(INDEX('Prix Vente'!C:C,MATCH($B$5&$D$5,'Prix Vente'!A:A&'Prix Vente'!B:B,0))*(1-20/100),"") -> #ERROR! | G22: =$F$5 -> 3.7 | H22: =IFERROR(F22-G22,"") -> #ERROR! | I22: =IFERROR(H22/F22,"") -> #ERROR!
A23: Hotels / Airbnb | B23: HT | C23: x6 -10% | D23: 6 | E23: =IFERROR(INDEX('Prix Vente'!C:C,MATCH($B$5&$D$5,'Prix Vente'!A:A&'Prix Vente'!B:B,0))*(1-10/100),"") -> #ERROR! | F23: =IFERROR(INDEX('Prix Vente'!C:C,MATCH($B$5&$D$5,'Prix Vente'!A:A&'Prix Vente'!B:B,0))*(1-10/100),"") -> #ERROR! | G23: =$F$5 -> 3.7 | H23: =IFERROR(F23-G23,"") -> #ERROR! | I23: =IFERROR(H23/F23,"") -> #ERROR!
A24: Hotels / Airbnb | B24: HT | C24: x12 -15% | D24: 12 | E24: =IFERROR(INDEX('Prix Vente'!C:C,MATCH($B$5&$D$5,'Prix Vente'!A:A&'Prix Vente'!B:B,0))*(1-15/100),"") -> #ERROR! | F24: =IFERROR(INDEX('Prix Vente'!C:C,MATCH($B$5&$D$5,'Prix Vente'!A:A&'Prix Vente'!B:B,0))*(1-15/100),"") -> #ERROR! | G24: =$F$5 -> 3.7 | H24: =IFERROR(F24-G24,"") -> #ERROR! | I24: =IFERROR(H24/F24,"") -> #ERROR!
A25: Hotels / Airbnb | B25: HT | C25: x24 -18% | D25: 24 | E25: =IFERROR(INDEX('Prix Vente'!C:C,MATCH($B$5&$D$5,'Prix Vente'!A:A&'Prix Vente'!B:B,0))*(1-18/100),"") -> #ERROR! | F25: =IFERROR(INDEX('Prix Vente'!C:C,MATCH($B$5&$D$5,'Prix Vente'!A:A&'Prix Vente'!B:B,0))*(1-18/100),"") -> #ERROR! | G25: =$F$5 -> 3.7 | H25: =IFERROR(F25-G25,"") -> #ERROR! | I25: =IFERROR(H25/F25,"") -> #ERROR!
A26: GMS | B26: HT | C26: x100 -25% | D26: 100 | E26: =IFERROR(INDEX('Prix Vente'!C:C,MATCH($B$5&$D$5,'Prix Vente'!A:A&'Prix Vente'!B:B,0))*(1-25/100),"") -> #ERROR! | F26: =IFERROR(INDEX('Prix Vente'!C:C,MATCH($B$5&$D$5,'Prix Vente'!A:A&'Prix Vente'!B:B,0))*(1-25/100),"") -> #ERROR! | G26: =$F$5 -> 3.7 | H26: =IFERROR(F26-G26,"") -> #ERROR! | I26: =IFERROR(H26/F26,"") -> #ERROR!
A27: GMS | B27: HT | C27: x200 -30% | D27: 200 | E27: =IFERROR(INDEX('Prix Vente'!C:C,MATCH($B$5&$D$5,'Prix Vente'!A:A&'Prix Vente'!B:B,0))*(1-30/100),"") -> #ERROR! | F27: =IFERROR(INDEX('Prix Vente'!C:C,MATCH($B$5&$D$5,'Prix Vente'!A:A&'Prix Vente'!B:B,0))*(1-30/100),"") -> #ERROR! | G27: =$F$5 -> 3.7 | H27: =IFERROR(F27-G27,"") -> #ERROR! | I27: =IFERROR(H27/F27,"") -> #ERROR!
A28: GMS | B28: HT | C28: x500 -35% | D28: 500 | E28: =IFERROR(INDEX('Prix Vente'!C:C,MATCH($B$5&$D$5,'Prix Vente'!A:A&'Prix Vente'!B:B,0))*(1-35/100),"") -> #ERROR! | F28: =IFERROR(INDEX('Prix Vente'!C:C,MATCH($B$5&$D$5,'Prix Vente'!A:A&'Prix Vente'!B:B,0))*(1-35/100),"") -> #ERROR! | G28: =$F$5 -> 3.7 | H28: =IFERROR(F28-G28,"") -> #ERROR! | I28: =IFERROR(H28/F28,"") -> #ERROR!

Sheet Simulateur Devis
A1: MAISON 41 — SIMULATEUR DEVIS — Calcul automatique prix + remise volume
A2: Saisir canal · gamme · format · quantite → Prix calcule + remise appliquee
A4: INFORMATIONS CLIENT
A5: Nom client / enseigne
A6: Type de client
A7: Canal de vente | B7: B to C Marches
A8: Date du devis
A9: Validite | B9: 30 jours
A11: LIGNES DE COMMANDE
A12: # | B12: Gamme | C12: Format Weck | D12: Quantite | E12: Prix unit. HT | F12: Remise volume % | G12: Net HT EUR | H12: Net TTC EUR
A13: 1 | E13: =IFERROR(INDEX('Prix Vente'!D:D,MATCH(B13&C13,'Prix Vente'!A:A&'Prix Vente'!B:B,0))/1.055,"") -> #ERROR! | F13: 0 | G13: =IFERROR(D13*E13*(1-F13/100),"") -> #ERROR! | H13: =IFERROR(G13*1.055,"") -> #ERROR!
A14: 2 | E14: =IFERROR(INDEX('Prix Vente'!D:D,MATCH(B14&C14,'Prix Vente'!A:A&'Prix Vente'!B:B,0))/1.055,"") -> #ERROR! | F14: 0 | G14: =IFERROR(D14*E14*(1-F14/100),"") -> #ERROR! | H14: =IFERROR(G14*1.055,"") -> #ERROR!
A15: 3 | E15: =IFERROR(INDEX('Prix Vente'!D:D,MATCH(B15&C15,'Prix Vente'!A:A&'Prix Vente'!B:B,0))/1.055,"") -> #ERROR! | F15: 0 | G15: =IFERROR(D15*E15*(1-F15/100),"") -> #ERROR! | H15: =IFERROR(G15*1.055,"") -> #ERROR!
A16: 4 | E16: =IFERROR(INDEX('Prix Vente'!D:D,MATCH(B16&C16,'Prix Vente'!A:A&'Prix Vente'!B:B,0))/1.055,"") -> #ERROR! | F16: 0 | G16: =IFERROR(D16*E16*(1-F16/100),"") -> #ERROR! | H16: =IFERROR(G16*1.055,"") -> #ERROR!
A17: 5 | E17: =IFERROR(INDEX('Prix Vente'!D:D,MATCH(B17&C17,'Prix Vente'!A:A&'Prix Vente'!B:B,0))/1.055,"") -> #ERROR! | F17: 0 | G17: =IFERROR(D17*E17*(1-F17/100),"") -> #ERROR! | H17: =IFERROR(G17*1.055,"") -> #ERROR!
A18: 6 | E18: =IFERROR(INDEX('Prix Vente'!D:D,MATCH(B18&C18,'Prix Vente'!A:A&'Prix Vente'!B:B,0))/1.055,"") -> #ERROR! | F18: 0 | G18: =IFERROR(D18*E18*(1-F18/100),"") -> #ERROR! | H18: =IFERROR(G18*1.055,"") -> #ERROR!
A19: 7 | E19: =IFERROR(INDEX('Prix Vente'!D:D,MATCH(B19&C19,'Prix Vente'!A:A&'Prix Vente'!B:B,0))/1.055,"") -> #ERROR! | F19: 0 | G19: =IFERROR(D19*E19*(1-F19/100),"") -> #ERROR! | H19: =IFERROR(G19*1.055,"") -> #ERROR!
A20: 8 | E20: =IFERROR(INDEX('Prix Vente'!D:D,MATCH(B20&C20,'Prix Vente'!A:A&'Prix Vente'!B:B,0))/1.055,"") -> #ERROR! | F20: 0 | G20: =IFERROR(D20*E20*(1-F20/100),"") -> #ERROR! | H20: =IFERROR(G20*1.055,"") -> #ERROR!
A21: 9 | E21: =IFERROR(INDEX('Prix Vente'!D:D,MATCH(B21&C21,'Prix Vente'!A:A&'Prix Vente'!B:B,0))/1.055,"") -> #ERROR! | F21: 0 | G21: =IFERROR(D21*E21*(1-F21/100),"") -> #ERROR! | H21: =IFERROR(G21*1.055,"") -> #ERROR!
A22: 10 | E22: =IFERROR(INDEX('Prix Vente'!D:D,MATCH(B22&C22,'Prix Vente'!A:A&'Prix Vente'!B:B,0))/1.055,"") -> #ERROR! | F22: 0 | G22: =IFERROR(D22*E22*(1-F22/100),"") -> #ERROR! | H22: =IFERROR(G22*1.055,"") -> #ERROR!
A23: TOTAL DEVIS | G23: =SUM(G13:G22) -> #ERROR! | H23: =SUM(H13:H22) -> #ERROR!

Sheet Planning
A1: MAISON 41 — PLANNING PRODUCTION — Lots · Autoclaves · Capacites automatiques
A2: Choisir Autoclave + Format + Fraction → Nb bocaux calcule auto · Recettes = actives uniquement
A3: Date | B3: N Lot (auto) | C3: Recette | D3: Gamme | E3: Format Weck | F3: Autoclave | G3: Fraction | H3: Cap. max | I3: Nb bocaux plan. | J3: Nb bocaux reels | K3: Taux rempl. | L3: N Cycle auto | M3: Poids MP brut (kg) | N3: Cout theo. EUR | O3: T coeur (C) | P3: Statut | Q3: DDM (auto) | R3: Operateur | S3: Notes | T3: Picking OK ?
A4: 46113.083 | B4: =IF(A4="","",IF(C4="","","LOT-"&TEXT(A4,"YYYYMMDD")&"-"&TEXT(ROW()-3,"000"))) -> #ERROR! | C4: Rillettes du Chef | D4: =IFERROR(INDEX(Recettes!C:C,MATCH(C4,Recettes!B:B,0)),"") -> #ERROR! | E4: RR100-1050 | F4: A | G4: Complet | I4: 0 | K4: =IFERROR(J4/I4,"") -> #ERROR! | O4: 115 | Q4: =IFERROR(IF(A4="","",A4+IFERROR(INDEX(Config!B:B,MATCH("DDM appertisation standard (mois)",Config!A:A,0)),36)*30),"") -> #ERROR!
A5: 46113.083 | B5: =IF(A5="","",IF(C5="","","LOT-"&TEXT(A5,"YYYYMMDD")&"-"&TEXT(ROW()-3,"000"))) -> #ERROR! | C5: Rillettes aux Ricard | D5: =IFERROR(INDEX(Recettes!C:C,MATCH(C5,Recettes!B:B,0)),"") -> #ERROR! | E5: W60-050 | F5: A | G5: Complet | I5: 192 | K5: =IFERROR(J5/I5,"") -> #ERROR! | O5: 115 | Q5: =IFERROR(IF(A5="","",A5+IFERROR(INDEX(Config!B:B,MATCH("DDM appertisation standard (mois)",Config!A:A,0)),36)*30),"") -> #ERROR!
A6: 46114.083 | B6: =IF(A6="","",IF(C6="","","LOT-"&TEXT(A6,"YYYYMMDD")&"-"&TEXT(ROW()-3,"000"))) -> #ERROR! | C6: Rillettes du Chef | D6: =IFERROR(INDEX(Recettes!C:C,MATCH(C6,Recettes!B:B,0)),"") -> #ERROR! | E6: RR100-290 | F6: A | G6: Complet | H6: =IFERROR(IF(F6="","",IF(F6="100x4/4 (100 boc. ref.)",SWITCH(E6,"W60-050",320,"W60-080",280,"W60-160",220,"RR100-290",130,"RR100-370",120,"RR100-580",130,"RR100-850",64,"RR100-1050",55,"RR100-1550",40,100),IF(F6="200x4/4 (200 boc. ref.)",SWITCH(E6,"W60-050",640,"W60-080",560,"W60-160",440,"RR100-290",260,"RR100-370",240,"RR100-580",260,"RR100-850",128,"RR100-1050",110,"RR100-1550",80,200),IF(F6="100L eau (~20 boc.)",SWITCH(E6,"W60-050",60,"W60-080",50,"W60-160",40,"RR100-290",28,"RR100-370",24,"RR100-580",20,"RR100-850",12,"RR100-1050",10,"RR100-1550",6,15),"")))),"") -> #ERROR! | I6: 96 | K6: =IFERROR(J6/I6,"") -> #ERROR! | O6: 115 | Q6: =IFERROR(IF(A6="","",A6+IFERROR(INDEX(Config!B:B,MATCH("DDM appertisation standard (mois)",Config!A:A,0)),36)*30),"") -> #ERROR!
B7: =IF(A7="","",IF(C7="","","LOT-"&TEXT(A7,"YYYYMMDD")&"-"&TEXT(ROW()-3,"000"))) -> #ERROR! | D7: =IFERROR(INDEX(Recettes!C:C,MATCH(C7,Recettes!B:B,0)),"") -> #ERROR! | H7: =IFERROR(IF(F7="","",IF(F7="100x4/4 (100 boc. ref.)",SWITCH(E7,"W60-050",320,"W60-080",280,"W60-160",220,"RR100-290",130,"RR100-370",120,"RR100-580",130,"RR100-850",64,"RR100-1050",55,"RR100-1550",40,100),IF(F7="200x4/4 (200 boc. ref.)",SWITCH(E7,"W60-050",640,"W60-080",560,"W60-160",440,"RR100-290",260,"RR100-370",240,"RR100-580",260,"RR100-850",128,"RR100-1050",110,"RR100-1550",80,200),IF(F7="100L eau (~20 boc.)",SWITCH(E7,"W60-050",60,"W60-080",50,"W60-160",40,"RR100-290",28,"RR100-370",24,"RR100-580",20,"RR100-850",12,"RR100-1050",10,"RR100-1550",6,15),"")))),"") -> #ERROR! | I7: 48 | K7: =IFERROR(J7/I7,"") -> #ERROR! | O7: 116 | Q7: =IFERROR(IF(A7="","",A7+IFERROR(INDEX(Config!B:B,MATCH("DDM appertisation standard (mois)",Config!A:A,0)),36)*30),"") -> #ERROR!
B8: =IF(A8="","",IF(C8="","","LOT-"&TEXT(A8,"YYYYMMDD")&"-"&TEXT(ROW()-3,"000"))) -> #ERROR! | D8: =IFERROR(INDEX(Recettes!C:C,MATCH(C8,Recettes!B:B,0)),"") -> #ERROR! | H8: =IFERROR(IF(F8="","",IF(F8="100x4/4 (100 boc. ref.)",SWITCH(E8,"W60-050",320,"W60-080",280,"W60-160",220,"RR100-290",130,"RR100-370",120,"RR100-580",130,"RR100-850",64,"RR100-1050",55,"RR100-1550",40,100),IF(F8="200x4/4 (200 boc. ref.)",SWITCH(E8,"W60-050",640,"W60-080",560,"W60-160",440,"RR100-290",260,"RR100-370",240,"RR100-580",260,"RR100-850",128,"RR100-1050",110,"RR100-1550",80,200),IF(F8="100L eau (~20 boc.)",SWITCH(E8,"W60-050",60,"W60-080",50,"W60-160",40,"RR100-290",28,"RR100-370",24,"RR100-580",20,"RR100-850",12,"RR100-1050",10,"RR100-1550",6,15),"")))),"") -> #ERROR! | I8: =IFERROR(IF(OR(H8="",G8=""),"",ROUND(H8*SWITCH(G8,"1/4",0.25,"1/2",0.5,"3/4",0.75,"Complet",1,1),0)),"") -> #ERROR! | K8: =IFERROR(J8/I8,"") -> #ERROR! | Q8: =IFERROR(IF(A8="","",A8+IFERROR(INDEX(Config!B:B,MATCH("DDM appertisation standard (mois)",Config!A:A,0)),36)*30),"") -> #ERROR!
B9: =IF(A9="","",IF(C9="","","LOT-"&TEXT(A9,"YYYYMMDD")&"-"&TEXT(ROW()-3,"000"))) -> #ERROR! | D9: =IFERROR(INDEX(Recettes!C:C,MATCH(C9,Recettes!B:B,0)),"") -> #ERROR! | H9: =IFERROR(IF(F9="","",IF(F9="100x4/4 (100 boc. ref.)",SWITCH(E9,"W60-050",320,"W60-080",280,"W60-160",220,"RR100-290",130,"RR100-370",120,"RR100-580",130,"RR100-850",64,"RR100-1050",55,"RR100-1550",40,100),IF(F9="200x4/4 (200 boc. ref.)",SWITCH(E9,"W60-050",640,"W60-080",560,"W60-160",440,"RR100-290",260,"RR100-370",240,"RR100-580",260,"RR100-850",128,"RR100-1050",110,"RR100-1550",80,200),IF(F9="100L eau (~20 boc.)",SWITCH(E9,"W60-050",60,"W60-080",50,"W60-160",40,"RR100-290",28,"RR100-370",24,"RR100-580",20,"RR100-850",12,"RR100-1050",10,"RR100-1550",6,15),"")))),"") -> #ERROR! | I9: =IFERROR(IF(OR(H9="",G9=""),"",ROUND(H9*SWITCH(G9,"1/4",0.25,"1/2",0.5,"3/4",0.75,"Complet",1,1),0)),"") -> #ERROR! | K9: =IFERROR(J9/I9,"") -> #ERROR! | Q9: =IFERROR(IF(A9="","",A9+IFERROR(INDEX(Config!B:B,MATCH("DDM appertisation standard (mois)",Config!A:A,0)),36)*30),"") -> #ERROR!
B10: =IF(A10="","",IF(C10="","","LOT-"&TEXT(A10,"YYYYMMDD")&"-"&TEXT(ROW()-3,"000"))) -> #ERROR! | D10: =IFERROR(INDEX(Recettes!C:C,MATCH(C10,Recettes!B:B,0)),"") -> #ERROR! | H10: =IFERROR(IF(F10="","",IF(F10="100x4/4 (100 boc. ref.)",SWITCH(E10,"W60-050",320,"W60-080",280,"W60-160",220,"RR100-290",130,"RR100-370",120,"RR100-580",130,"RR100-850",64,"RR100-1050",55,"RR100-1550",40,100),IF(F10="200x4/4 (200 boc. ref.)",SWITCH(E10,"W60-050",640,"W60-080",560,"W60-160",440,"RR100-290",260,"RR100-370",240,"RR100-580",260,"RR100-850",128,"RR100-1050",110,"RR100-1550",80,200),IF(F10="100L eau (~20 boc.)",SWITCH(E10,"W60-050",60,"W60-080",50,"W60-160",40,"RR100-290",28,"RR100-370",24,"RR100-580",20,"RR100-850",12,"RR100-1050",10,"RR100-1550",6,15),"")))),"") -> #ERROR! | I10: =IFERROR(IF(OR(H10="",G10=""),"",ROUND(H10*SWITCH(G10,"1/4",0.25,"1/2",0.5,"3/4",0.75,"Complet",1,1),0)),"") -> #ERROR! | K10: =IFERROR(J10/I10,"") -> #ERROR! | Q10: =IFERROR(IF(A10="","",A10+IFERROR(INDEX(Config!B:B,MATCH("DDM appertisation standard (mois)",Config!A:A,0)),36)*30),"") -> #ERROR!
B11: =IF(A11="","",IF(C11="","","LOT-"&TEXT(A11,"YYYYMMDD")&"-"&TEXT(ROW()-3,"000"))) -> #ERROR! | D11: =IFERROR(INDEX(Recettes!C:C,MATCH(C11,Recettes!B:B,0)),"") -> #ERROR! | H11: =IFERROR(IF(F11="","",IF(F11="100x4/4 (100 boc. ref.)",SWITCH(E11,"W60-050",320,"W60-080",280,"W60-160",220,"RR100-290",130,"RR100-370",120,"RR100-580",130,"RR100-850",64,"RR100-1050",55,"RR100-1550",40,100),IF(F11="200x4/4 (200 boc. ref.)",SWITCH(E11,"W60-050",640,"W60-080",560,"W60-160",440,"RR100-290",260,"RR100-370",240,"RR100-580",260,"RR100-850",128,"RR100-1050",110,"RR100-1550",80,200),IF(F11="100L eau (~20 boc.)",SWITCH(E11,"W60-050",60,"W60-080",50,"W60-160",40,"RR100-290",28,"RR100-370",24,"RR100-580",20,"RR100-850",12,"RR100-1050",10,"RR100-1550",6,15),"")))),"") -> #ERROR! | I11: =IFERROR(IF(OR(H11="",G11=""),"",ROUND(H11*SWITCH(G11,"1/4",0.25,"1/2",0.5,"3/4",0.75,"Complet",1,1),0)),"") -> #ERROR! | K11: =IFERROR(J11/I11,"") -> #ERROR! | Q11: =IFERROR(IF(A11="","",A11+IFERROR(INDEX(Config!B:B,MATCH("DDM appertisation standard (mois)",Config!A:A,0)),36)*30),"") -> #ERROR!
B12: =IF(A12="","",IF(C12="","","LOT-"&TEXT(A12,"YYYYMMDD")&"-"&TEXT(ROW()-3,"000"))) -> #ERROR! | D12: =IFERROR(INDEX(Recettes!C:C,MATCH(C12,Recettes!B:B,0)),"") -> #ERROR! | H12: =IFERROR(IF(F12="","",IF(F12="100x4/4 (100 boc. ref.)",SWITCH(E12,"W60-050",320,"W60-080",280,"W60-160",220,"RR100-290",130,"RR100-370",120,"RR100-580",130,"RR100-850",64,"RR100-1050",55,"RR100-1550",40,100),IF(F12="200x4/4 (200 boc. ref.)",SWITCH(E12,"W60-050",640,"W60-080",560,"W60-160",440,"RR100-290",260,"RR100-370",240,"RR100-580",260,"RR100-850",128,"RR100-1050",110,"RR100-1550",80,200),IF(F12="100L eau (~20 boc.)",SWITCH(E12,"W60-050",60,"W60-080",50,"W60-160",40,"RR100-290",28,"RR100-370",24,"RR100-580",20,"RR100-850",12,"RR100-1050",10,"RR100-1550",6,15),"")))),"") -> #ERROR! | I12: =IFERROR(IF(OR(H12="",G12=""),"",ROUND(H12*SWITCH(G12,"1/4",0.25,"1/2",0.5,"3/4",0.75,"Complet",1,1),0)),"") -> #ERROR! | K12: =IFERROR(J12/I12,"") -> #ERROR! | Q12: =IFERROR(IF(A12="","",A12+IFERROR(INDEX(Config!B:B,MATCH("DDM appertisation standard (mois)",Config!A:A,0)),36)*30),"") -> #ERROR!
B13: =IF(A13="","",IF(C13="","","LOT-"&TEXT(A13,"YYYYMMDD")&"-"&TEXT(ROW()-3,"000"))) -> #ERROR! | D13: =IFERROR(INDEX(Recettes!C:C,MATCH(C13,Recettes!B:B,0)),"") -> #ERROR! | H13: =IFERROR(IF(F13="","",IF(F13="100x4/4 (100 boc. ref.)",SWITCH(E13,"W60-050",320,"W60-080",280,"W60-160",220,"RR100-290",130,"RR100-370",120,"RR100-580",130,"RR100-850",64,"RR100-1050",55,"RR100-1550",40,100),IF(F13="200x4/4 (200 boc. ref.)",SWITCH(E13,"W60-050",640,"W60-080",560,"W60-160",440,"RR100-290",260,"RR100-370",240,"RR100-580",260,"RR100-850",128,"RR100-1050",110,"RR100-1550",80,200),IF(F13="100L eau (~20 boc.)",SWITCH(E13,"W60-050",60,"W60-080",50,"W60-160",40,"RR100-290",28,"RR100-370",24,"RR100-580",20,"RR100-850",12,"RR100-1050",10,"RR100-1550",6,15),"")))),"") -> #ERROR! | I13: =IFERROR(IF(OR(H13="",G13=""),"",ROUND(H13*SWITCH(G13,"1/4",0.25,"1/2",0.5,"3/4",0.75,"Complet",1,1),0)),"") -> #ERROR! | K13: =IFERROR(J13/I13,"") -> #ERROR! | Q13: =IFERROR(IF(A13="","",A13+IFERROR(INDEX(Config!B:B,MATCH("DDM appertisation standard (mois)",Config!A:A,0)),36)*30),"") -> #ERROR!
B14: =IF(A14="","",IF(C14="","","LOT-"&TEXT(A14,"YYYYMMDD")&"-"&TEXT(ROW()-3,"000"))) -> #ERROR! | D14: =IFERROR(INDEX(Recettes!C:C,MATCH(C14,Recettes!B:B,0)),"") -> #ERROR! | H14: =IFERROR(IF(F14="","",IF(F14="100x4/4 (100 boc. ref.)",SWITCH(E14,"W60-050",320,"W60-080",280,"W60-160",220,"RR100-290",130,"RR100-370",120,"RR100-580",130,"RR100-850",64,"RR100-1050",55,"RR100-1550",40,100),IF(F14="200x4/4 (200 boc. ref.)",SWITCH(E14,"W60-050",640,"W60-080",560,"W60-160",440,"RR100-290",260,"RR100-370",240,"RR100-580",260,"RR100-850",128,"RR100-1050",110,"RR100-1550",80,200),IF(F14="100L eau (~20 boc.)",SWITCH(E14,"W60-050",60,"W60-080",50,"W60-160",40,"RR100-290",28,"RR100-370",24,"RR100-580",20,"RR100-850",12,"RR100-1050",10,"RR100-1550",6,15),"")))),"") -> #ERROR! | I14: =IFERROR(IF(OR(H14="",G14=""),"",ROUND(H14*SWITCH(G14,"1/4",0.25,"1/2",0.5,"3/4",0.75,"Complet",1,1),0)),"") -> #ERROR! | K14: =IFERROR(J14/I14,"") -> #ERROR! | Q14: =IFERROR(IF(A14="","",A14+IFERROR(INDEX(Config!B:B,MATCH("DDM appertisation standard (mois)",Config!A:A,0)),36)*30),"") -> #ERROR!
B15: =IF(A15="","",IF(C15="","","LOT-"&TEXT(A15,"YYYYMMDD")&"-"&TEXT(ROW()-3,"000"))) -> #ERROR! | D15: =IFERROR(INDEX(Recettes!C:C,MATCH(C15,Recettes!B:B,0)),"") -> #ERROR! | H15: =IFERROR(IF(F15="","",IF(F15="100x4/4 (100 boc. ref.)",SWITCH(E15,"W60-050",320,"W60-080",280,"W60-160",220,"RR100-290",130,"RR100-370",120,"RR100-580",130,"RR100-850",64,"RR100-1050",55,"RR100-1550",40,100),IF(F15="200x4/4 (200 boc. ref.)",SWITCH(E15,"W60-050",640,"W60-080",560,"W60-160",440,"RR100-290",260,"RR100-370",240,"RR100-580",260,"RR100-850",128,"RR100-1050",110,"RR100-1550",80,200),IF(F15="100L eau (~20 boc.)",SWITCH(E15,"W60-050",60,"W60-080",50,"W60-160",40,"RR100-290",28,"RR100-370",24,"RR100-580",20,"RR100-850",12,"RR100-1050",10,"RR100-1550",6,15),"")))),"") -> #ERROR! | I15: =IFERROR(IF(OR(H15="",G15=""),"",ROUND(H15*SWITCH(G15,"1/4",0.25,"1/2",0.5,"3/4",0.75,"Complet",1,1),0)),"") -> #ERROR! | K15: =IFERROR(J15/I15,"") -> #ERROR! | Q15: =IFERROR(IF(A15="","",A15+IFERROR(INDEX(Config!B:B,MATCH("DDM appertisation standard (mois)",Config!A:A,0)),36)*30),"") -> #ERROR!
B16: =IF(A16="","",IF(C16="","","LOT-"&TEXT(A16,"YYYYMMDD")&"-"&TEXT(ROW()-3,"000"))) -> #ERROR! | D16: =IFERROR(INDEX(Recettes!C:C,MATCH(C16,Recettes!B:B,0)),"") -> #ERROR! | H16: =IFERROR(IF(F16="","",IF(F16="100x4/4 (100 boc. ref.)",SWITCH(E16,"W60-050",320,"W60-080",280,"W60-160",220,"RR100-290",130,"RR100-370",120,"RR100-580",130,"RR100-850",64,"RR100-1050",55,"RR100-1550",40,100),IF(F16="200x4/4 (200 boc. ref.)",SWITCH(E16,"W60-050",640,"W60-080",560,"W60-160",440,"RR100-290",260,"RR100-370",240,"RR100-580",260,"RR100-850",128,"RR100-1050",110,"RR100-1550",80,200),IF(F16="100L eau (~20 boc.)",SWITCH(E16,"W60-050",60,"W60-080",50,"W60-160",40,"RR100-290",28,"RR100-370",24,"RR100-580",20,"RR100-850",12,"RR100-1050",10,"RR100-1550",6,15),"")))),"") -> #ERROR! | I16: =IFERROR(IF(OR(H16="",G16=""),"",ROUND(H16*SWITCH(G16,"1/4",0.25,"1/2",0.5,"3/4",0.75,"Complet",1,1),0)),"") -> #ERROR! | K16: =IFERROR(J16/I16,"") -> #ERROR! | Q16: =IFERROR(IF(A16="","",A16+IFERROR(INDEX(Config!B:B,MATCH("DDM appertisation standard (mois)",Config!A:A,0)),36)*30),"") -> #ERROR!
B17: =IF(A17="","",IF(C17="","","LOT-"&TEXT(A17,"YYYYMMDD")&"-"&TEXT(ROW()-3,"000"))) -> #ERROR! | D17: =IFERROR(INDEX(Recettes!C:C,MATCH(C17,Recettes!B:B,0)),"") -> #ERROR! | H17: =IFERROR(IF(F17="","",IF(F17="100x4/4 (100 boc. ref.)",SWITCH(E17,"W60-050",320,"W60-080",280,"W60-160",220,"RR100-290",130,"RR100-370",120,"RR100-580",130,"RR100-850",64,"RR100-1050",55,"RR100-1550",40,100),IF(F17="200x4/4 (200 boc. ref.)",SWITCH(E17,"W60-050",640,"W60-080",560,"W60-160",440,"RR100-290",260,"RR100-370",240,"RR100-580",260,"RR100-850",128,"RR100-1050",110,"RR100-1550",80,200),IF(F17="100L eau (~20 boc.)",SWITCH(E17,"W60-050",60,"W60-080",50,"W60-160",40,"RR100-290",28,"RR100-370",24,"RR100-580",20,"RR100-850",12,"RR100-1050",10,"RR100-1550",6,15),"")))),"") -> #ERROR! | I17: =IFERROR(IF(OR(H17="",G17=""),"",ROUND(H17*SWITCH(G17,"1/4",0.25,"1/2",0.5,"3/4",0.75,"Complet",1,1),0)),"") -> #ERROR! | K17: =IFERROR(J17/I17,"") -> #ERROR! | Q17: =IFERROR(IF(A17="","",A17+IFERROR(INDEX(Config!B:B,MATCH("DDM appertisation standard (mois)",Config!A:A,0)),36)*30),"") -> #ERROR!
B18: =IF(A18="","",IF(C18="","","LOT-"&TEXT(A18,"YYYYMMDD")&"-"&TEXT(ROW()-3,"000"))) -> #ERROR! | D18: =IFERROR(INDEX(Recettes!C:C,MATCH(C18,Recettes!B:B,0)),"") -> #ERROR! | H18: =IFERROR(IF(F18="","",IF(F18="100x4/4 (100 boc. ref.)",SWITCH(E18,"W60-050",320,"W60-080",280,"W60-160",220,"RR100-290",130,"RR100-370",120,"RR100-580",130,"RR100-850",64,"RR100-1050",55,"RR100-1550",40,100),IF(F18="200x4/4 (200 boc. ref.)",SWITCH(E18,"W60-050",640,"W60-080",560,"W60-160",440,"RR100-290",260,"RR100-370",240,"RR100-580",260,"RR100-850",128,"RR100-1050",110,"RR100-1550",80,200),IF(F18="100L eau (~20 boc.)",SWITCH(E18,"W60-050",60,"W60-080",50,"W60-160",40,"RR100-290",28,"RR100-370",24,"RR100-580",20,"RR100-850",12,"RR100-1050",10,"RR100-1550",6,15),"")))),"") -> #ERROR! | I18: =IFERROR(IF(OR(H18="",G18=""),"",ROUND(H18*SWITCH(G18,"1/4",0.25,"1/2",0.5,"3/4",0.75,"Complet",1,1),0)),"") -> #ERROR! | K18: =IFERROR(J18/I18,"") -> #ERROR! | Q18: =IFERROR(IF(A18="","",A18+IFERROR(INDEX(Config!B:B,MATCH("DDM appertisation standard (mois)",Config!A:A,0)),36)*30),"") -> #ERROR!
B19: =IF(A19="","",IF(C19="","","LOT-"&TEXT(A19,"YYYYMMDD")&"-"&TEXT(ROW()-3,"000"))) -> #ERROR! | D19: =IFERROR(INDEX(Recettes!C:C,MATCH(C19,Recettes!B:B,0)),"") -> #ERROR! | H19: =IFERROR(IF(F19="","",IF(F19="100x4/4 (100 boc. ref.)",SWITCH(E19,"W60-050",320,"W60-080",280,"W60-160",220,"RR100-290",130,"RR100-370",120,"RR100-580",130,"RR100-850",64,"RR100-1050",55,"RR100-1550",40,100),IF(F19="200x4/4 (200 boc. ref.)",SWITCH(E19,"W60-050",640,"W60-080",560,"W60-160",440,"RR100-290",260,"RR100-370",240,"RR100-580",260,"RR100-850",128,"RR100-1050",110,"RR100-1550",80,200),IF(F19="100L eau (~20 boc.)",SWITCH(E19,"W60-050",60,"W60-080",50,"W60-160",40,"RR100-290",28,"RR100-370",24,"RR100-580",20,"RR100-850",12,"RR100-1050",10,"RR100-1550",6,15),"")))),"") -> #ERROR! | I19: =IFERROR(IF(OR(H19="",G19=""),"",ROUND(H19*SWITCH(G19,"1/4",0.25,"1/2",0.5,"3/4",0.75,"Complet",1,1),0)),"") -> #ERROR! | K19: =IFERROR(J19/I19,"") -> #ERROR! | Q19: =IFERROR(IF(A19="","",A19+IFERROR(INDEX(Config!B:B,MATCH("DDM appertisation standard (mois)",Config!A:A,0)),36)*30),"") -> #ERROR!
... B303: =IF(A303="","",IF(C303="","","LOT-"&TEXT(A303,"YYYYMMDD")&"-"&TEXT(ROW()-3,"000"))) -> #ERROR! | D303: =IFERROR(INDEX(Recettes!C:C,MATCH(C303,Recettes!B:B,0)),"") -> #ERROR! | H303: =IFERROR(IF(F303="","",IF(F303="100x4/4 (100 boc. ref.)",SWITCH(E303,"W60-050",320,"W60-080",280,"W60-160",220,"RR100-290",130,"RR100-370",120,"RR100-580",130,"RR100-850",64,"RR100-1050",55,"RR100-1550",40,100),IF(F303="200x4/4 (200 boc. ref.)",SWITCH(E303,"W60-050",640,"W60-080",560,"W60-160",440,"RR100-290",260,"RR100-370",240,"RR100-580",260,"RR100-850",128,"RR100-1050",110,"RR100-1550",80,200),IF(F303="100L eau (~20 boc.)",SWITCH(E303,"W60-050",60,"W60-080",50,"W60-160",40,"RR100-290",28,"RR100-370",24,"RR100-580",20,"RR100-850",12,"RR100-1050",10,"RR100-1550",6,15),"")))),"") -> #ERROR! | I303: =IFERROR(IF(OR(H303="",G303=""),"",ROUND(H303*SWITCH(G303,"1/4",0.25,"1/2",0.5,"3/4",0.75,"Complet",1,1),0)),"") -> #ERROR! | K303: =IFERROR(J303/I303,"") -> #ERROR! | Q303: =IFERROR(IF(A303="","",A303+IFERROR(INDEX(Config!B:B,MATCH("DDM appertisation standard (mois)",Config!A:A,0)),36)*30),"") -> #ERROR!
A304: 46108 | C304: Pate Chataigne Ardeche | E304: rr100 | F304: Korimat 1 | P304: Prévu

Sheet Stock
A1: MAISON 41 — GESTION DES STOCKS — MP + Bocaux · Sync app
A2: Total bocaux en stock : | B2: =IFERROR(SUM(Stock!D208:D261),0) -> #ERROR! | D2: MP en rupture (<seuil) : | E2: =IFERROR(COUNTIF(G6:G205,"Rupture"),0) -> #ERROR!
A4: STOCK MATIERES PREMIERES
A5: Code | B5: Designation | C5: Categorie | D5: Unite | E5: Stock actuel | F5: Seuil alerte | G5: Statut | H5: Valeur EUR | I5: Conso theo. | J5: Stock theo.
A6: MP01 | B6: Porc epaule desossee | C6: Viande porc | D6: kg | E6: 0 | F6: 1 | G6: =IF(E6="","",IF(E6<F6,"Rupture","OK")) -> #ERROR! | H6: =IFERROR(E6*INDEX('MP Referentiel'!F:F,MATCH(A6,'MP Referentiel'!A:A,0)),"") -> #ERROR!
A7: MP02 | B7: Porc gorge (gras dur) | C7: Viande porc | D7: kg | E7: 0 | F7: 1 | G7: =IF(E7="","",IF(E7<F7,"Rupture","OK")) -> #ERROR! | H7: =IFERROR(E7*INDEX('MP Referentiel'!F:F,MATCH(A7,'MP Referentiel'!A:A,0)),"") -> #ERROR!
A8: MP03 | B8: Porc foie | C8: Viande porc | D8: kg | E8: 0 | F8: 1 | G8: =IF(E8="","",IF(E8<F8,"Rupture","OK")) -> #ERROR! | H8: =IFERROR(E8*INDEX('MP Referentiel'!F:F,MATCH(A8,'MP Referentiel'!A:A,0)),"") -> #ERROR!
A9: MP04 | B9: Porc couenne | C9: Viande porc | D9: kg | E9: 0 | F9: 1 | G9: =IF(E9="","",IF(E9<F9,"Rupture","OK")) -> #ERROR! | H9: =IFERROR(E9*INDEX('MP Referentiel'!F:F,MATCH(A9,'MP Referentiel'!A:A,0)),"") -> #ERROR!
A10: MP05 | B10: Lardons nature sans nitrite | C10: Viande porc | D10: kg | E10: 0 | F10: 1 | G10: =IF(E10="","",IF(E10<F10,"Rupture","OK")) -> #ERROR! | H10: =IFERROR(E10*INDEX('MP Referentiel'!F:F,MATCH(A10,'MP Referentiel'!A:A,0)),"") -> #ERROR!
A11: MP06 | B11: Saucisses Toulouse artisanales | C11: Charcuterie | D11: kg | E11: 0 | F11: 1 | G11: =IF(E11="","",IF(E11<F11,"Rupture","OK")) -> #ERROR! | H11: =IFERROR(E11*INDEX('MP Referentiel'!F:F,MATCH(A11,'MP Referentiel'!A:A,0)),"") -> #ERROR!
A12: MP07 | B12: Boeuf paleron | C12: Viande boeuf | D12: kg | E12: 0 | F12: 1 | G12: =IF(E12="","",IF(E12<F12,"Rupture","OK")) -> #ERROR! | H12: =IFERROR(E12*INDEX('MP Referentiel'!F:F,MATCH(A12,'MP Referentiel'!A:A,0)),"") -> #ERROR!
A13: MP08 | B13: Os a moelle boeuf | C13: Viande boeuf | D13: kg | E13: 0 | F13: 1 | G13: =IF(E13="","",IF(E13<F13,"Rupture","OK")) -> #ERROR! | H13: =IFERROR(E13*INDEX('MP Referentiel'!F:F,MATCH(A13,'MP Referentiel'!A:A,0)),"") -> #ERROR!
A14: MP09 | B14: Ail frais | C14: Legumes | D14: kg | E14: 0 | F14: 1 | G14: =IF(E14="","",IF(E14<F14,"Rupture","OK")) -> #ERROR! | H14: =IFERROR(E14*INDEX('MP Referentiel'!F:F,MATCH(A14,'MP Referentiel'!A:A,0)),"") -> #ERROR!
A15: MP10 | B15: Carotte | C15: Legumes | D15: kg | E15: 0 | F15: 1 | G15: =IF(E15="","",IF(E15<F15,"Rupture","OK")) -> #ERROR! | H15: =IFERROR(E15*INDEX('MP Referentiel'!F:F,MATCH(A15,'MP Referentiel'!A:A,0)),"") -> #ERROR!
A16: MP11 | B16: Celeri branche | C16: Legumes | D16: kg | E16: 0 | F16: 1 | G16: =IF(E16="","",IF(E16<F16,"Rupture","OK")) -> #ERROR! | H16: =IFERROR(E16*INDEX('MP Referentiel'!F:F,MATCH(A16,'MP Referentiel'!A:A,0)),"") -> #ERROR!
A17: MP12 | B17: Celeri-rave | C17: Legumes | D17: kg | E17: 0 | F17: 1 | G17: =IF(E17="","",IF(E17<F17,"Rupture","OK")) -> #ERROR! | H17: =IFERROR(E17*INDEX('MP Referentiel'!F:F,MATCH(A17,'MP Referentiel'!A:A,0)),"") -> #ERROR!
... A78: MP73 | B78: Bocal Weck W60-160 + joint | C78: Consommable | D78: u | E78: 0 | F78: 1 | G78: =IF(E78="","",IF(E78<F78,"Rupture","OK")) -> #ERROR! | H78: =IFERROR(E78*INDEX('MP Referentiel'!F:F,MATCH(A78,'MP Referentiel'!A:A,0)),"") -> #ERROR!
G79: =IF(E79="","",IF(E79<F79,"Rupture","OK")) -> #ERROR! | H79: =IFERROR(E79*INDEX('MP Referentiel'!F:F,MATCH(A79,'MP Referentiel'!A:A,0)),"") -> #ERROR!
G80: =IF(E80="","",IF(E80<F80,"Rupture","OK")) -> #ERROR! | H80: =IFERROR(E80*INDEX('MP Referentiel'!F:F,MATCH(A80,'MP Referentiel'!A:A,0)),"") -> #ERROR!
G81: =IF(E81="","",IF(E81<F81,"Rupture","OK")) -> #ERROR! | H81: =IFERROR(E81*INDEX('MP Referentiel'!F:F,MATCH(A81,'MP Referentiel'!A:A,0)),"") -> #ERROR!
G82: =IF(E82="","",IF(E82<F82,"Rupture","OK")) -> #ERROR! | H82: =IFERROR(E82*INDEX('MP Referentiel'!F:F,MATCH(A82,'MP Referentiel'!A:A,0)),"") -> #ERROR!
G83: =IF(E83="","",IF(E83<F83,"Rupture","OK")) -> #ERROR! | H83: =IFERROR(E83*INDEX('MP Referentiel'!F:F,MATCH(A83,'MP Referentiel'!A:A,0)),"") -> #ERROR!
G84: =IF(E84="","",IF(E84<F84,"Rupture","OK")) -> #ERROR! | H84: =IFERROR(E84*INDEX('MP Referentiel'!F:F,MATCH(A84,'MP Referentiel'!A:A,0)),"") -> #ERROR!
G85: =IF(E85="","",IF(E85<F85,"Rupture","OK")) -> #ERROR! | H85: =IFERROR(E85*INDEX('MP Referentiel'!F:F,MATCH(A85,'MP Referentiel'!A:A,0)),"") -> #ERROR!
G86: =IF(E86="","",IF(E86<F86,"Rupture","OK")) -> #ERROR! | H86: =IFERROR(E86*INDEX('MP Referentiel'!F:F,MATCH(A86,'MP Referentiel'!A:A,0)),"") -> #ERROR!
G87: =IF(E87="","",IF(E87<F87,"Rupture","OK")) -> #ERROR! | H87: =IFERROR(E87*INDEX('MP Referentiel'!F:F,MATCH(A87,'MP Referentiel'!A:A,0)),"") -> #ERROR!
G88: =IF(E88="","",IF(E88<F88,"Rupture","OK")) -> #ERROR! | H88: =IFERROR(E88*INDEX('MP Referentiel'!F:F,MATCH(A88,'MP Referentiel'!A:A,0)),"") -> #ERROR!
G89: =IF(E89="","",IF(E89<F89,"Rupture","OK")) -> #ERROR! | H89: =IFERROR(E89*INDEX('MP Referentiel'!F:F,MATCH(A89,'MP Referentiel'!A:A,0)),"") -> #ERROR!
G90: =IF(E90="","",IF(E90<F90,"Rupture","OK")) -> #ERROR! | H90: =IFERROR(E90*INDEX('MP Referentiel'!F:F,MATCH(A90,'MP Referentiel'!A:A,0)),"") -> #ERROR!
... G205: =IF(E205="","",IF(E205<F205,"Rupture","OK")) -> #ERROR! | H205: =IFERROR(E205*INDEX('MP Referentiel'!F:F,MATCH(A205,'MP Referentiel'!A:A,0)),"") -> #ERROR!
A206: STOCK BOCAUX (par gamme x format)
A207: Gamme | B207: Format | C207: Poids g | D207: Bocaux en stock | E207: Valeur pot. EUR | F207: Entree recente | G207: Sortie recente | H207: DDM proche
A208: Pates & Terrines | B208: RR100-290 | C208: 250 | D208: 0 | E208: =IFERROR(D208*INDEX('Prix Vente'!C:C,MATCH(A208&B208,'Prix Vente'!A:A&'Prix Vente'!B:B,0)),"") -> #ERROR!
A209: Pates & Terrines | B209: RR100-370 | C209: 320 | D209: 0 | E209: =IFERROR(D209*INDEX('Prix Vente'!C:C,MATCH(A209&B209,'Prix Vente'!A:A&'Prix Vente'!B:B,0)),"") -> #ERROR!
A210: Pates & Terrines | B210: RR100-580 | C210: 500 | D210: 0 | E210: =IFERROR(D210*INDEX('Prix Vente'!C:C,MATCH(A210&B210,'Prix Vente'!A:A&'Prix Vente'!B:B,0)),"") -> #ERROR!
A211: Pates & Terrines | B211: RR100-850 | C211: 730 | D211: 0 | E211: =IFERROR(D211*INDEX('Prix Vente'!C:C,MATCH(A211&B211,'Prix Vente'!A:A&'Prix Vente'!B:B,0)),"") -> #ERROR!
A212: Pates & Terrines | B212: RR100-1050 | C212: 900 | D212: 0 | E212: =IFERROR(D212*INDEX('Prix Vente'!C:C,MATCH(A212&B212,'Prix Vente'!A:A&'Prix Vente'!B:B,0)),"") -> #ERROR!
A213: Pates & Terrines | B213: RR100-1550 | C213: 1350 | D213: 0 | E213: =IFERROR(D213*INDEX('Prix Vente'!C:C,MATCH(A213&B213,'Prix Vente'!A:A&'Prix Vente'!B:B,0)),"") -> #ERROR!
A214: Pates & Terrines | B214: W60-050 | C214: 40 | D214: 0 | E214: =IFERROR(D214*INDEX('Prix Vente'!C:C,MATCH(A214&B214,'Prix Vente'!A:A&'Prix Vente'!B:B,0)),"") -> #ERROR!
A215: Pates & Terrines | B215: W60-080 | C215: 65 | D215: 0 | E215: =IFERROR(D215*INDEX('Prix Vente'!C:C,MATCH(A215&B215,'Prix Vente'!A:A&'Prix Vente'!B:B,0)),"") -> #ERROR!
A216: Pates & Terrines | B216: W60-160 | C216: 130 | D216: 0 | E216: =IFERROR(D216*INDEX('Prix Vente'!C:C,MATCH(A216&B216,'Prix Vente'!A:A&'Prix Vente'!B:B,0)),"") -> #ERROR!
A217: Rillettes | B217: RR100-290 | C217: 250 | D217: 0 | E217: =IFERROR(D217*INDEX('Prix Vente'!C:C,MATCH(A217&B217,'Prix Vente'!A:A&'Prix Vente'!B:B,0)),"") -> #ERROR!
A218: Rillettes | B218: RR100-370 | C218: 320 | D218: 0 | E218: =IFERROR(D218*INDEX('Prix Vente'!C:C,MATCH(A218&B218,'Prix Vente'!A:A&'Prix Vente'!B:B,0)),"") -> #ERROR!
A219: Rillettes | B219: RR100-580 | C219: 500 | D219: 0 | E219: =IFERROR(D219*INDEX('Prix Vente'!C:C,MATCH(A219&B219,'Prix Vente'!A:A&'Prix Vente'!B:B,0)),"") -> #ERROR!
... A261: Soupes | B261: W60-160 | C261: 130 | D261: 0 | E261: =IFERROR(D261*INDEX('Prix Vente'!C:C,MATCH(A261&B261,'Prix Vente'!A:A&'Prix Vente'!B:B,0)),"") -> #ERROR!

Sheet Fiche Lot
A1: MAISON 41 — FICHE LOT & TRACABILITE — HACCP obligatoire
A2: N Lot
A3: N° Lot : format LOT-AAAAMMJJ-XXX · Numero UNIQUE sur toute la vie de l'entreprise
L4: =IF(B4="","",B4+IFERROR(INDEX(Config!B:B,MATCH("DDM appertisation standard (mois)",Config!A:A,0)),36)*30) -> #ERROR! | R4: =IFERROR(IF(A4="","",COUNTIF(Ventes!B5:B504,A4)),"") -> #ERROR!
L5: =IF(B5="","",B5+IFERROR(INDEX(Config!B:B,MATCH("DDM appertisation standard (mois)",Config!A:A,0)),36)*30) -> #ERROR! | R5: =IFERROR(IF(A5="","",COUNTIF(Ventes!B5:B504,A5)),"") -> #ERROR!
L6: =IF(B6="","",B6+IFERROR(INDEX(Config!B:B,MATCH("DDM appertisation standard (mois)",Config!A:A,0)),36)*30) -> #ERROR! | R6: =IFERROR(IF(A6="","",COUNTIF(Ventes!B5:B504,A6)),"") -> #ERROR!
L7: =IF(B7="","",B7+IFERROR(INDEX(Config!B:B,MATCH("DDM appertisation standard (mois)",Config!A:A,0)),36)*30) -> #ERROR! | R7: =IFERROR(IF(A7="","",COUNTIF(Ventes!B5:B504,A7)),"") -> #ERROR!
L8: =IF(B8="","",B8+IFERROR(INDEX(Config!B:B,MATCH("DDM appertisation standard (mois)",Config!A:A,0)),36)*30) -> #ERROR! | R8: =IFERROR(IF(A8="","",COUNTIF(Ventes!B5:B504,A8)),"") -> #ERROR!
L9: =IF(B9="","",B9+IFERROR(INDEX(Config!B:B,MATCH("DDM appertisation standard (mois)",Config!A:A,0)),36)*30) -> #ERROR! | R9: =IFERROR(IF(A9="","",COUNTIF(Ventes!B5:B504,A9)),"") -> #ERROR!
L10: =IF(B10="","",B10+IFERROR(INDEX(Config!B:B,MATCH("DDM appertisation standard (mois)",Config!A:A,0)),36)*30) -> #ERROR! | R10: =IFERROR(IF(A10="","",COUNTIF(Ventes!B5:B504,A10)),"") -> #ERROR!
L11: =IF(B11="","",B11+IFERROR(INDEX(Config!B:B,MATCH("DDM appertisation standard (mois)",Config!A:A,0)),36)*30) -> #ERROR! | R11: =IFERROR(IF(A11="","",COUNTIF(Ventes!B5:B504,A11)),"") -> #ERROR!
L12: =IF(B12="","",B12+IFERROR(INDEX(Config!B:B,MATCH("DDM appertisation standard (mois)",Config!A:A,0)),36)*30) -> #ERROR! | R12: =IFERROR(IF(A12="","",COUNTIF(Ventes!B5:B504,A12)),"") -> #ERROR!
L13: =IF(B13="","",B13+IFERROR(INDEX(Config!B:B,MATCH("DDM appertisation standard (mois)",Config!A:A,0)),36)*30) -> #ERROR! | R13: =IFERROR(IF(A13="","",COUNTIF(Ventes!B5:B504,A13)),"") -> #ERROR!
L14: =IF(B14="","",B14+IFERROR(INDEX(Config!B:B,MATCH("DDM appertisation standard (mois)",Config!A:A,0)),36)*30) -> #ERROR! | R14: =IFERROR(IF(A14="","",COUNTIF(Ventes!B5:B504,A14)),"") -> #ERROR!
L15: =IF(B15="","",B15+IFERROR(INDEX(Config!B:B,MATCH("DDM appertisation standard (mois)",Config!A:A,0)),36)*30) -> #ERROR! | R15: =IFERROR(IF(A15="","",COUNTIF(Ventes!B5:B504,A15)),"") -> #ERROR!
L16: =IF(B16="","",B16+IFERROR(INDEX(Config!B:B,MATCH("DDM appertisation standard (mois)",Config!A:A,0)),36)*30) -> #ERROR! | R16: =IFERROR(IF(A16="","",COUNTIF(Ventes!B5:B504,A16)),"") -> #ERROR!
L17: =IF(B17="","",B17+IFERROR(INDEX(Config!B:B,MATCH("DDM appertisation standard (mois)",Config!A:A,0)),36)*30) -> #ERROR! | R17: =IFERROR(IF(A17="","",COUNTIF(Ventes!B5:B504,A17)),"") -> #ERROR!
L18: =IF(B18="","",B18+IFERROR(INDEX(Config!B:B,MATCH("DDM appertisation standard (mois)",Config!A:A,0)),36)*30) -> #ERROR! | R18: =IFERROR(IF(A18="","",COUNTIF(Ventes!B5:B504,A18)),"") -> #ERROR!
L19: =IF(B19="","",B19+IFERROR(INDEX(Config!B:B,MATCH("DDM appertisation standard (mois)",Config!A:A,0)),36)*30) -> #ERROR! | R19: =IFERROR(IF(A19="","",COUNTIF(Ventes!B5:B504,A19)),"") -> #ERROR!
L20: =IF(B20="","",B20+IFERROR(INDEX(Config!B:B,MATCH("DDM appertisation standard (mois)",Config!A:A,0)),36)*30) -> #ERROR! | R20: =IFERROR(IF(A20="","",COUNTIF(Ventes!B5:B504,A20)),"") -> #ERROR!
L21: =IF(B21="","",B21+IFERROR(INDEX(Config!B:B,MATCH("DDM appertisation standard (mois)",Config!A:A,0)),36)*30) -> #ERROR! | R21: =IFERROR(IF(A21="","",COUNTIF(Ventes!B5:B504,A21)),"") -> #ERROR!
L22: =IF(B22="","",B22+IFERROR(INDEX(Config!B:B,MATCH("DDM appertisation standard (mois)",Config!A:A,0)),36)*30) -> #ERROR! | R22: =IFERROR(IF(A22="","",COUNTIF(Ventes!B5:B504,A22)),"") -> #ERROR!
L23: =IF(B23="","",B23+IFERROR(INDEX(Config!B:B,MATCH("DDM appertisation standard (mois)",Config!A:A,0)),36)*30) -> #ERROR! | R23: =IFERROR(IF(A23="","",COUNTIF(Ventes!B5:B504,A23)),"") -> #ERROR!
L24: =IF(B24="","",B24+IFERROR(INDEX(Config!B:B,MATCH("DDM appertisation standard (mois)",Config!A:A,0)),36)*30) -> #ERROR! | R24: =IFERROR(IF(A24="","",COUNTIF(Ventes!B5:B504,A24)),"") -> #ERROR!
L25: =IF(B25="","",B25+IFERROR(INDEX(Config!B:B,MATCH("DDM appertisation standard (mois)",Config!A:A,0)),36)*30) -> #ERROR! | R25: =IFERROR(IF(A25="","",COUNTIF(Ventes!B5:B504,A25)),"") -> #ERROR!
L26: =IF(B26="","",B26+IFERROR(INDEX(Config!B:B,MATCH("DDM appertisation standard (mois)",Config!A:A,0)),36)*30) -> #ERROR! | R26: =IFERROR(IF(A26="","",COUNTIF(Ventes!B5:B504,A26)),"") -> #ERROR!
L27: =IF(B27="","",B27+IFERROR(INDEX(Config!B:B,MATCH("DDM appertisation standard (mois)",Config!A:A,0)),36)*30) -> #ERROR! | R27: =IFERROR(IF(A27="","",COUNTIF(Ventes!B5:B504,A27)),"") -> #ERROR!
L28: =IF(B28="","",B28+IFERROR(INDEX(Config!B:B,MATCH("DDM appertisation standard (mois)",Config!A:A,0)),36)*30) -> #ERROR! | R28: =IFERROR(IF(A28="","",COUNTIF(Ventes!B5:B504,A28)),"") -> #ERROR!
L29: =IF(B29="","",B29+IFERROR(INDEX(Config!B:B,MATCH("DDM appertisation standard (mois)",Config!A:A,0)),36)*30) -> #ERROR! | R29: =IFERROR(IF(A29="","",COUNTIF(Ventes!B5:B504,A29)),"") -> #ERROR!
L30: =IF(B30="","",B30+IFERROR(INDEX(Config!B:B,MATCH("DDM appertisation standard (mois)",Config!A:A,0)),36)*30) -> #ERROR! | R30: =IFERROR(IF(A30="","",COUNTIF(Ventes!B5:B504,A30)),"") -> #ERROR!
L31: =IF(B31="","",B31+IFERROR(INDEX(Config!B:B,MATCH("DDM appertisation standard (mois)",Config!A:A,0)),36)*30) -> #ERROR! | R31: =IFERROR(IF(A31="","",COUNTIF(Ventes!B5:B504,A31)),"") -> #ERROR!
L32: =IF(B32="","",B32+IFERROR(INDEX(Config!B:B,MATCH("DDM appertisation standard (mois)",Config!A:A,0)),36)*30) -> #ERROR! | R32: =IFERROR(IF(A32="","",COUNTIF(Ventes!B5:B504,A32)),"") -> #ERROR!
L33: =IF(B33="","",B33+IFERROR(INDEX(Config!B:B,MATCH("DDM appertisation standard (mois)",Config!A:A,0)),36)*30) -> #ERROR! | R33: =IFERROR(IF(A33="","",COUNTIF(Ventes!B5:B504,A33)),"") -> #ERROR!
L34: =IF(B34="","",B34+IFERROR(INDEX(Config!B:B,MATCH("DDM appertisation standard (mois)",Config!A:A,0)),36)*30) -> #ERROR! | R34: =IFERROR(IF(A34="","",COUNTIF(Ventes!B5:B504,A34)),"") -> #ERROR!
L35: =IF(B35="","",B35+IFERROR(INDEX(Config!B:B,MATCH("DDM appertisation standard (mois)",Config!A:A,0)),36)*30) -> #ERROR! | R35: =IFERROR(IF(A35="","",COUNTIF(Ventes!B5:B504,A35)),"") -> #ERROR!
L36: =IF(B36="","",B36+IFERROR(INDEX(Config!B:B,MATCH("DDM appertisation standard (mois)",Config!A:A,0)),36)*30) -> #ERROR! | R36: =IFERROR(IF(A36="","",COUNTIF(Ventes!B5:B504,A36)),"") -> #ERROR!
L37: =IF(B37="","",B37+IFERROR(INDEX(Config!B:B,MATCH("DDM appertisation standard (mois)",Config!A:A,0)),36)*30) -> #ERROR! | R37: =IFERROR(IF(A37="","",COUNTIF(Ventes!B5:B504,A37)),"") -> #ERROR!
L38: =IF(B38="","",B38+IFERROR(INDEX(Config!B:B,MATCH("DDM appertisation standard (mois)",Config!A:A,0)),36)*30) -> #ERROR! | R38: =IFERROR(IF(A38="","",COUNTIF(Ventes!B5:B504,A38)),"") -> #ERROR!
L39: =IF(B39="","",B39+IFERROR(INDEX(Config!B:B,MATCH("DDM appertisation standard (mois)",Config!A:A,0)),36)*30) -> #ERROR! | R39: =IFERROR(IF(A39="","",COUNTIF(Ventes!B5:B504,A39)),"") -> #ERROR!
L40: =IF(B40="","",B40+IFERROR(INDEX(Config!B:B,MATCH("DDM appertisation standard (mois)",Config!A:A,0)),36)*30) -> #ERROR! | R40: =IFERROR(IF(A40="","",COUNTIF(Ventes!B5:B504,A40)),"") -> #ERROR!
L41: =IF(B41="","",B41+IFERROR(INDEX(Config!B:B,MATCH("DDM appertisation standard (mois)",Config!A:A,0)),36)*30) -> #ERROR! | R41: =IFERROR(IF(A41="","",COUNTIF(Ventes!B5:B504,A41)),"") -> #ERROR!
L42: =IF(B42="","",B42+IFERROR(INDEX(Config!B:B,MATCH("DDM appertisation standard (mois)",Config!A:A,0)),36)*30) -> #ERROR! | R42: =IFERROR(IF(A42="","",COUNTIF(Ventes!B5:B504,A42)),"") -> #ERROR!
L43: =IF(B43="","",B43+IFERROR(INDEX(Config!B:B,MATCH("DDM appertisation standard (mois)",Config!A:A,0)),36)*30) -> #ERROR! | R43: =IFERROR(IF(A43="","",COUNTIF(Ventes!B5:B504,A43)),"") -> #ERROR!
L44: =IF(B44="","",B44+IFERROR(INDEX(Config!B:B,MATCH("DDM appertisation standard (mois)",Config!A:A,0)),36)*30) -> #ERROR! | R44: =IFERROR(IF(A44="","",COUNTIF(Ventes!B5:B504,A44)),"") -> #ERROR!
L45: =IF(B45="","",B45+IFERROR(INDEX(Config!B:B,MATCH("DDM appertisation standard (mois)",Config!A:A,0)),36)*30) -> #ERROR! | R45: =IFERROR(IF(A45="","",COUNTIF(Ventes!B5:B504,A45)),"") -> #ERROR!
L46: =IF(B46="","",B46+IFERROR(INDEX(Config!B:B,MATCH("DDM appertisation standard (mois)",Config!A:A,0)),36)*30) -> #ERROR! | R46: =IFERROR(IF(A46="","",COUNTIF(Ventes!B5:B504,A46)),"") -> #ERROR!
L47: =IF(B47="","",B47+IFERROR(INDEX(Config!B:B,MATCH("DDM appertisation standard (mois)",Config!A:A,0)),36)*30) -> #ERROR! | R47: =IFERROR(IF(A47="","",COUNTIF(Ventes!B5:B504,A47)),"") -> #ERROR!
L48: =IF(B48="","",B48+IFERROR(INDEX(Config!B:B,MATCH("DDM appertisation standard (mois)",Config!A:A,0)),36)*30) -> #ERROR! | R48: =IFERROR(IF(A48="","",COUNTIF(Ventes!B5:B504,A48)),"") -> #ERROR!
L49: =IF(B49="","",B49+IFERROR(INDEX(Config!B:B,MATCH("DDM appertisation standard (mois)",Config!A:A,0)),36)*30) -> #ERROR! | R49: =IFERROR(IF(A49="","",COUNTIF(Ventes!B5:B504,A49)),"") -> #ERROR!
L50: =IF(B50="","",B50+IFERROR(INDEX(Config!B:B,MATCH("DDM appertisation standard (mois)",Config!A:A,0)),36)*30) -> #ERROR! | R50: =IFERROR(IF(A50="","",COUNTIF(Ventes!B5:B504,A50)),"") -> #ERROR!
L51: =IF(B51="","",B51+IFERROR(INDEX(Config!B:B,MATCH("DDM appertisation standard (mois)",Config!A:A,0)),36)*30) -> #ERROR! | R51: =IFERROR(IF(A51="","",COUNTIF(Ventes!B5:B504,A51)),"") -> #ERROR!
L52: =IF(B52="","",B52+IFERROR(INDEX(Config!B:B,MATCH("DDM appertisation standard (mois)",Config!A:A,0)),36)*30) -> #ERROR! | R52: =IFERROR(IF(A52="","",COUNTIF(Ventes!B5:B504,A52)),"") -> #ERROR!
L53: =IF(B53="","",B53+IFERROR(INDEX(Config!B:B,MATCH("DDM appertisation standard (mois)",Config!A:A,0)),36)*30) -> #ERROR! | R53: =IFERROR(IF(A53="","",COUNTIF(Ventes!B5:B504,A53)),"") -> #ERROR!
L54: =IF(B54="","",B54+IFERROR(INDEX(Config!B:B,MATCH("DDM appertisation standard (mois)",Config!A:A,0)),36)*30) -> #ERROR! | R54: =IFERROR(IF(A54="","",COUNTIF(Ventes!B5:B504,A54)),"") -> #ERROR!
L55: =IF(B55="","",B55+IFERROR(INDEX(Config!B:B,MATCH("DDM appertisation standard (mois)",Config!A:A,0)),36)*30) -> #ERROR! | R55: =IFERROR(IF(A55="","",COUNTIF(Ventes!B5:B504,A55)),"") -> #ERROR!
L56: =IF(B56="","",B56+IFERROR(INDEX(Config!B:B,MATCH("DDM appertisation standard (mois)",Config!A:A,0)),36)*30) -> #ERROR! | R56: =IFERROR(IF(A56="","",COUNTIF(Ventes!B5:B504,A56)),"") -> #ERROR!
L57: =IF(B57="","",B57+IFERROR(INDEX(Config!B:B,MATCH("DDM appertisation standard (mois)",Config!A:A,0)),36)*30) -> #ERROR! | R57: =IFERROR(IF(A57="","",COUNTIF(Ventes!B5:B504,A57)),"") -> #ERROR!
L58: =IF(B58="","",B58+IFERROR(INDEX(Config!B:B,MATCH("DDM appertisation standard (mois)",Config!A:A,0)),36)*30) -> #ERROR! | R58: =IFERROR(IF(A58="","",COUNTIF(Ventes!B5:B504,A58)),"") -> #ERROR!
L59: =IF(B59="","",B59+IFERROR(INDEX(Config!B:B,MATCH("DDM appertisation standard (mois)",Config!A:A,0)),36)*30) -> #ERROR! | R59: =IFERROR(IF(A59="","",COUNTIF(Ventes!B5:B504,A59)),"") -> #ERROR!
L60: =IF(B60="","",B60+IFERROR(INDEX(Config!B:B,MATCH("DDM appertisation standard (mois)",Config!A:A,0)),36)*30) -> #ERROR! | R60: =IFERROR(IF(A60="","",COUNTIF(Ventes!B5:B504,A60)),"") -> #ERROR!
L61: =IF(B61="","",B61+IFERROR(INDEX(Config!B:B,MATCH("DDM appertisation standard (mois)",Config!A:A,0)),36)*30) -> #ERROR! | R61: =IFERROR(IF(A61="","",COUNTIF(Ventes!B5:B504,A61)),"") -> #ERROR!
L62: =IF(B62="","",B62+IFERROR(INDEX(Config!B:B,MATCH("DDM appertisation standard (mois)",Config!A:A,0)),36)*30) -> #ERROR! | R62: =IFERROR(IF(A62="","",COUNTIF(Ventes!B5:B504,A62)),"") -> #ERROR!
L63: =IF(B63="","",B63+IFERROR(INDEX(Config!B:B,MATCH("DDM appertisation standard (mois)",Config!A:A,0)),36)*30) -> #ERROR! | R63: =IFERROR(IF(A63="","",COUNTIF(Ventes!B5:B504,A63)),"") -> #ERROR!
L64: =IF(B64="","",B64+IFERROR(INDEX(Config!B:B,MATCH("DDM appertisation standard (mois)",Config!A:A,0)),36)*30) -> #ERROR! | R64: =IFERROR(IF(A64="","",COUNTIF(Ventes!B5:B504,A64)),"") -> #ERROR!
L65: =IF(B65="","",B65+IFERROR(INDEX(Config!B:B,MATCH("DDM appertisation standard (mois)",Config!A:A,0)),36)*30) -> #ERROR! | R65: =IFERROR(IF(A65="","",COUNTIF(Ventes!B5:B504,A65)),"") -> #ERROR!
L66: =IF(B66="","",B66+IFERROR(INDEX(Config!B:B,MATCH("DDM appertisation standard (mois)",Config!A:A,0)),36)*30) -> #ERROR! | R66: =IFERROR(IF(A66="","",COUNTIF(Ventes!B5:B504,A66)),"") -> #ERROR!
L67: =IF(B67="","",B67+IFERROR(INDEX(Config!B:B,MATCH("DDM appertisation standard (mois)",Config!A:A,0)),36)*30) -> #ERROR! | R67: =IFERROR(IF(A67="","",COUNTIF(Ventes!B5:B504,A67)),"") -> #ERROR!
L68: =IF(B68="","",B68+IFERROR(INDEX(Config!B:B,MATCH("DDM appertisation standard (mois)",Config!A:A,0)),36)*30) -> #ERROR! | R68: =IFERROR(IF(A68="","",COUNTIF(Ventes!B5:B504,A68)),"") -> #ERROR!
L69: =IF(B69="","",B69+IFERROR(INDEX(Config!B:B,MATCH("DDM appertisation standard (mois)",Config!A:A,0)),36)*30) -> #ERROR! | R69: =IFERROR(IF(A69="","",COUNTIF(Ventes!B5:B504,A69)),"") -> #ERROR!
L70: =IF(B70="","",B70+IFERROR(INDEX(Config!B:B,MATCH("DDM appertisation standard (mois)",Config!A:A,0)),36)*30) -> #ERROR! | R70: =IFERROR(IF(A70="","",COUNTIF(Ventes!B5:B504,A70)),"") -> #ERROR!
L71: =IF(B71="","",B71+IFERROR(INDEX(Config!B:B,MATCH("DDM appertisation standard (mois)",Config!A:A,0)),36)*30) -> #ERROR! | R71: =IFERROR(IF(A71="","",COUNTIF(Ventes!B5:B504,A71)),"") -> #ERROR!
L72: =IF(B72="","",B72+IFERROR(INDEX(Config!B:B,MATCH("DDM appertisation standard (mois)",Config!A:A,0)),36)*30) -> #ERROR! | R72: =IFERROR(IF(A72="","",COUNTIF(Ventes!B5:B504,A72)),"") -> #ERROR!
L73: =IF(B73="","",B73+IFERROR(INDEX(Config!B:B,MATCH("DDM appertisation standard (mois)",Config!A:A,0)),36)*30) -> #ERROR! | R73: =IFERROR(IF(A73="","",COUNTIF(Ventes!B5:B504,A73)),"") -> #ERROR!
L74: =IF(B74="","",B74+IFERROR(INDEX(Config!B:B,MATCH("DDM appertisation standard (mois)",Config!A:A,0)),36)*30) -> #ERROR! | R74: =IFERROR(IF(A74="","",COUNTIF(Ventes!B5:B504,A74)),"") -> #ERROR!
L75: =IF(B75="","",B75+IFERROR(INDEX(Config!B:B,MATCH("DDM appertisation standard (mois)",Config!A:A,0)),36)*30) -> #ERROR! | R75: =IFERROR(IF(A75="","",COUNTIF(Ventes!B5:B504,A75)),"") -> #ERROR!
L76: =IF(B76="","",B76+IFERROR(INDEX(Config!B:B,MATCH("DDM appertisation standard (mois)",Config!A:A,0)),36)*30) -> #ERROR! | R76: =IFERROR(IF(A76="","",COUNTIF(Ventes!B5:B504,A76)),"") -> #ERROR!
L77: =IF(B77="","",B77+IFERROR(INDEX(Config!B:B,MATCH("DDM appertisation standard (mois)",Config!A:A,0)),36)*30) -> #ERROR! | R77: =IFERROR(IF(A77="","",COUNTIF(Ventes!B5:B504,A77)),"") -> #ERROR!
L78: =IF(B78="","",B78+IFERROR(INDEX(Config!B:B,MATCH("DDM appertisation standard (mois)",Config!A:A,0)),36)*30) -> #ERROR! | R78: =IFERROR(IF(A78="","",COUNTIF(Ventes!B5:B504,A78)),"") -> #ERROR!
L79: =IF(B79="","",B79+IFERROR(INDEX(Config!B:B,MATCH("DDM appertisation standard (mois)",Config!A:A,0)),36)*30) -> #ERROR! | R79: =IFERROR(IF(A79="","",COUNTIF(Ventes!B5:B504,A79)),"") -> #ERROR!
L80: =IF(B80="","",B80+IFERROR(INDEX(Config!B:B,MATCH("DDM appertisation standard (mois)",Config!A:A,0)),36)*30) -> #ERROR! | R80: =IFERROR(IF(A80="","",COUNTIF(Ventes!B5:B504,A80)),"") -> #ERROR!
L81: =IF(B81="","",B81+IFERROR(INDEX(Config!B:B,MATCH("DDM appertisation standard (mois)",Config!A:A,0)),36)*30) -> #ERROR! | R81: =IFERROR(IF(A81="","",COUNTIF(Ventes!B5:B504,A81)),"") -> #ERROR!
L82: =IF(B82="","",B82+IFERROR(INDEX(Config!B:B,MATCH("DDM appertisation standard (mois)",Config!A:A,0)),36)*30) -> #ERROR! | R82: =IFERROR(IF(A82="","",COUNTIF(Ventes!B5:B504,A82)),"") -> #ERROR!
L83: =IF(B83="","",B83+IFERROR(INDEX(Config!B:B,MATCH("DDM appertisation standard (mois)",Config!A:A,0)),36)*30) -> #ERROR! | R83: =IFERROR(IF(A83="","",COUNTIF(Ventes!B5:B504,A83)),"") -> #ERROR!
L84: =IF(B84="","",B84+IFERROR(INDEX(Config!B:B,MATCH("DDM appertisation standard (mois)",Config!A:A,0)),36)*30) -> #ERROR! | R84: =IFERROR(IF(A84="","",COUNTIF(Ventes!B5:B504,A84)),"") -> #ERROR!
L85: =IF(B85="","",B85+IFERROR(INDEX(Config!B:B,MATCH("DDM appertisation standard (mois)",Config!A:A,0)),36)*30) -> #ERROR! | R85: =IFERROR(IF(A85="","",COUNTIF(Ventes!B5:B504,A85)),"") -> #ERROR!
L86: =IF(B86="","",B86+IFERROR(INDEX(Config!B:B,MATCH("DDM appertisation standard (mois)",Config!A:A,0)),36)*30) -> #ERROR! | R86: =IFERROR(IF(A86="","",COUNTIF(Ventes!B5:B504,A86)),"") -> #ERROR!
L87: =IF(B87="","",B87+IFERROR(INDEX(Config!B:B,MATCH("DDM appertisation standard (mois)",Config!A:A,0)),36)*30) -> #ERROR! | R87: =IFERROR(IF(A87="","",COUNTIF(Ventes!B5:B504,A87)),"") -> #ERROR!
L88: =IF(B88="","",B88+IFERROR(INDEX(Config!B:B,MATCH("DDM appertisation standard (mois)",Config!A:A,0)),36)*30) -> #ERROR! | R88: =IFERROR(IF(A88="","",COUNTIF(Ventes!B5:B504,A88)),"") -> #ERROR!
L89: =IF(B89="","",B89+IFERROR(INDEX(Config!B:B,MATCH("DDM appertisation standard (mois)",Config!A:A,0)),36)*30) -> #ERROR! | R89: =IFERROR(IF(A89="","",COUNTIF(Ventes!B5:B504,A89)),"") -> #ERROR!
L90: =IF(B90="","",B90+IFERROR(INDEX(Config!B:B,MATCH("DDM appertisation standard (mois)",Config!A:A,0)),36)*30) -> #ERROR! | R90: =IFERROR(IF(A90="","",COUNTIF(Ventes!B5:B504,A90)),"") -> #ERROR!
L91: =IF(B91="","",B91+IFERROR(INDEX(Config!B:B,MATCH("DDM appertisation standard (mois)",Config!A:A,0)),36)*30) -> #ERROR! | R91: =IFERROR(IF(A91="","",COUNTIF(Ventes!B5:B504,A91)),"") -> #ERROR!
L92: =IF(B92="","",B92+IFERROR(INDEX(Config!B:B,MATCH("DDM appertisation standard (mois)",Config!A:A,0)),36)*30) -> #ERROR! | R92: =IFERROR(IF(A92="","",COUNTIF(Ventes!B5:B504,A92)),"") -> #ERROR!
L93: =IF(B93="","",B93+IFERROR(INDEX(Config!B:B,MATCH("DDM appertisation standard (mois)",Config!A:A,0)),36)*30) -> #ERROR! | R93: =IFERROR(IF(A93="","",COUNTIF(Ventes!B5:B504,A93)),"") -> #ERROR!
L94: =IF(B94="","",B94+IFERROR(INDEX(Config!B:B,MATCH("DDM appertisation standard (mois)",Config!A:A,0)),36)*30) -> #ERROR! | R94: =IFERROR(IF(A94="","",COUNTIF(Ventes!B5:B504,A94)),"") -> #ERROR!
L95: =IF(B95="","",B95+IFERROR(INDEX(Config!B:B,MATCH("DDM appertisation standard (mois)",Config!A:A,0)),36)*30) -> #ERROR! | R95: =IFERROR(IF(A95="","",COUNTIF(Ventes!B5:B504,A95)),"") -> #ERROR!
L96: =IF(B96="","",B96+IFERROR(INDEX(Config!B:B,MATCH("DDM appertisation standard (mois)",Config!A:A,0)),36)*30) -> #ERROR! | R96: =IFERROR(IF(A96="","",COUNTIF(Ventes!B5:B504,A96)),"") -> #ERROR!
L97: =IF(B97="","",B97+IFERROR(INDEX(Config!B:B,MATCH("DDM appertisation standard (mois)",Config!A:A,0)),36)*30) -> #ERROR! | R97: =IFERROR(IF(A97="","",COUNTIF(Ventes!B5:B504,A97)),"") -> #ERROR!
L98: =IF(B98="","",B98+IFERROR(INDEX(Config!B:B,MATCH("DDM appertisation standard (mois)",Config!A:A,0)),36)*30) -> #ERROR! | R98: =IFERROR(IF(A98="","",COUNTIF(Ventes!B5:B504,A98)),"") -> #ERROR!
L99: =IF(B99="","",B99+IFERROR(INDEX(Config!B:B,MATCH("DDM appertisation standard (mois)",Config!A:A,0)),36)*30) -> #ERROR! | R99: =IFERROR(IF(A99="","",COUNTIF(Ventes!B5:B504,A99)),"") -> #ERROR!
L100: =IF(B100="","",B100+IFERROR(INDEX(Config!B:B,MATCH("DDM appertisation standard (mois)",Config!A:A,0)),36)*30) -> #ERROR! | R100: =IFERROR(IF(A100="","",COUNTIF(Ventes!B5:B504,A100)),"") -> #ERROR!
...

Sheet Historique Lots
A1: MAISON 41 — HISTORIQUE COMPLET DES LOTS — Alimente depuis Fiche Lot
A2: Saisir le N° Lot col A → tout se remplit automatiquement depuis Fiche Lot
A3: Saisir uniquement le N° Lot (col A) — Recette, Format, Bocaux, DDM se remplissent automatiquement
A4: N Lot | B4: Date | C4: Recette | D4: Gamme | E4: Format | F4: Autoclave | G4: Bocaux prod. | H4: Bocaux vendus | I4: Pertes | J4: Taux rempl. | K4: CA reel EUR | L4: Cout theo. | M4: Cout reel | N4: Marge EUR | O4: Marge % | P4: T serie | Q4: DDM | R4: Statut | S4: Operateur | T4: Duree (min) | U4: Notes
A5: LOT-20260401-001 | B5: =IFERROR(INDEX('Fiche Lot'!B:B,MATCH(A5,'Fiche Lot'!A:A,0)),"") -> #ERROR! | C5: =IFERROR(INDEX('Fiche Lot'!C:C,MATCH(A5,'Fiche Lot'!A:A,0)),"") -> #ERROR! | D5: =IFERROR(INDEX('Fiche Lot'!D:D,MATCH(A5,'Fiche Lot'!A:A,0)),"") -> #ERROR! | E5: =IFERROR(INDEX('Fiche Lot'!E:E,MATCH(A5,'Fiche Lot'!A:A,0)),"") -> #ERROR! | G5: =IFERROR(INDEX('Fiche Lot'!H:H,MATCH(A5,'Fiche Lot'!A:A,0)),"") -> #ERROR! | J5: =IFERROR(H5/G5,"") -> #ERROR! | N5: =IFERROR(K5-M5,"") -> #ERROR! | O5: =IFERROR(N5/K5,"") -> #ERROR! | P5: =IFERROR(INDEX('Fiche Lot'!J:J,MATCH(A5,'Fiche Lot'!A:A,0)),"") -> #ERROR! | Q5: =IFERROR(INDEX('Fiche Lot'!L:L,MATCH(A5,'Fiche Lot'!A:A,0)),"") -> #ERROR! | R5: =IFERROR(INDEX('Fiche Lot'!M:M,MATCH(A5,'Fiche Lot'!A:A,0)),"") -> #ERROR! | S5: =IFERROR(INDEX('Fiche Lot'!G:G,MATCH(A5,'Fiche Lot'!A:A,0)),"") -> #ERROR!
